Workbook

Sheet Auditoria_Respostas
A1: Carimbo de data/hora | B1: ID_Auditoria | C1: Viagem | D1: ID_Viagem | E1: ID_Relatorio | F1: IDTecnico | G1: Motivo | H1: Tecnico_Auditado | I1: Data_Auditoria | J1: ExecucaoTecnica | K1: InfraestruturaeSistemas | L1: PosturaeDocumentacao | M1: Nota_Causa_Raiz | N1: Nota_Uso_Pecas | O1: Nota_Dominio_Ferramentas | P1: Nota_Acabamento | Q1: Nota_Zelo_Patrimonio | R1: Nota_Cabeamento | S1: Nota_Rack | T1: Nota_Internet | U1: Nota_Software | V1: Nota_Rede_Logica | W1: Nota_Cordialidade | X1: Nota_Resiliencia | Y1: Nota_Fotos | Z1: Check_EPI_Uniforme | AA1: Check_Preenchimento | AB1: Check_Roteiro | AC1: Parecer_Lider | AD1: Endereço de e-mail
A2: 46099.707 | F2: Barclay de Medeiros Normando | H2: Nielson Alexandre de Almeida Dantas | I2: 46099 | M2: 3 | Q2: 4 | U2: 3 | W2: 4 | X2: 4 | Y2: 4 | Z2: 5 | AA2: 4 | AB2: 4 | AD2: barclaymedeiros@gmail.com
A3: 46099.708 | F3: Barclay de Medeiros Normando | H3: Joana Darc Marques Do Nascimento | I3: 46099 | Q3: 4 | U3: 4 | V3: 4 | W3: 4 | X3: 5 | Y3: 1 | Z3: 5 | AB3: 5 | AC3: Não tirou fotos e nem fez vídeos, mesmo eu pedindo. | AD3: barclaymedeiros@gmail.com
A4: 46101.498 | F4: Nielson Alexandre de Almeida Dantas | H4: Barclay de Medeiros Normando | I4: 46101 | M4: 5 | Q4: 5 | U4: 5 | W4: 5 | X4: 5 | Z4: 5 | AB4: 5 | AD4: nielson1903@gmail.com
A5: 46101.502 | F5: Nielson Alexandre de Almeida Dantas | H5: Joana Darc Marques Do Nascimento | I5: 46101 | M5: 5 | Q5: 5 | W5: 4 | X5: 4 | Z5: 5 | AB5: 5 | AD5: nielson1903@gmail.com
A6: 46104.871 | F6: Joana Darc Marques Do Nascimento | H6: Barclay de Medeiros Normando | I6: 46101 | M6: 5 | N6: 1 | O6: 5 | P6: 1 | Q6: 5 | U6: 5 | W6: 5 | X6: 5 | Y6: 5 | AA6: 5 | AB6: 5 | AD6: joana.nascimento@see.pb.gov.br
A7: 46104.873 | F7: Joana Darc Marques Do Nascimento | H7: Nielson Alexandre de Almeida Dantas | I7: 46101 | M7: 5 | O7: 5 | Q7: 5 | U7: 5 | W7: 5 | X7: 5 | Y7: 5 | AA7: 5 | AB7: 5 | AD7: joana.nascimento@see.pb.gov.br

Sheet Escolas
A1: Inep | B1: Escola | C1: Regional | D1: Endereco | E1: EnderecoGPS | F1: Município | G1: UF
A2: 25000047 | B2: ECI NOSSA SENHORA DA CONCEICAO | C2: 08ª GRE (Catolé do Rocha) | D2: RUA JOAO BATISTA DE OLIVEIRA FORTE, 411 CASA. CENTRO. 58895-000 Belém do Brejo do Cruz - PB. | F2: Belém do Brejo do Cruz | G2: PB
A3: 25000055 | B3: EEEFM AMERICO MAIA | C3: 08ª GRE (Catolé do Rocha) | D3: RUA JOAO AGRIPINO, 331 PREDIO. CENTRO. 58895-000 Belém do Brejo do Cruz - PB. | F3: Belém do Brejo do Cruz | G3: PB
A4: 25000349 | B4: ECIT PADRE ARISTIDES | C4: 08ª GRE (Catolé do Rocha) | D4: RUA FRANCISCO GONCALVES DE ALMEIDA, SN CENTRO. 58887-000 Bom Sucesso - PB. | F4: Bom Sucesso | G4: PB
A5: 25000373 | B5: EEEM DOUTOR JOSE PAZ DE LIMA | C5: 08ª GRE (Catolé do Rocha) | D5: RUA ANTONIO ALMINO, 17 CENTRO. 58887-000 Bom Sucesso - PB. | F5: Bom Sucesso | G5: PB
A6: 25000640 | B6: ECIT PROFESSOR JOSE OLIMPIO MAIA | C6: 08ª GRE (Catolé do Rocha) | D6: RUA HORACIO PIMENTA, 225 PREDIO ESCOLAR. CENTRO. 58890-000 Brejo do Cruz - PB. | F6: Brejo do Cruz | G6: PB
A7: 25000659 | B7: EEEM ANTONIO GOMES | C7: 08ª GRE (Catolé do Rocha) | D7: RUA ANGELINA MARIZ, 50 CENTRO. 58890-000 Brejo do Cruz - PB. | F7: Brejo do Cruz | G7: PB
A8: 25001302 | B8: ECI EM OLIVIA SARAIVA MAIA | C8: 08ª GRE (Catolé do Rocha) | D8: RUA CONEGO SANDOVAL, 124 CENTRO. 58893-000 São José do Brejo do Cruz - PB. | F8: São José do Brejo do Cruz | G8: PB
A9: 25001477 | B9: ECI PROFESSORA DIVA GUEDES DE ARAUJO | C9: 08ª GRE (Catolé do Rocha) | D9: RUA APOLONIO PEREIRA DE SOUSA, 150 CENTRO. 58880-000 Brejo dos Santos - PB. | F9: Brejo dos Santos | G9: PB
A10: 25001825 | B10: EEEM ESC AGROTECNICA DO CAJUEIRO CAMPUS IV - UEPB | C10: 08ª GRE (Catolé do Rocha) | D10: SITIO CAJUEIRO, SN ESCOLA. 58884-000 Catolé do Rocha - PB. | F10: Catolé do Rocha | G10: PB
A11: 25001833 | B11: ECIT OBDULIA DANTAS | C11: 08ª GRE (Catolé do Rocha) | D11: AVENIDA VENANCIO NEIVA, 804 EM FRENTE AO PARQUE. CENTRO. 58884-000 Catolé do Rocha - PB. | F11: Catolé do Rocha | G11: PB
A12: 25001868 | B12: EEEF JOAQUIM VALDEVINO DE LIMA | C12: 08ª GRE (Catolé do Rocha) | D12: SITIO CAJAZEIRINHA, SN SITIO. ZONA RURAL. 58884-000 Catolé do Rocha - PB. | F12: Catolé do Rocha | G12: PB
A13: 25001876 | B13: EEEF JOSE DE SA CAVALCANTE | C13: 08ª GRE (Catolé do Rocha) | D13: SITIO CATOLE DE BAIXO, SN AO LADO DO PSF. ZONA RURAL. 58884-000 Catolé do Rocha - PB. | F13: Catolé do Rocha | G13: PB
... A18: 25002457 | B18: ECI JOSE SERAFIM DE LIMA | C18: 08ª GRE (Catolé do Rocha) | D18: RUA ANTONIO SERAFIM DE LIMA, 16 CENTRO. 58832-000 Mato Grosso - PB. | F18: Mato Grosso | G18: PB
A19: 25003011 | B19: EEEF VARZEA DOS CALADOS | D19: SITIO VARZEA DOS CALADOS, 58835-000 Lagoa - PB. | F19: Lagoa | G19: PB
A20: 25003038 | B20: EEEFM MONSENHOR VALERIANO PEREIRA | C20: 13ª GRE (Pombal) | D20: TRAVESSA SIMPLICIO ROQUE, 02 PREDIO ESCOLAR. CENTRO. 58835-000 Lagoa - PB. | F20: Lagoa | G20: PB
A21: 25003054 | B21: ECI FREI BRUNO | C21: 13ª GRE (Pombal) | D21: RUA PADRE ARISTIDES, 0 CENTRO. 58835-000 Lagoa - PB. | F21: Lagoa | G21: PB
A22: 25003410 | B22: ECIT DANIEL CARNEIRO | C22: 08ª GRE (Catolé do Rocha) | D22: RUA DR ANTONIO CARNEIRO, 60 PREDIO. CENTRO. 58870-000 Riacho dos Cavalos - PB. | F22: Riacho dos Cavalos | G22: PB
A23: 25003844 | B23: EEEM JOAO SILVEIRA GUIMARAES | C23: 08ª GRE (Catolé do Rocha) | D23: RUA SAO JUDAS TADEU, 53 PREDIO. SAO JOSE. 58865-000 São Bento - PB. | F23: São Bento | G23: PB
A24: 25003852 | B24: EEEIF FAUSTO MEIRA | C24: 08ª GRE (Catolé do Rocha) | D24: RUA DR JOAO AGREPINO, 232 CENTRO. 58865-000 São Bento - PB. | F24: São Bento | G24: PB
A25: 25004875 | B25: EEEFM MINISTRO JOSE AMERICO DE ALMEIDA | C25: 09ª GRE (Cajazeiras) | D25: RUA VIDAL DE NEGREIROS, 134 CENTRO. 58910-000 São João do Rio do Peixe - PB. | F25: São João do Rio do Peixe | G25: PB
A26: 25004883 | B26: ECIT CORONEL JACOB GUILHERME FRANTZ | C26: 09ª GRE (Cajazeiras) | D26: RUA PADRE JOAQUIM CIRILO DE SA, 95 CENTRO. 58910-000 São João do Rio do Peixe - PB. | F26: São João do Rio do Peixe | G26: PB
A27: 25004948 | B27: EEEIEF DISTRITO DE UMARI | C27: 09ª GRE (Cajazeiras) | D27: DISTRITO DE UMARI, S/N ZONA RURAL. 58910-000 São João do Rio do Peixe - PB. | F27: São João do Rio do Peixe | G27: PB
A28: 25004999 | B28: EEEM DE BANDARRA | D28: DISTRITO DE BANDARRA, 0 ZONA RURAL. 58910-000 São João do Rio do Peixe - PB. | F28: São João do Rio do Peixe | G28: PB
A29: 25005995 | B29: ECIT PROFESSORA FRANCISCA FONSECA MATIAS | C29: 09ª GRE (Cajazeiras) | D29: AV FREI DAMIAO, 00 PROXIMO AO PORTAL DE. BAIRRO DAS POPULARES. 58908-000 Poço de José de Moura - PB. | F29: Poço de José de Moura | G29: PB
A30: 25006029 | B30: ECI PROFESSOR JOAQUIM UMBELINO | C30: 09ª GRE (Cajazeiras) | D30: RUA 05 DE NOVEMBRO, 1 ASA BRANCA. 58930-000 Bom Jesus - PB. | F30: Bom Jesus | G30: PB
A31: 25006223 | B31: ECIT MONSENHOR MORAIS | C31: 09ª GRE (Cajazeiras) | D31: RUA APRIGIO PEREIRA DA SILVA, 1 PREDIO. ALTO DA BOA VISTA. 58960-000 Bonito de Santa Fé - PB. | F31: Bonito de Santa Fé | G31: PB
A32: 25006231 | B32: EEEFM JOAQUIM NABUCO | D32: RUA PREFEITO JOSE FERREIRA CAJU, 204 PREDIO. CENTRO. 58960-000 Bonito de Santa Fé - PB. | F32: Bonito de Santa Fé | G32: PB
A33: 25007092 | B33: ECI PROFESSOR ADALBERTO DE SOUSA OLIVEIRA | C33: 09ª GRE (Cajazeiras) | D33: RUA SERGIO MOREIRA, 45 PREDIO ESCOLAR. CENTRO. 58935-000 Cachoeira dos Índios - PB. | F33: Cachoeira dos Índios | G33: PB
A34: 25007718 | B34: EEEFM PROFESSOR MANOEL MANGUEIRA LIMA | C34: 09ª GRE (Cajazeiras) | D34: RUA JOSE LEITE DE OLIVEIRA, 215 POR DO SOL. 58900-000 Cajazeiras - PB. | F34: Cajazeiras | G34: PB
A35: 25007726 | B35: ECI EEFM PROFESSOR CRISPIM COELHO | C35: 09ª GRE (Cajazeiras) | D35: AV PEDRO MORENO GONDIM, 0 ESTADUAL. CENTRO. 58900-000 Cajazeiras - PB. | F35: Cajazeiras | G35: PB
A36: 25007742 | B36: EEEFM DOM MOISES COELHO | C36: 09ª GRE (Cajazeiras) | D36: RUA PADRE JOSE TOMAZ, 387 TERREO. CENTRO. 58900-000 Cajazeiras - PB. | F36: Cajazeiras | G36: PB
A37: 25007785 | B37: ECIT CRISTIANO CARTAXO | C37: 09ª GRE (Cajazeiras) | D37: AV JULIO MARQUES DO NASCIMENTO, 915 JARDIM OASIS. 58900-000 Cajazeiras - PB. | F37: Cajazeiras | G37: PB
A38: 25007840 | B38: EEEF MONSENHOR JOAO MILANES | C38: 09ª GRE (Cajazeiras) | D38: PRACA DOM ADAUTO, SN PRACA DO XAMEGAO. CENTRO. 58900-000 Cajazeiras - PB. | F38: Cajazeiras | G38: PB
A39: 25007882 | B39: EEEF SINHAZINHA RAMALHO | D39: RUA PROJETADA, 25 POR DO SOL. 58900-000 Cajazeiras - PB. | F39: Cajazeiras | G39: PB
A40: 25007904 | B40: EEEFM MONSENHOR CONSTANTINO VIEIRA | C40: 09ª GRE (Cajazeiras) | D40: RUA PADRE ROLIM, 457 CENTRO. 58900-000 Cajazeiras - PB. | F40: Cajazeiras | G40: PB
A41: 25008951 | B41: EEEF MONTE CARMELO | C41: 09ª GRE (Cajazeiras) | D41: RUA VICENTE BEZERRA, 1 ESCOLA. ESPERANCA. 58900-000 Cajazeiras - PB. | F41: Cajazeiras | G41: PB
A42: 25009192 | B42: ECI JOEL PEREIRA DA SILVA | C42: 09ª GRE (Cajazeiras) | D42: RUA JOAO BEZERRA SN, 00 TERREO. CENTRO. 58945-000 Carrapateira - PB. | F42: Carrapateira | G42: PB
A43: 25009214 | B43: EEEF DE AVE MARIA | D43: SITIO AVE MARIA, SN RURAL. 58945-000 Carrapateira - PB. | F43: Carrapateira | G43: PB
A44: 25009559 | B44: ECI BONIFACIO SARAIVA DE MOURA | C44: 09ª GRE (Cajazeiras) | D44: RUA PROJETADA, SN PREDIO ESCOLAR A MAR. CENTRO. 58950-000 Monte Horebe - PB. | F44: Monte Horebe | G44: PB
A45: 25009923 | B45: EEEM PROFESSOR JOSE BENTO | C45: 09ª GRE (Cajazeiras) | D45: RUA JOSIAS FRANCISCO DINIZ, 208 ESCOLA. CENTRO. 58925-000 Santa Helena - PB. | F45: Santa Helena | G45: PB
A46: 25009931 | B46: ECI ELAINE SOARES BRASILEIRO | C46: 09ª GRE (Cajazeiras) | D46: RUA JOANA FERREIRA DE SOUSA, 272 PREDIO. CENTRO. 58925-000 Santa Helena - PB. | F46: Santa Helena | G46: PB
A47: 25010565 | B47: ECIT PREFEITO JOAQUIM LACERDA LEITE | C47: 09ª GRE (Cajazeiras) | D47: RAIMUNDO ALVES, 125 SANTO ANTONIO. 58940-000 São José de Piranhas - PB. | F47: São José de Piranhas | G47: PB
A48: 25010638 | B48: EEEF PROF LUIZ ALBERTO DE PAIVA | D48: RUA EXPEDITO RODRIGUES DE HOLANDA, S/N CENTRO. 58940-000 São José de Piranhas - PB. | F48: São José de Piranhas | G48: PB
A49: 25010646 | B49: EEEF SAO SEBASTIAO | D49: AV. CENTENARIA, 14 SAO SEBASTIAO. 58940-000 São José de Piranhas - PB. | F49: São José de Piranhas | G49: PB
A50: 25010670 | B50: EEEF BAIRRO SANTO ANTONIO | D50: AVENIDA CENTENARIA, 239 SAO SEBASTIAO. 58940-000 São José de Piranhas - PB. | F50: São José de Piranhas | G50: PB
A51: 25010727 | B51: EEEF SANTA MARIA GORETE | D51: RUA INACIO LIRA, 543 CENTRO. 58940-000 São José de Piranhas - PB. | F51: São José de Piranhas | G51: PB
A52: 25011669 | B52: EEEM SAO JOSE | C52: 09ª GRE (Cajazeiras) | D52: RUA EXPEDITO RODRIGUES DE HOLANDA, 146 CENTRO. 58940-000 São José de Piranhas - PB. | F52: São José de Piranhas | G52: PB
A53: 25012185 | B53: EEEM ANTONIO FRANCISCO DUARTE | C53: 09ª GRE (Cajazeiras) | D53: AV JOSE DUARTE DE SA, 89 PREDIO. CENTRO. 58920-000 Triunfo - PB. | F53: Triunfo | G53: PB
A54: 25012193 | B54: ECI NELSON BATISTA ALVES | C54: 09ª GRE (Cajazeiras) | D54: RUA JOSE ESTRELA ABRANTES, 245 CENTRO. 58922-000 Bernardino Batista - PB. | F54: Bernardino Batista | G54: PB
A55: 25012207 | B55: ECIT BERNARDINO JOSE BATISTA | C55: 09ª GRE (Cajazeiras) | D55: TABELIAO ANTONIO LISBOA LISBOA, SN BELA VISTA. 58920-000 Triunfo - PB. | F55: Triunfo | G55: PB
A56: 25012916 | B56: ECIT DOUTOR JOSE DUARTE FILHO | C56: 09ª GRE (Cajazeiras) | D56: RUA FRANCISCO LEAO VELOSO, 448 CENTRO. 58915-000 Uiraúna - PB. | F56: Uiraúna | G56: PB
A57: 25012924 | B57: EEEFM JOVELINA GOMES | C57: 09ª GRE (Cajazeiras) | D57: RUA JOAO PESSOA, 88 FRENTE A PRACA PALMI. SAO JOSE. 58915-000 Uiraúna - PB. | F57: Uiraúna | G57: PB
A58: 25012932 | B58: ECI SAO JOSE OPERARIO | C58: 09ª GRE (Cajazeiras) | D58: RUA PROJETADA SN, 1 CENTRO. 58928-000 Joca Claudino - PB. | F58: Joca Claudino | G58: PB
A59: 25012940 | B59: ECI JOSE NILSON SANTIAGO | C59: 09ª GRE (Cajazeiras) | D59: RUA ODILON FRANCISCO DE OLIVEIRA, SN PROXIMO AO HOSPITAL. CENTRO. 58933-000 Poço Dantas - PB. | F59: Poço Dantas | G59: PB
A60: 25012959 | B60: EEEF ERNANI SATIRO | C60: 09ª GRE (Cajazeiras) | D60: RUA BRASILIANO VIEIRA, 34 ALTO BELA VISTA. 58915-000 Uiraúna - PB. | F60: Uiraúna | G60: PB
A61: 25012967 | B61: EEEFM MONSENHOR CONSTANTINO VIEIRA | D61: DISTRITO DE QUIXABA DE CIMA, SN DISTRITO DE QUIXABA. 58915-000 Uiraúna - PB. | F61: Uiraúna | G61: PB
A62: 25013840 | B62: ECIT DR TRAJANO PIRES DA NOBREGA | C62: 13ª GRE (Pombal) | D62: RUA MIGUEL FERNANDES FERREIRA, SN PROXIMO AO CAMPO MUN. CENTRO. 58714-000 Condado - PB. | F62: Condado | G62: PB
A63: 25013866 | B63: EEEF DR JOSE QUEIROGA | D63: RUA JOSE MACHADO DE OLIVEIRA, 5 CENTRO. 58714-000 Condado - PB. | F63: Condado | G63: PB
A64: 25014226 | B64: ECI MANOEL MEDEIROS DE ARAUJO | C64: 13ª GRE (Pombal) | D64: RUA JOAO FRANCISCO FILHO, 190 CENTRO. 58710-000 Vista Serrana - PB. | F64: Vista Serrana | G64: PB
A65: 25014412 | B65: ECI NESTORINA ABRANTES | C65: 10ª GRE (Sousa) | D65: RUA PEDRO ABRANTES FERREIRA, 278 CENTRO. 58820-000 Lastro - PB. | F65: Lastro | G65: PB
A66: 25014692 | B66: ECIT DOUTOR ANTONIO FERNANDES MEDEIROS | C66: 06ª GRE (Patos) | D66: RUA CEL ANTONIO DE ASSIS FERREIRA, SN PROXIMO A BR 230. CENTRO. 58713-000 Malta - PB. | F66: Malta | G66: PB
A67: 25014951 | B67: ECI FRANCISCO AUGUSTO CAMPOS | C67: 10ª GRE (Sousa) | D67: RUA HERCULANO VIEIRA, SN BAIRRO FRANCISCO MEN. FRANCISCO MENDES CAMPOS. 58817-000 Nazarezinho - PB. | F67: Nazarezinho | G67: PB
A68: 25014960 | B68: EEEF MANOEL MENDES | C68: 10ª GRE (Sousa) | D68: RUA JOAO LUIZ, SN CENTRO. 58817-000 Nazarezinho - PB. | F68: Nazarezinho | G68: PB
A69: 25015320 | B69: ECIT FRANCISCO DE SA CAVALCANTE | C69: 13ª GRE (Pombal) | D69: RUA BELARMINO FERNANDES DE FRANCA, SN PREDIO. CENTRO. 58860-000 Paulista - PB. | F69: Paulista | G69: PB
A70: 25015346 | B70: EEEF DE QUEIMADAS | D70: SITIO QUEIMADAS, 58860-000 Paulista - PB. | F70: Paulista | G70: PB
A71: 25015869 | B71: ECIT MONSENHOR VICENTE FREITAS | C71: 13ª GRE (Pombal) | D71: RUA PROFESSOR LUIZ FERREIRA CAMPOS, 309 ESCOLA TECNICA ESTAD. JARDIM ROGERIO. 58840-000 Pombal - PB. | F71: Pombal | G71: PB
A72: 25015885 | B72: EEEFM JOAO DA MATA | C72: 13ª GRE (Pombal) | D72: PRACA DR JOSE FERREIRA DE QUEIROGA, 00 PRACA DO CENTENARIO. CENTRO. 58840-000 Pombal - PB. | F72: Pombal | G72: PB
A73: 25015893 | B73: EEEFM ARRUDA CAMARA | C73: 13ª GRE (Pombal) | D73: MARGEM DA BR230, SN PREDIO PROPRIO. JARDIM ROGERIO. 58840-000 Pombal - PB. | F73: Pombal | G73: PB
A74: 25016024 | B74: EEEFM OITO DE JULHO | C74: 13ª GRE (Pombal) | D74: RUA PRACA DA BANDEIRA, 723 ESQUINA. CENTRO. 58840-000 Pombal - PB. | F74: Pombal | G74: PB
A75: 25016032 | B75: EEEFM AMELIA MARIA DA LUZ | C75: 13ª GRE (Pombal) | D75: TRAVESSA CORONEL JOSE AVELINO, SN TERREO. PETROPOLIS. 58840-000 Pombal - PB. | F75: Pombal | G75: PB
A76: 25016059 | B76: ECI MARIA SOLEDADE ASSIS FREITAS | C76: 13ª GRE (Pombal) | D76: RUA ANTONIO CEZARIO DA SILVA, SN PREDIO. CENTRO. 58855-000 Cajazeirinhas - PB. | F76: Cajazeirinhas | G76: PB
A77: 25016075 | B77: EEEF DE ESTRELO | D77: SITIO ESTRELO, 00 PREDIO. ZONA RURAL. 58840-000 Pombal - PB. | F77: Pombal | G77: PB
A78: 25016083 | B78: EEEF DE MUNDO NOVO | D78: ASSENTAMENTO JACU, SN CASA. ZONA RURAL. 58840-000 Pombal - PB. | F78: Pombal | G78: PB
A79: 25016105 | B79: ECI DEPUTADO LEVI OLIMPIO FERREIRA | C79: 13ª GRE (Pombal) | D79: RUA ERNANE ROQUE DE ARRUDA, SN CENTRO. 58857-000 São Bentinho - PB. | F79: São Bentinho | G79: PB
A80: 25016156 | B80: EEEF SANTA MARIA | D80: SITIO SANTA MARIA, 58840-000 Pombal - PB. | F80: Pombal | G80: PB
A81: 25016164 | B81: ECIT CICERO SEVERO LOPES | C81: 13ª GRE (Pombal) | D81: RUA EMILIA SANTINA DE JESUS, 0 BELA VISTA. 58853-000 São Domingos - PB. | F81: São Domingos | G81: PB
A82: 25017071 | B82: EEEF PROFESSOR NESTOR ANTUNES | C82: 10ª GRE (Sousa) | D82: RUA JOSE VITAL DE OLIVEIRA, 61 CENTRO. 58824-000 Santa Cruz - PB. | F82: Santa Cruz | G82: PB
A83: 25017080 | B83: ECIT VALDEMIRO WANDERLEY DE OLIVEIRA | C83: 10ª GRE (Sousa) | D83: CONJUNTO MAURICIO GOMES, SN SAO FRANCISCO. 58824-000 Santa Cruz - PB. | F83: Santa Cruz | G83: PB
A84: 25017438 | B84: ECI ANTONIO GREGORIO DE LACERDA | C84: 10ª GRE (Sousa) | D84: RUA ANTONIO GREGORIO DE LACERDA, SN PROXIMO A CAGEPA. SANHAUA. 58815-000 São José da Lagoa Tapada - PB. | F84: São José da Lagoa Tapada | G84: PB
A85: 25018060 | B85: EEEFM IZIDRA PACIFICO DE ARAUJO | D85: NUCLEO HABITACIONAL I, 01 SAO GONCALO. 58814-000 Sousa - PB. | F85: Sousa | G85: PB
A86: 25018078 | B86: EEEFM ANDRE GADELHA | C86: 10ª GRE (Sousa) | D86: RUA VEREADOR JOSE FRANCISCO VIEIRA DE FIGUEIREDO, 88 PREDIO ESCOLAR. AREIAS. 58801-455 Sousa - PB. | F86: Sousa | G86: PB
A87: 25018094 | B87: ECIT DOUTOR JOSE GADELHA | C87: 10ª GRE (Sousa) | D87: RUA JOAO AMANCIO PIRES, 95 CENTRO. 58823-000 Aparecida - PB. | F87: Aparecida | G87: PB
A88: 25018124 | B88: EEEF BATISTA LEITE | C88: 10ª GRE (Sousa) | D88: RUA LUIS PEREIRA DA SILVA, 22 CENTRO. 58800-040 Sousa - PB. | F88: Sousa | G88: PB
A89: 25018132 | B89: EEEF BENTO FREIRE | C89: 10ª GRE (Sousa) | D89: RUA JOAQUIM PINTO NETO, 2 ESTACAO. 58807-275 Sousa - PB. | F89: Sousa | G89: PB
A90: 25018140 | B90: EEEFM CELSO MARIZ | C90: 10ª GRE (Sousa) | D90: ARY FERNANDES DE ARAGAO, SN TERREO. JARDIM SORRILANDIA III. 58805-535 Sousa - PB. | F90: Sousa | G90: PB
A91: 25018183 | B91: EEEFM ESTEVAM MARINHO | D91: AVENIDA RIO PIRANHAS - Centro, Sousa - PB, 58814-000 | F91: Sousa | G91: PB
A92: 25018191 | B92: EEEFM FRANCISCO CICERO SOBRINHO | D92: NUCLEO HABITACIONAL III, SN SAO GONCALO. SAO GONCALO. 58814-600 Sousa - PB. | F92: Sousa | G92: PB
A93: 25018221 | B93: EEEFM CONEGO JOAO CARTAXO ROLIM | C93: 10ª GRE (Sousa) | D93: RUA DORGIVAL DA NOBREGA ASSIS, SN PAROQUIA SAO JOAO BA. ALTO DO CRUZEIRO. 58806-250 Sousa - PB. | F93: Sousa | G93: PB
A94: 25018256 | B94: EEEF DE DEMONSTRACAO DE SOUSA | C94: 10ª GRE (Sousa) | D94: RUA JOSE DE PAIVA GADELHA, 141 GATO PRETO. 58802-085 Sousa - PB. | F94: Sousa | G94: PB
A95: 25018264 | B95: EEEF JAIME MEIRA FONTES | C95: 10ª GRE (Sousa) | D95: RUA RAIMUNDO MARQUES BRAGA ROLIM FILHO, 22 PREDIO ALUGADO. DOUTOR ZEZE. 58804-450 Sousa - PB. | F95: Sousa | G95: PB
A96: 25018272 | B96: EEEFM PROFESSORA DIONE DINIZ OLIVEIRA DIAS | D96: NUCLEO HABITACIONAL II, SN AREA RURAL. 58814-500 Sousa - PB. | F96: Sousa | G96: PB
A97: 25018280 | B97: ECIT MESTRE JULIO SARMENTO | C97: 10ª GRE (Sousa) | D97: RUA JOSE DE PAIVA GADELHA, 125 GATO PRETO. 58802-085 Sousa - PB. | F97: Sousa | G97: PB
A98: 25018582 | B98: EEEM JOSE DE PAIVA GADELHA | C98: 10ª GRE (Sousa) | D98: RUA JOSE DE PAIVA GADELHA, 127 VIZINHO A SECRETARIA. GATO PRETO. 58802-085 Sousa - PB. | F98: Sousa | G98: PB
A99: 25018639 | B99: EEEFM DOUTOR THOMAZ PIRES | C99: 10ª GRE (Sousa) | D99: RUA RAIMUNDO PEREIRA DE OLIVEIRA, SN JARDIM SORRILANDIA I. 58805-150 Sousa - PB. | F99: Sousa | G99: PB
A100: 25019228 | B100: EEEFM ANTONIO TEODORO NETO | C100: 10ª GRE (Sousa) | D100: RUA VEREADOR JOSE GONCALVES FORMIGA, SN MUTIRAO. SANTAREM. 58808-470 Sousa - PB. | F100: Sousa | G100: PB
A101: 25019538 | B101: ECIT DOUTOR SILVA MARIZ | C101: 10ª GRE (Sousa) | D101: RUA BELARMINO RUFINO DE CARVALHO, 22 CENTRO. 58819-000 Marizópolis - PB. | F101: Marizópolis | G101: PB
A102: 25019597 | B102: ECI DORGIVAL SILVEIRA | C102: 10ª GRE (Sousa) | D102: RUA FRANCISCO ANTONIO DA SILVEIRA, 110 PREDIO. CENTRO. 58818-000 São Francisco - PB. | F102: São Francisco | G102: PB
A103: 25019740 | B103: ECI MARIA MOREIRA PINTO | C103: 10ª GRE (Sousa) | D103: RUA AGRIPINO FERNANDES DAS CHAGAS, SN CENTRO. 58822-000 Vieirópolis - PB. | F103: Vieirópolis | G103: PB
A104: 25019813 | B104: ECI ALDO SATIRO XAVIER | C104: 06ª GRE (Patos) | D104: RUA GILVAN SOARES, SN SALAS CEDIDAS. CENTRO. 58730-000 Cacimba de Areia - PB. | F104: Cacimba de Areia | G104: PB
...

Sheet Ambientes
A1: Id_Ambiente | B1: Id_Escola | C1: Nome_Ambiente | D1: Qtd_alunos | E1: MetrosQ | F1: PossuiCabeamento | G1: QualidadeWifi | H1: Foto | I1: Observacao

Sheet Itens_Infra
A1: Id_Item | B1: Id_Ambiente | C1: Equipamento | D1: Modelo_Sugerido | E1: Quantidade | F1: Preco_Estimado

Sheet Configuracoes_Padrao
A1: Id_Config | B1: Equipamento | C1: Modelo_Padrao | D1: Preco_Base

Sheet Dns
A1: Id_Dns | B1: Escola | C1: DataImplantacao | D1: TipodeDNS | E1: Login | F1: Senha | G1: LocalInstalacao | H1: TipoControle | I1: Always_block | J1: Never_block | K1: OpenDNSupdater | L1: NetworkID | M1: IdRede | N1: Controleparental | O1: Listanegra | P1: Listabranca | Q1: Observacao
A2: 2966589f | B2: 25070576 | C2: 45965 | D2: OpenDns | E2: 25070576pb@gmail.com | F2: @dmSeepb1 | L2: 177.66.87.9 | Q2: Inativo desde 15/01/2026, hoje é 25/02/2026
A3: 5a9cd105 | B3: 25059629 | C3: 46000 | D3: OpenDns | E3: 25059629pb@see.pb.gov.br | F3: @dmSeepb1 | Q3: Inativo desde 10/01/2026
A4: c6798880 | B4: 25067133 | C4: 45994 | Q4: A escola ja possui um firewall, foi feita a configuração e refinamento dos bloqueios.
A5: 827fb07c | B5: 25066013 | C5: 46000 | D5: OpenDns | E5: 25066013pb@see.pb.gov.br | F5: @dmSeepb1 | L5: 177.66.87.21
A6: b673a4db | B6: 25094556 | C6: 46045 | D6: NextDNS | E6: 25094556pb@see.pb.gov.br | F6: @dmSeepb | M6: 1336d4
A7: b9e2ec2e | B7: 25101099 | C7: 45938 | D7: NextDNS | E7: 25101099pb@gmail.com | F7: @dmSeepb1 | M7: 1851ad
A8: dc9aa510 | B8: 25094459 | C8: 46063 | D8: NextDNS | E8: barclaymedeiros@gmail.com | M8: 69287d

Sheet Controle_Filtro
A1: Id | B1: Mes | C1: Ano
A2: 1 | B2: 10 | C2: 2026

Sheet Regionais
A1: Regional
A2: 01ª GRE (João Pessoa)
A3: 02ª GRE (Guarabira)
A4: 03ª GRE (Campina Grande)
A5: 04ª GRE (Cuité)
A6: 05ª GRE (Monteiro)
A7: 06ª GRE (Patos)
A8: 07ª GRE (Itaporanga)
A9: 08ª GRE (Catolé do Rocha)
A10: 09ª GRE (Cajazeiras)
A11: 10ª GRE (Sousa)
A12: 11ª GRE (Princesa Isabel)
... A17: 16ª GRE (João Pessoa)

Sheet Auditoria
A1: ID_Auditoria | B1: Viagem | C1: ID_Viagem | D1: ID_Relatorio | E1: IDTecnico | F1: Motivo | G1: Tecnico_Auditado | H1: Data_Auditoria | I1: ExecucaoTecnica | J1: InfraestruturaeSistemas | K1: PosturaeDocumentacao | L1: Nota_Causa_Raiz | M1: Nota_Uso_Pecas | N1: Nota_Dominio_Ferramentas | O1: Nota_Acabamento | P1: Nota_Zelo_Patrimonio | Q1: Nota_Cabeamento | R1: Nota_Rack | S1: Nota_Internet | T1: Nota_Software | U1: Nota_Rede_Logica | V1: Nota_Cordialidade | W1: Nota_Resiliencia | X1: Nota_Fotos | Y1: Check_EPI_Uniforme | Z1: Check_Preenchimento | AA1: Check_Roteiro | AB1: Parecer_Lider
A2: =Auditoria_Respostas!B8 | B2: =Auditoria_Respostas!C8 | C2: =Auditoria_Respostas!D8 | D2: =Auditoria_Respostas!E8 | E2: =Auditoria_Respostas!F8 | F2: =Auditoria_Respostas!G8 | G2: =Auditoria_Respostas!H8 | H2: =Auditoria_Respostas!I8 | ... AB2: =Auditoria_Respostas!AC8

Sheet Viagens
A1: Id | B1: Viagem_Id | C1: Data_Ida | D1: Data_Volta | E1: Tecnicos | F1: Regional | G1: Escolas | H1: Motivo | I1: PBDOC | J1: Status | K1: Cancelado | L1: Link_Relatorio | M1: ATIVIDADESEXECUTADAS_FATOSTRANSCORRIDOS | N1: OUTRASOBSERVAÇOES
A2: bb85f3f0 | B2: 020226-050226 - 08ª GRE (Catolé do Rocha) | C2: 46055 | D2: 46058 | E2: 2fc34ae3 | F2: 08ª GRE (Catolé do Rocha) | G2: 8 | H2: Cabeamento Estruturado | I2: SEE-PRC-2026/03833 | K2: FALSE
A3: e26643bf | B3: 230226-270226 - 04ª GRE (Cuité) _ 05ª GRE (Monteiro) | C3: 46076 | D3: 46080 | E3: 8aec2db9 , 54d6fbb6 , be4898e6 | F3: 04ª GRE (Cuité) , 05ª GRE (Monteiro) | G3: 25043897 , 25043870 , 25115359 , 25047116 | H3: Analise Técnica , Cabeamento Estruturado | I3: SEE-PRC-2026/04335 | M3: ECIT Cìcero dos Anjos - GRE4 - Análise Técnica Para Implementação de Laboratório de Informática. ECI Maria Francinete de Souza - GRE4 - Análise Técnica Para Implementação de Laboratório de Informática. ECI Mario Oliveira Chaves - GRE5 - Análise Técnica Para Implementação de Laboratório de Informática. EEEM João Oliveira Chaves - Cabeamento Estruturado e Configuração da Rede Interna de Dados.
A6: 53e81e0b | B6: 160326-200326 - 09ª GRE (Cajazeiras) | C6: 46097 | D6: 46101 | E6: 16f6798d , 09fd55aa , 14fb10d2 | F6: 09ª GRE (Cajazeiras) | G6: 25007718 , 25007742 , 25007726 | H6: Analise Técnica | I6: SEE-PRC-2026/04920 | K6: FALSE
A7: 13a33551 | B7: 090326-130326 - 09ª GRE (Cajazeiras) | C7: 46090 | D7: 46094 | E7: 2fc34ae3 , 4aca042e , be4898e6 | F7: 09ª GRE (Cajazeiras) | G7: 25007904 , 25008951 , 25007840 | H7: Analise Técnica | I7: SEE-PRC-2026/04918 | K7: FALSE
A8: 2e32c6c0 | B8: 020326-060326 - 09ª GRE (Cajazeiras) | C8: 46083 | D8: 46087 | E8: 6bbd148a , b96f4e6b , 04531b9c | F8: 09ª GRE (Cajazeiras) | G8: 25129325 , 25129295 , 25007785 | H8: Analise Técnica | I8: SEE-PRC-2026/04917 | K8: FALSE
A9: 853ad56b | B9: 230326-270326 - 03ª GRE (Campina Grande) _ 05ª GRE (Monteiro) _ 14ª GRE (Mamanguape) | C9: 46104 | D9: 46108 | E9: 16f6798d , 14fb10d2 , 94f6e6b3 | F9: 03ª GRE (Campina Grande) , 05ª GRE (Monteiro) , 14ª GRE (Mamanguape) | G9: 25063421 , 25062220 , 25054023 , 25062069 , 25087304 | H9: Análise Técnica | I9: SEE-PRC-2026/06133 | K9: FALSE
A10: d4897c65 | B10: 060426-100426 - 12ª GRE (Itabaiana) | C10: 46118 | D10: 46122 | E10: 4aca042e , 54d6fbb6 , be4898e6 | F10: 12ª GRE (Itabaiana) | G10: 25080849 | H10: Cabeamento Estruturado | I10: SEE-PRC-2026/06134 | K10: FALSE
A11: 6dada0ad | B11: 060526-080526 - 08ª GRE (Catolé do Rocha) _ 09ª GRE (Cajazeiras) _ 10ª GRE (Sousa) _ 13ª GRE (Pombal) | C11: 46148 | D11: 46150 | E11: 6bbd148a , b96f4e6b , 04531b9c | F11: 08ª GRE (Catolé do Rocha) , 09ª GRE (Cajazeiras) , 10ª GRE (Sousa) , 13ª GRE (Pombal) | H11: Robótica | K11: FALSE
A12: 6e527e1f | B12: 110526-160526 - 05ª GRE (Monteiro) _ 06ª GRE (Patos) _ 07ª GRE (Itaporanga) _ 11ª GRE (Princesa Isabel) | C12: 46153 | D12: 46158 | E12: 6bbd148a , b96f4e6b , 04531b9c | F12: 05ª GRE (Monteiro) , 06ª GRE (Patos) , 07ª GRE (Itaporanga) , 11ª GRE (Princesa Isabel) | H12: Robótica | K12: FALSE
A13: 1d45e106 | B13: 180526-230526 - 12ª GRE (Itabaiana) _ 14ª GRE (Mamanguape) | C13: 46160 | D13: 46165 | E13: 6bbd148a , b96f4e6b , 04531b9c | F13: 12ª GRE (Itabaiana) , 14ª GRE (Mamanguape) | H13: Robótica | K13: FALSE
A14: 9bd7519a | B14: 250526-260526 - 02ª GRE (Guarabira) _ 03ª GRE (Campina Grande) _ 04ª GRE (Cuité) _ 15ª GRE (Queimadas) _ 16ª GRE (João Pessoa) | C14: 46167 | D14: 46168 | E14: 6bbd148a , b96f4e6b , 04531b9c | F14: 02ª GRE (Guarabira) , 03ª GRE (Campina Grande) , 04ª GRE (Cuité) , 15ª GRE (Queimadas) , 16ª GRE (João Pessoa) | H14: Robótica | K14: FALSE
A15: 03f67c5e | B15: 050526-090526 - 07ª GRE (Itaporanga) _ 09ª GRE (Cajazeiras) _ 11ª GRE (Princesa Isabel) | C15: 46147 | D15: 46151 | E15: 2fc34ae3 , be4898e6 | F15: 07ª GRE (Itaporanga) , 09ª GRE (Cajazeiras) , 11ª GRE (Princesa Isabel) | H15: Orçamento Democrático Estadual | K15: FALSE
A16: 4997cea8 | B16: 110526-150526 - 08ª GRE (Catolé do Rocha) _ 10ª GRE (Sousa) | C16: 46153 | D16: 46157 | E16: 2fc34ae3 , be4898e6 | F16: 08ª GRE (Catolé do Rocha) , 10ª GRE (Sousa) | H16: Orçamento Democrático Estadual | K16: FALSE
A18: b8b6f776 | B18: 260526-300526 - 03ª GRE (Campina Grande) _ 04ª GRE (Cuité) _ 05ª GRE (Monteiro) | C18: 46168 | D18: 46172 | E18: 2fc34ae3 , be4898e6 | F18: 03ª GRE (Campina Grande) , 04ª GRE (Cuité) , 05ª GRE (Monteiro) | H18: Orçamento Democrático Estadual | K18: FALSE
A19: e73d8e72 | B19: 030626-070626 - 06ª GRE (Patos) _ 12ª GRE (Itabaiana) | C19: 46176 | D19: 46180 | E19: 2fc34ae3 , be4898e6 | F19: 06ª GRE (Patos) , 12ª GRE (Itabaiana) | H19: Orçamento Democrático Estadual | K19: FALSE
A20: fcbf02a6 | B20: 270426-300426 - 11ª GRE (Princesa Isabel) | C20: 46139 | D20: 46142 | E20: 16f6798d , 8aec2db9 , 54d6fbb6 | F20: 11ª GRE (Princesa Isabel) | H20: Levantamento Patrimonial | K20: FALSE
A21: 161168f1 | B21: 130426-170426 - 11ª GRE (Princesa Isabel) | C21: 46125 | D21: 46129 | E21: 16f6798d , 8aec2db9 , 54d6fbb6 | F21: 11ª GRE (Princesa Isabel) | H21: Levantamento Patrimonial | K21: FALSE
A22: a449c6bc | B22: 220426-230426 - 14ª GRE (Mamanguape) | C22: 46134 | D22: 46135 | E22: 6bbd148a , b96f4e6b , 04531b9c | F22: 14ª GRE (Mamanguape) | H22: Robótica | K22: FALSE
A23: dc51db5b | B23: 260426-300426 - 10ª GRE (Sousa) | C23: 46138 | D23: 46142 | E23: 6bbd148a , b96f4e6b , 04531b9c | F23: 10ª GRE (Sousa) | H23: Robótica | K23: FALSE
... A26: 7efe0f0e | B26: 150626-190626 - 05ª GRE (Monteiro) | C26: 46188 | D26: 46192 | E26: 8aec2db9 , 09fd55aa , 2f2e208d | F26: 05ª GRE (Monteiro) | H26: Levantamento Patrimonial | K26: FALSE
A27: 3ab34167 | B27: 290626-030726 - | C27: 46202 | D27: 46206 | E27: 8aec2db9 , 09fd55aa , 2f2e208d | H27: Levantamento Patrimonial | K27: FALSE
A28: 90bcfc7f | B28: 080626-120626 - 08ª GRE (Catolé do Rocha) | C28: 46181 | D28: 46185 | E28: 16f6798d , 14fb10d2 , 54d6fbb6 | F28: 08ª GRE (Catolé do Rocha) | H28: Levantamento Patrimonial | K28: FALSE
A29: 82e0e58f | B29: 150626-190626 - 08ª GRE (Catolé do Rocha) | C29: 46188 | D29: 46192 | E29: 16f6798d , 14fb10d2 , 54d6fbb6 | F29: 08ª GRE (Catolé do Rocha) | H29: Levantamento Patrimonial | K29: FALSE
A30: e3a4abf4 | B30: 290626-030726 - 08ª GRE (Catolé do Rocha) | C30: 46202 | D30: 46206 | E30: 16f6798d , 14fb10d2 , 54d6fbb6 | F30: 08ª GRE (Catolé do Rocha) | H30: Levantamento Patrimonial | K30: FALSE

Sheet Relatorios
A1: Id_Relatorio | B1: ID_Viagem | C1: Data_Relatorio | D1: Escola | E1: Tecnico_Responsavel | F1: Tecnicos | G1: Assinatura_Tecnico | H1: Motivo_Chamado | I1: Descricao_Problema | J1: Resolucao_Chamado | K1: Nome_Responsavel_Escola | L1: Assinatura_Escola | M1: Ultima_Atualizacao | N1: Status_Relatorio
A2: ec91dca7 | C2: 46056 | D2: 25094688 | F2: 16f6798d , 4aca042e , be4898e6 | H2: Manutenção Corretiva | I2: *Office 365 com problema de autenticação *Office em língua inglesa. | J2: *Feito backup e reinstalação da imagem, pois o office não esta sendo aceito pelo computador *Troca da língua para português br | K2: 1940759 | L2: Relatorios_Images/ec91dca7.Assinatura_Escola.124820.png | M2: 46059.934 | N2: Gerar PDF
A3: 80d9fd4a | C3: 46056 | D3: 25094459 | F3: 16f6798d , 4aca042e , be4898e6 | H3: Manutenção Corretiva | I3: *Computadores DATEN do laboratorio com instalação de softwares não pedagógicos *Computador HP com fonte queimada | J3: *Será instalado o sistema de proteção DNS *Computador com fonte queimada sera feito a troca caso se tenha a mesma no almoxarifado. | M3: 46057.219 | N3: Rascunho
A4: d20ca6dd | C4: 46058 | D4: 25093827 | F4: be4898e6 , 04531b9c , 98b2226d | H4: Manutenção Corretiva | I4: Direção e secretaria não estava conseguindo imprimir nas impressoras Epson L4260. | J4: Foi feito a instalação de duas impressoras Epson L4260, e foi feito o compartilhamento para os computadores da secretaria e direção. Foi feito a organização dos nomes dos computadores sec001, sec002, sec003 e na direção - DIREÇÃO001 | K4: 1803310 | L4: Relatorios_Images/d20ca6dd.Assinatura_Escola.141909.png | M4: 46059.928 | N4: Gerar PDF
A5: 2d983fab | C5: 46059 | D5: 25093835 | F5: 16f6798d , 4aca042e , be4898e6 | H5: Cabeamento Estruturado | I5: *Computador sem rede; | J5: *Feito cabo de rede para o computador(foto em anexo). | K5: 1942956 | L5: Relatorios_Images/2d983fab.Assinatura_Escola.125033.png | M5: 46059.937 | N5: Gerar PDF
A6: 4bc0c752 | C6: 46059 | D6: 25128337 | F6: 16f6798d , 4aca042e , be4898e6 | H6: Internet Offline | I6: Secretaria sem internet | J6: Resete no roteador CODATA e voltou a funcionar. | K6: 1859862 | L6: Relatorios_Images/4bc0c752.Assinatura_Escola.143654.png | M6: 46059.484 | N6: Gerar PDF
A7: be11ab15 | C7: 46062 | D7: 25094211 | E7: 16f6798d | F7: be4898e6 | G7: Relatorios_Images/be11ab15.Assinatura_Tecnico.132421.png | H7: Análise Técnica | J7: 1 . LISTA DE MATERIAIS PARA AQUISIÇÃO • 01 Roteador Gateway TP-Link ER605 V2: Equipamento central para gestão dos dois links de internet (Tely/Codata e Oi), controle de tráfego e aplicação do filtro NextDNS. • 01 Switch de 24portas giga: Responsável por interligar todos os pontos. • 08 Access Points TP-Link Omada: Sendo recomendados modelos Wi-Fi 6 (como o EAP610) ou (EAP225) para áreas de alta densidade como o pátio. (Aps com fonte injetoras) • 02 Caixas de Cabo de Rede Cat5e (305m cada): • 100 Barras de Canaleta de PVC 50x20mm (2 metros cada): Sistema de proteção e acabamento para condução dos cabos pelas paredes, substituindo as eletrocalhas. 2. ESTRATÉGIA DE CONECTIVIDADE E SEGURANÇA • Redundância de Internet (Dual-WAN): O sistema utilizará o link da Tely/Codata (100Mb) como principal e o link da Oi (10Mb) como reserva. Em caso de queda, a transição é automática, garantindo que as atividades escolares não parem. • Segurança Digital (NextDNS): Implementação de filtro rigoroso que bloqueia sites inadequados, anúncios e ameaças digitais em todos os dispositivos conectados, mantendo o foco educativo. • Infraestrutura com Canaletas: Todo o cabeamento será protegido por canaletas fixadas com parafusos, garantindo segurança contra vandalismo e uma estética organizada nos corredores, pátio e laboratório. 3. DISTRIBUIÇÃO FÍSICA • Corredores (Esq./Dir.): 06 unidades instaladas via canaleta para cobertura total das salas. • Pátio Central: 01 unidade de alta performance para suportar o fluxo de alunos. • Laboratório de Ciências: 01 unidade dedicada para suporte a pesquisas. | M7: 46062.646 | N7: Gerar PDF
A8: f1de38f0 | C8: 46062 | D8: 25094211 | F8: 16f6798d , be4898e6 | H8: Manutenção Corretiva | J8: Migração da rede Oi para Tely concluída. Realizada a instalação e configuração da impressora nas estações de trabalho e notebooks do setor administrativo | K8: 1902733 | L8: Relatorios_Images/f1de38f0.Assinatura_Escola.143150.png | M8: 46062.51 | N8: Gerar PDF
A9: 1b9303f3 | C9: 46063 | D9: 25093894 | F9: 16f6798d , 4aca042e , be4898e6 , 04531b9c | H9: Internet Offline | J9: Foi identificado dois links da oi: 1 no pátio com a fibra desligada (foto anexa) 1 no laboratório de informática funcionando (foto anexa). O link da oi no laboratório está ativo e funcional, porém não utilizam, usam link da escola conectada da Claro. Reconfiguração do roteador TP-Link *Ssid SALA DE PLANEJAMENTO *SENHA 78668362 | K9: 1636952 | L9: Relatorios_Images/1b9303f3.Assinatura_Escola.133926.png | M9: 46064.407 | N9: Gerar PDF
A10: f9fe4efe | C10: 46063 | D10: 25093894 | E10: 16f6798d | F10: 4aca042e , be4898e6 , 04531b9c | G10: Relatorios_Images/f9fe4efe.Assinatura_Tecnico.180520.png | H10: Análise Técnica | J10: Laboratório de Informática 01 Rack de Parede: Destinado ao acondicionamento seguro dos equipamentos, proteção contra poeira e organização do cabeamento. 01 Switch de 48 Portas Gigabit: Garante alta velocidade de transmissão de dados (10/100/1000 Mbps) para todas as estações de trabalho, assegurando estabilidade em atividades simultâneas. Secretaria e Administração 01 Switch de 48 Portas Gigabit (Substituição): Substituição do ativo atual que apresenta falhas físicas (portas danificadas). A troca é essencial para restabelecer a conectividade integral do setor administrativo e evitar interrupções nos serviços críticos. *Corredor do Laboratório: 03 Access Points (APs) para suporte à alta demanda de conexão móvel. *Corredor Frontal: 03 Access Points (APs) para cobertura de áreas comuns e salas adjacentes. *Anexo: 01 Access Point (AP) dedicado para garantir a integração do espaço à rede principal. | M10: 46063.631 | N10: Gerar PDF
A11: 41746962 | C11: 46064 | D11: 25094190 | F11: 16f6798d , be4898e6 | H11: Internet Offline | J11: Incidente de Conectividade: Identificada perda de sinal óptico (LED LOS em vermelho) nos links Opix e CODATA. Procedendo com a abertura de chamado técnico junto às operadoras para reparo imediato. | K11: 1848186 | L11: Relatorios_Images/41746962.Assinatura_Escola.132635.png | M11: 46064.481 | N11: Rascunho
A12: d7b2c7cf | C12: 46064 | D12: 25094181 | F12: 16f6798d , be4898e6 | H12: Internet Offline | J12: Rede RNP/RIX: Identificado status "LOS" (perda de sinal óptico) no LED vermelho; chamado de reparo aberto junto à operadora. Correção: Identificado e removido loop físico na rede local. Segregação de Tráfego: Configurada a rede CODATA para uso exclusivo da Secretaria e o link OI para atendimento ao Laboratório. | K12: 1875973 | L12: Relatorios_Images/d7b2c7cf.Assinatura_Escola.141930.png | M12: 46064.48 | N12: Rascunho
A13: 2ddf654d | C13: 46064 | D13: 25095056 | F13: 16f6798d , 54d6fbb6 | H13: Internet Offline | J13: Link CODATA se encontra no rack da secretaria. Foi devidamente configurado no roteador TP-Link, que agora realiza a distribuição de conectividade para toda a rede interna da unidade escolar, antes era link da oi de 10mb. SSID em foto anexa. | K13: 1916611 | L13: Relatorios_Images/2ddf654d.Assinatura_Escola.174654.png | M13: 46065.403 | N13: Gerar PDF
A14: f5efc0ea | C14: 46066 | D14: 25092332 | F14: 16f6798d , be4898e6 | H14: Internet Offline | J14: Assunto: Configuração de Redundância de Internet – Link CODATA Informamos que o link da CODATA foi devidamente instalado e conectado ao roteador TP-Link. Este link está configurado como conexão de contingência (backup). Caso o link principal apresente instabilidade ou queda, o link CODATA deverá ser utilizado para garantir a continuidade das atividades administrativas e pedagógicas. Esta medida visa minimizar o tempo de inatividade da rede escolar. | K14: 1708643 | L14: Relatorios_Images/f5efc0ea.Assinatura_Escola.125525.png | M14: 46066.419 | N14: Rascunho
A15: 07af17fa | C15: 46066 | D15: 25093932 | F15: 16f6798d , be4898e6 | H15: Internet Offline | J15: Status dos Links Link RIX: O circuito foi identificado fisicamente no local, porém, não apresenta navegação. Foi constatada a necessidade de abertura de chamado técnico junto à operadora para reparo. Link OI: Conforme informações da direção da escola, o equipamento Fortinet foi retirado da unidade. Link PBLE: Não localizado na infraestrutura interna da escola durante a inspeção. Observações Técnicas e Recomendações No momento da visita, constatou-se que um professor tentava suporte junto à operadora RIX, porém, as evidências físicas (fotos do circuito) indicam que a fibra da RIX está conectada indevidamente em um equipamento da OI. Recomendação: É necessário que a equipe técnica da RIX compareça ao local para realizar a instalação utilizando sua própria infraestrutura de fibra óptica, corrigindo o uso indevido da rede da Oi e garantindo o pleno funcionamento do link contratado. | K15: 1845799 | L15: Relatorios_Images/07af17fa.Assinatura_Escola.133818.png | M15: 46066.471 | N15: Rascunho
A16: 2359b68b | C16: 46066 | D16: 25095005 | F16: 16f6798d , 4aca042e , be4898e6 | H16: Manutenção Corretiva | J16: Escola fechada. | M16: 46066.624 | N16: Rascunho
A17: 035147c5 | C17: 46073 | D17: 25091638 | E17: 16f6798d | F17: 16f6798d , 4aca042e , be4898e6 | H17: Instalação de Softwares , Redefinição de Senha | J17: Status do Sistema: Concluída a replicação de imagem e configuração de software em todos os 18 terminais do laboratório. Necessidades de Infraestrutura: Para a conformidade da rede local, é necessária a aquisição de 2 Racks (padrão 19") e 2 Switches Gigabit Ethernet com, no mínimo, 24 portas cada. Essa configuração visa garantir a organização do cabeamento e a alta disponibilidade de banda para as estações. | K17: 1939726 | L17: Relatorios_Images/035147c5.Assinatura_Escola.143825.png | M17: 46074.34 | N17: Gerar PDF
A18: e4f5579b | C18: 46077 | D18: 25094181 | F18: 16f6798d , 2fc34ae3 , 4aca042e | H18: Internet Offline | J18: Informamos que o link CODATA (Tely) apresenta instabilidade. Após contato com a operadora, foi agendada uma visita técnica para verificação presencial dos equipamentos. Enquanto o reparo não é concluído, a Secretaria operará prioritariamente através do link de contingência da Rix. Chamado junto a Tely de Nº1189716 | K18: 1875973 | L18: Relatorios_Images/e4f5579b.Assinatura_Escola.134825.png | M18: 46077.618 | N18: Gerar PDF
A19: 69bee1ed | B19: e26643bf | C19: 46080 | D19: 25115359 | F19: 8aec2db9 , be4898e6 , 54d6fbb6 | H19: Cabeamento Estruturado | J19: 1. Atividades Realizadas Durante a visita técnica, foram executados os seguintes serviços: Montagem e organização de rack de conexões, com instalação de 02 (dois) switches para distribuição da rede de dados. Conectorização de pontos de rede (RJ-45 fêmea), conforme detalhamento: Laboratório de Informática: 26 (vinte e seis) pontos de rede. Laboratório de Química: 13 (treze) pontos de rede. Grêmio Estudantil: 08 (oito) pontos de rede. Configuração da rede interna de dados do Laboratório de Informática, incluindo parametrização básica para funcionamento do ambiente. Identificação de link de internet dedicado com velocidade nominal de 200 Mbps, destinado ao Laboratório de Informática, com compartilhamento previsto para o Laboratório de Química e o Grêmio Estudantil. 2. Levantamento Técnico e Orientações Durante a vistoria técnica nas dependências da escola, foram identificados 03 (três) pontos adicionais de distribuição de rede de dados, que necessitam de infraestrutura ativa para pleno funcionamento. Diante disso, foi orientada a Direção da Unidade Escolar quanto à necessidade de aquisição dos seguintes equipamentos: 03 (três) switches adicionais; 04 (quatro) Access Points para ampliação da cobertura de rede sem fio. Foi informado que, após a aquisição dos equipamentos mencionados, a Unidade Escolar deverá abrir novo chamado técnico para execução dos serviços complementares e finalização da expansão da rede. 3. Considerações Finais Os serviços executados encontram-se operacionais conforme escopo desta visita técnica. A continuidade da expansão da infraestrutura de rede dependerá da aquisição dos equipamentos recomendados. | K19: 1937600 | L19: Relatorios_Images/69bee1ed.Assinatura_Escola.124120.png | M19: 46084.359 | N19: Gerar PDF
A20: bbf36504 | B20: e26643bf | C20: 46083 | D20: 25043897 | E20: 8aec2db9 | F20: be4898e6 , 54d6fbb6 | G20: Relatorios_Images/bbf36504.Assinatura_Tecnico.155802.png | H20: Análise Técnica | J20: RELATÓRIO TÉCNICO DE ANÁLISE – INFRAESTRUTURA PARA LABORATÓRIO DE INFORMÁTICA Data da análise: 23/02/2026 1. Objetivo Apresentar o resultado da análise técnica realizada na unidade escolar ECIT Cícero dos Anjos – São Vicente do Seridó – GRE4, com a finalidade de verificar as condições de infraestrutura para a implementação de um laboratório de informática. 2. Situação Encontrada Após vistoria técnica realizada na unidade escolar, constatou-se que a instituição dispõe de um espaço físico destinado à implantação de um laboratório de informática, apresentando infraestrutura básica adequada para a instalação dos equipamentos. No local, verificou-se a existência de bancadas apropriadas para acomodação dos computadores, contendo furações padrão para passagem de cabeamento, bem como pontos de energia elétrica devidamente instalados, possibilitando a alimentação elétrica dos equipamentos que venham a compor o laboratório. No entanto, o espaço não conta com aparelho de ar condicionado. No que se refere à infraestrutura de rede, foram identificadas fêmeas de rede instaladas nos pontos de utilização, porém sem a devida crimpagem/conectorização do cabeamento, o que impossibilita, neste momento, o funcionamento da rede lógica. A unidade também possui link de acesso à internet com velocidade de 300 Mbps. Entretanto, considerando a quantidade de setores e usuários existentes na unidade escolar, essa velocidade não se mostra operacional para atender adequadamente toda a demanda de conectividade da escola, sobretudo após a implantação e utilização do laboratório de informática. Quanto à estrutura central de rede, foi identificado rack de piso instalado, contendo 02 (dois) switches Gigalan de 24 portas cada, destinados à distribuição da rede de dados. Observou-se ainda que a distribuição do cabeamento estruturado é realizada por meio de eletrocalhas, instaladas e distribuídas pelas dependências da unidade escolar. 3. Análise Técnica Diante do que foi observado durante a vistoria, verifica-se que a unidade escolar possui infraestrutura física e parte da infraestrutura lógica preparada para a implantação do laboratório de informática. Entretanto, alguns procedimentos técnicos ainda são necessários para viabilizar o funcionamento completo do ambiente. Há necessidade de intervenção técnica especializada para a realização das seguintes atividades: Crimpagem e organização do cabeamento de rede existente; Montagem, instalação e configuração da rede interna de dados; Montagem, instalação e configuração dos computadores que irão compor o laboratório; Realização de testes de conectividade e validação do funcionamento da rede e dos equipamentos. 4. Conclusão Conclui-se que a unidade escolar ECIT Cícero dos Anjos – São Vicente do Seridó – GRE4 possui condições estruturais adequadas para a implantação do laboratório de informática. No entanto, para que o ambiente entre em pleno funcionamento, faz-se necessária a execução das intervenções técnicas mencionadas neste relatório. | M20: 46098.323 | N20: Gerar PDF
A21: 0c021bc1 | B21: e26643bf | C21: 46083 | D21: 25043870 | E21: 8aec2db9 | F21: 54d6fbb6 , be4898e6 | G21: Relatorios_Images/0c021bc1.Assinatura_Tecnico.105443.png | H21: Análise Técnica | J21: RELATÓRIO TÉCNICO DE ANÁLISE – INFRAESTRUTURA PARA LABORATÓRIO DE INFORMÁTICA Unidade Escolar: ECI Maria Francinete de Souza – São Vicente do Seridó – GRE4 Data da análise: 24/02/2026 1. Objetivo Apresentar o resultado da análise técnica realizada na unidade escolar ECI Maria Francinete de Souza – São Vicente do Seridó – GRE4, com a finalidade de verificar as condições de infraestrutura para a implementação de um laboratório de informática. 2. Situação Encontrada Após vistoria técnica realizada na unidade escolar, constatou-se que a instituição dispõe de um espaço físico destinado à implantação de um laboratório de informática, apresentando infraestrutura básica adequada para a instalação dos equipamentos. No local, verificou-se a existência de bancadas adequadas para acomodação dos computadores. Entretanto, as mesmas não possuem as furações padrão destinadas à passagem de cabeamento, o que inviabiliza a instalação adequada dos equipamentos. Tal situação pode ocasionar dificuldades no manuseio dos computadores pelos alunos, além de comprometer a organização e a segurança do cabeamento. Constatou-se, ainda, que os pontos de energia elétrica encontram-se devidamente instalados, possibilitando a alimentação elétrica dos equipamentos que venham a compor o laboratório. No que se refere à infraestrutura de rede, foram identificadas caixas de passagem destinadas à instalação de pontos de rede para conectores RJ-45 fêmea. Entretanto, constatou-se a ausência dos referidos conectores, fato que impossibilita, neste momento, o funcionamento da rede lógica. A unidade também possui link de acesso à internet com velocidade de 250 Mbps. Entretanto, considerando a quantidade de setores e usuários existentes na unidade escolar, essa velocidade não se mostra operacional para atender adequadamente toda a demanda de conectividade da escola, sobretudo após a implantação e utilização do laboratório de informática. Quanto à estrutura central de rede, foi identificado um rack de parede instalado, porém sem a presença de equipamentos de rede responsáveis pela distribuição do sinal para os computadores. Tal situação impossibilita o acesso à rede de dados. Observou-se, ainda, que a distribuição do cabeamento estruturado é realizada por meio de eletrocalhas, devidamente instaladas e distribuídas pelas dependências da unidade escolar. 3. Análise Técnica Diante do que foi observado durante a vistoria, verifica-se que a unidade escolar possui infraestrutura física e parte da infraestrutura lógica preparada para a implantação do laboratório de informática. Entretanto, alguns procedimentos técnicos ainda são necessários para viabilizar o funcionamento completo do ambiente. Há necessidade de intervenção técnica especializada para a realização das seguintes atividades: Instalação dos conectores fêmea RJ-45, crimpagem e organização do cabeamento de rede existente; Montagem, instalação e configuração da rede interna de dados; Montagem, instalação e configuração dos computadores que irão compor o laboratório; Realização de furação nas bancadas, com a criação dos pontos para cada estação, a fim de possibilitar a devida acomodação dos computadores; Realização de testes de conectividade e validação do funcionamento da rede e dos equipamentos. Adicionalmente, recomenda-se avaliação da ampliação da capacidade do link de internet, considerando a demanda da unidade escolar e a futura utilização do laboratório de informática. 4. Conclusão Conclui-se que a unidade escolar ECI Maria Francinete de Souza – São Vicente do Seridó – GRE4 possui condições estruturais adequadas para a implantação do laboratório de informática. Contudo, para que o ambiente entre em pleno funcionamento, faz-se necessária a execução das intervenções técnicas mencionadas neste relatório, bem como a análise da adequação da capacidade do link de internet para atendimento satisfatório de toda a unidade escolar. | M21: 46105.322 | N21: Gerar PDF
A22: eb048320 | C22: 46093 | D22: 25094432 | F22: 16f6798d , 54d6fbb6 | H22: Internet Offline | J22: Equipamento: Roteador (conforme foto anexa). Sintoma: O dispositivo apresenta perda intermitente de conectividade, exigindo o reinício físico (reboot) para a normalização temporária do serviço. Solicitação: Diagnóstico e solução definitiva para evitar a recorrência das quedas, troca do roteador ou a relocação do mesmo para a sala da secretaria. | K22: 6248900 | L22: Relatorios_Images/eb048320.Assinatura_Escola.125302.png | M22: 46093.449
A23: 1d611201 | C23: 46093 | D23: 25094203 | F23: 16f6798d , 54d6fbb6 | H23: Manutenção Corretiva , Internet Offline | J23: Computador DATEN: Identificada falha técnica (conforme fotos em anexo). Procederemos com a abertura de chamado junto ao suporte do fabricante. Rede Opix: Apresentando instabilidade/problemas de conexão. Foi aberto chamado técnico junto à operadora sob numeração: 260312111400. Foto anexada. | K23: 6157165 | L23: Relatorios_Images/1d611201.Assinatura_Escola.165407.png | M23: 46093.579 | N23: Rascunho
A24: 6cf6e5cc | C24: 46093 | D24: 25094181 | F24: 16f6798d | H24: Internet Offline | J24: O link da Tely CODATA foi recolocado para a secretaria. Ficando o Rix apenas para o laboratório de informática | K24: 1875973 | L24: Relatorios_Images/6cf6e5cc.Assinatura_Escola.175137.png | M24: 46094.333 | N24: Gerar PDF
A25: f5abfe9c | C25: 46094 | D25: 25094718 | F25: 16f6798d | H25: Manutenção Preventiva , Instalação de Softwares | J25: Atividades Realizadas Instalação de Hardware: Configuração e instalação de 03 computadores HP EliteDesk na Secretaria da escola. Licenciamento de Software: Ativação do sistema operacional Windows 10 em 02 terminais. Suporte Direção: Instalação e configuração do pacote Microsoft Office 2019 na estação de trabalho da Direção. Pendências e Chamados Manutenção Corretiva: Abertura de chamado técnico para o computador da marca DATEN, que apresenta falha de hardware (equipamento liga, mas não gera imagem/vídeo). | K25: 1944029 | L25: Relatorios_Images/f5abfe9c.Assinatura_Escola.185538.png | M25: 46094.834 | N25: Gerar PDF
A26: b889667d | C26: 46094 | D26: 25094718 | E26: 16f6798d | G26: Relatorios_Images/b889667d.Assinatura_Tecnico.224929.png | H26: Análise Técnica | J26: Atualmente, a infraestrutura conta com os seguintes ativos de rede que demandam conexão cabeada: Secretaria: 05 computadores e 01 impressora. Diretoria: 01 computador. Ponto de Acesso: O link de internet chega via roteador da operadora em uma sala adjacente à diretoria, já dispondo de um cabo de rede (uplink) pronto para distribuição. 2. Solução Proposta Recomenda-se a instalação de um Switch de 16 portas Gigabit (10/100/1000 Mbps). 3. Justificativa Técnica Capacidade de Atendimento: Das 16 portas disponíveis, 08 serão ocupadas de imediato (7 dispositivos + 1 entrada de internet), restando 08 portas livres. Escalabilidade: Essa folga de 50% permite a expansão futura para novos computadores, impressoras de rede ou pontos de acesso Wi-Fi sem a necessidade de novos investimentos em hardware de comutação. Performance: O padrão Gigalan garante que a comunicação interna (troca de arquivos e impressão) ocorra na velocidade máxima permitida pelos equipamentos atuais, evitando gargalos. | M26: 46094.833 | N26: Gerar PDF
A27: 8c3937b9 | C27: 46098 | D27: 25007742 | F27: 16f6798d , 09fd55aa , 14fb10d2 | H27: Manutenção Corretiva , Manutenção Preventiva , Backup de Dados | J27: Relatório de Manutenção: Mini HP (Patrimônio: [Número]) Realizado backup integral dos dados. Instalação do sistema operacional Windows 10. Instalação de softwares essenciais e drivers de sistema. | K27: 1918206 | L27: Relatorios_Images/8c3937b9.Assinatura_Escola.165448.png | M27: 46098.618 | N27: Gerar PDF
A28: de1a8cac | C28: 46098 | D28: 25007742 | E28: 16f6798d | F28: 09fd55aa , 14fb10d2 | G28: Relatorios_Images/de1a8cac.Assinatura_Tecnico.115909.png | H28: Análise Técnica | J28: 1. INTRODUÇÃO O presente documento tem por objetivo registrar as condições físicas e estruturais do Laboratório de Informática da EEEFM Dom Moises Coelho. Através de inspeção visual e registro fotográfico, constatou-se que a unidade encontra-se em estado de desativação crítica, apresentando riscos à saúde e à integridade de qualquer equipamento tecnológico que venha a ser instalado no recinto. 2. ANÁLISE DO CENÁRIO ATUAL As imagens anexas ao processo original revelam um ambiente em avançado estágio de degradação. 3. QUADRO DETALHADO DE DANOS E NECESSIDADES Item / Área Descrição da Patologia Criticidade Ação Necessária Alvenaria Infiltração severa, umidade ascendente e mofo. Alta Impermeabilização e nova pintura. Mobiliário Bancadas podres, quebradas e restos de madeira no piso. Alta Substituição total por bancadas em MDF ou Granito. Elétrica Fiação exposta e ausência de aterramento para TI. Crítica Revisão total da rede e instalação de disjuntores. Lógica Cabos de rede pendurados e sem proteção. Alta Instalação de canaletas e rack de servidores. Climatização Inexistência de controle de temperatura. Alta Instalação de aparelhos de Ar-Condicionado. Higiene Acúmulo de entulho e risco biológico (fungos). Média 4. RISCOS PATRIMONIAIS E À SAÚDE Dano ao Hardware: A umidade excessiva e a instabilidade elétrica causarão a queima imediata de placas-mãe e oxidação de componentes internos de novos computadores. Insalubridade: A presença de bolor e poeira de madeira em decomposição torna o ar impróprio para alunos e professores, podendo causar crises alérgicas e respiratórias. Segurança: O estado das esquadrias não garante a proteção contra furtos de equipamentos de alto valor. 5. CONCLUSÃO E PARECER TÉCNICO Diante do exposto, o laboratório de informática da EEEFM Dom Moises Coelho é considerado INAPTO para receber computadores no momento. A instalação de equipamentos sem a prévia reforma estrutural configuraria dano ao erário e má gestão de recursos públicos, visto que a vida útil do hardware seria drasticamente reduzida pelas condições hostis do ambiente. | M28: 46121.375 | N28: Gerar PDF
A29: e244d3c1 | B29: 9bd7519a | C29: 46099 | D29: 25094556 | F29: be4898e6 , 04531b9c | H29: Manutenção Corretiva , Instalação de Softwares | J29: Foi instalado o Office 2019 em um computador Elitedesk Mini na entrada da coordenação de nome "DESKTOP-F4HTR7E" e tombamento 884475, verificado também o computador Positivo Master C820 MINIPRO, de tombamento 1623223, e constatado o não funcionamento. | K29: 1801643 | M29: 46099.471
A30: d7d9cec5 | C30: 46100 | D30: 25093916 | F30: 6bbd148a , be4898e6 | H30: Cabeamento Estruturado | J30: Foi realizado reparos nos pontos de rede da sala de psicologia e dois pontos na biblioteca e 5 pontos no laboratório de informática | K30: 6571280 | L30: Relatorios_Images/d7d9cec5.Assinatura_Escola.131000.png | M30: 46118.482
A31: 57da1445 | C31: 46101 | D31: 25092898 | F31: 2fc34ae3 , be4898e6 | H31: Manutenção Corretiva , Instalação de Softwares | J31: Foi feito a ativação de um windows 10 e foi relacionado duas formatação. | K31: 894061 | L31: Relatorios_Images/57da1445.Assinatura_Escola.133244.png | M31: 46108.469
A32: 9ce39fd4 | B32: 9bd7519a | C32: 46101 | D32: 25080849 | F32: 2fc34ae3 , be4898e6 | H32: Instalação de Softwares , Cabeamento Estruturado | J32: Foi realizado a montagem de 10 computadores . Todos estão com mouse Teclado Monitor CPU Cabo VGA Infelizmente está faltando os cabos de energia tanso o do monitor quanto o da CPU. Está faltando 20 cabos de energia padrão novo(cabo de força) O laboratório de informática está sendo dividida com o da robotica. | M32: 46101.638
A33: aa8dc0c1 | C33: 46101 | D33: 25093835 | F33: 2fc34ae3 , be4898e6 | H33: Instalação de Softwares , Cabeamento Estruturado | J33: Foi instalado 10 computadores HP. Ficou faltando 20 cabos de energia do padrão novo para poder finalizar a instalação, a sala já possui pontos de redes , a sala de informática está sendo dividida com o laboratório bde robótica. | K33: 1942956 | L33: Relatorios_Images/aa8dc0c1.Assinatura_Escola.183738.png | M33: 46107.294
A34: 199da9cb | C34: 46102 | D34: 25007726 | E34: 16f6798d | F34: 09fd55aa , 14fb10d2 | G34: Relatorios_Images/199da9cb.Assinatura_Tecnico.115334.png | H34: Análise Técnica | J34: RELATÓRIO SOBRE A SITUAÇÃO DO LABORATÓRIO DE INFORMÁTICA DA ECI EEFM PROFESSOR CRISPIM COELHO. O presente relatório tem por finalidade apresentar a situação atual do laboratório de informática da ECI EEFM PROFESSOR CRISPIM COELHO, destacando suas condições de funcionamento, a estrutura disponível e as principais necessidades de manutenção identificadas no espaço. Atualmente, o laboratório conta com 05 (cinco) computadores Mini HP em funcionamento, todos instalados e conectados à internet por meio de cabeamento de rede. Os equipamentos encontram-se em condições de uso após a realização de procedimentos técnicos de formatação, executados com o objetivo de corrigir problemas de lentidão que estavam comprometendo o desempenho das máquinas. Durante a verificação dos computadores, constatou-se que os equipamentos apresentavam baixo rendimento, o que dificultava sua utilização nas atividades desenvolvidas pela escola. Além disso, em um dos computadores, os funcionários da unidade não possuíam a senha de acesso ao sistema, situação que impossibilitava o uso regular da máquina. Diante desse cenário, foi necessária a formatação dos 05 (cinco) computadores, procedimento que contribuiu para a melhoria do desempenho e para o restabelecimento de condições adequadas de funcionamento. Apesar dos avanços obtidos com a manutenção dos computadores, ainda foram identificadas necessidades relacionadas à infraestrutura de rede do laboratório. Durante os testes realizados, observou-se que 01 (um) dos 05 (cinco) computadores não conseguiu estabelecer conexão com a rede, mesmo estando conectado por cabo. Tal situação indica a possibilidade de falha em cabo de rede, conector ou ponto da rede lógica, tornando necessária uma avaliação técnica mais detalhada da estrutura de cabeamento. Ressalta-se que o laboratório possui capacidade estrutural para receber até 20 (vinte) computadores, dispondo, inclusive, de cabeamento instalado para essa quantidade de equipamentos. No entanto, para que essa capacidade seja plenamente aproveitada, faz-se indispensável a realização de manutenção preventiva e corretiva na rede, assegurando o adequado funcionamento de todos os pontos de conexão existentes. Dessa forma, verifica-se que o laboratório de informática da Escola Crispim Coelho apresenta condições parciais de funcionamento, uma vez que os computadores atualmente disponíveis estão operando de forma satisfatória após a formatação, mas ainda persistem limitações na infraestrutura de rede que precisam ser sanadas. A manutenção dos cabos e da rede lógica é medida necessária para garantir maior estabilidade no acesso à internet, ampliar a utilização do espaço e possibilitar, futuramente, a instalação de novos equipamentos. Conclui-se, portanto, que o laboratório possui potencial para melhor atender às demandas pedagógicas e administrativas da escola, desde que sejam adotadas providências voltadas à manutenção da rede e à adequação completa de sua infraestrutura tecnológica. A resolução dessas necessidades contribuirá significativamente para o fortalecimento das atividades educacionais desenvolvidas com o uso dos recursos de informática. | M34: 46121.373 | N34: Gerar PDF
A35: 05b6971f | C35: 46102 | D35: 25007718 | E35: 16f6798d | F35: 09fd55aa , 14fb10d2 | G35: Relatorios_Images/05b6971f.Assinatura_Tecnico.120245.png | H35: Análise Técnica | J35: A EEEFM Professor Manoel Mangueira Lima, localizada na cidade de Cajazeiras, encontra-se com o laboratório de informática em funcionamento normal, operando atualmente por meio de conexão Wi-Fi, com 18 computadores da marca Daten em uso. No entanto, a parte da infraestrutura cabeada ainda necessita de adequações, uma vez que os cabos de rede instalados são curtos e não alcançam a altura das bancadas, impossibilitando a conexão direta aos computadores de forma adequada. Dessa forma, embora o laboratório esteja funcionando regularmente por meio da rede sem fio, torna-se necessária a realização de ajustes na estrutura de cabeamento, a fim de garantir melhores condições de uso e possibilitar o pleno aproveitamento da conectividade cabeada no espaço. | M35: 46121.38 | N35: Gerar PDF
A36: a79d7d64 | B36: e26643bf | C36: 46078 | D36: 25047116 | E36: 8aec2db9 | F36: 54d6fbb6 , be4898e6 | G36: Relatorios_Images/a79d7d64.Assinatura_Tecnico.104423.png | H36: Análise Técnica | J36: RELATÓRIO TÉCNICO DE ANÁLISE – INFRAESTRUTURA PARA LABORATÓRIO DE INFORMÁTICA Data da análise: 25/02/2026 1. Objetivo Apresentar o resultado da análise técnica realizada na unidade escolar ECI Mario Oliveira Chaves – São João do Tigre – GRE5, com a finalidade de verificar as condições de infraestrutura para a implementação de um laboratório de informática. 2. Situação Encontrada Após vistoria técnica realizada na unidade escolar, constatou-se que a instituição dispõe de um espaço físico destinado à implantação de um laboratório de informática, apresentando infraestrutura básica adequada para a instalação dos equipamentos. No local, verificou-se a existência de bancadas apropriadas para acomodação dos computadores, contendo furações padrão para passagem de cabeamento. No entanto, como pode ser evidenciado nas imagens, pelo tamanho das bancadas e disposição das furações, só há possibilidade de instalação de dois computadores em cada bancada. Há pontos de energia elétrica devidamente instalados, possibilitando a alimentação elétrica dos equipamentos que venham a compor o laboratório. O espaço conta com dois aparelhos de ar condicionado. No que se refere à infraestrutura de rede, foram identificadas fêmeas de rede instaladas nos pontos de utilização, porém sem a devida crimpagem/conectorização do cabeamento, o que impossibilita, neste momento, o funcionamento da rede lógica. A unidade também possui link de acesso à internet com velocidade de 400 Mbps. Entretanto, considerando a quantidade de setores e usuários existentes na unidade escolar, essa velocidade não se mostra operacional para atender adequadamente toda a demanda de conectividade da escola, sobretudo após a implantação e utilização do laboratório de informática. Quanto à estrutura central de rede, foi identificado rack de parede instalado, contendo 01 (um) switch Gigalan de 24 portas, destinados à distribuição da rede de dados. Observou-se ainda que a distribuição do cabeamento estruturado é realizada por meio de eletrocalhas, instaladas e distribuídas pelas dependências da unidade escolar. 3. Análise Técnica Diante do que foi observado durante a vistoria, verifica-se que a unidade escolar possui infraestrutura física e parte da infraestrutura lógica preparada para a implantação do laboratório de informática. Entretanto, alguns procedimentos técnicos ainda são necessários para viabilizar o funcionamento completo do ambiente. Há necessidade de intervenção técnica especializada para a realização das seguintes atividades: Crimpagem e organização do cabeamento de rede existente; Montagem, instalação e configuração da rede interna de dados; Montagem, instalação e configuração dos computadores que irão compor o laboratório; Realização de furação adicional nas bancadas, com a criação de mais um ponto por estação, a fim de possibilitar a acomodação de um computador adicional por bancada; Realização de testes de conectividade e validação do funcionamento da rede e dos equipamentos. Adicionalmente, recomenda-se avaliação da ampliação da capacidade do link de internet, considerando a demanda da unidade escolar e a futura utilização do laboratório de informática. 4. Conclusão Conclui-se que a unidade escolar ECI Mario Oliveira Chaves – São João do Tigre – GRE5 possui condições estruturais adequadas para a implantação do laboratório de informática. No entanto, para que o ambiente entre em pleno funcionamento, faz-se necessária a execução das intervenções técnicas mencionadas neste relatório. | M36: 46105.322 | N36: Gerar PDF
A37: 797862d8 | C37: 46118 | D37: 25054023 | E37: 16f6798d | F37: 14fb10d2 , 94f6e6b3 | G37: Relatorios_Images/797862d8.Assinatura_Tecnico.190356.png | H37: Análise Técnica | J37: Após análise das condições estruturais da Escola ECIT Profº Neir Alves Porto, localizada no município de Santo André, constatou-se que a unidade escolar dispõe de laboratório de informática com infraestrutura física adequada para implantação e funcionamento de, no mínimo, 20 computadores. O espaço destinado ao laboratório apresenta condições favoráveis para a instalação dos equipamentos, contando com ambiente organizado, estrutura compatível e requisitos básicos que possibilitam sua utilização para fins pedagógicos e administrativos. Verifica-se, portanto, que a instituição já possui base estrutural suficiente para viabilizar o funcionamento do laboratório de informática, demonstrando preparo prévio para receber os equipamentos necessários ao desenvolvimento das atividades educacionais. Entretanto, apesar da infraestrutura existente estar apta para uso, observa-se que o laboratório ainda não pode operar plenamente em razão da ausência dos computadores. Tal situação compromete a efetiva implementação de práticas pedagógicas mediadas por tecnologia, limitando o acesso dos estudantes e docentes a recursos digitais essenciais ao processo de ensino-aprendizagem. Ressalta-se que a disponibilização de equipamentos de informática é medida indispensável para garantir a utilização integral do espaço já estruturado, bem como para promover inclusão digital e ampliação das oportunidades educacionais oferecidas pela escola. A inexistência desses computadores impede o desenvolvimento de aulas práticas, pesquisas, atividades interativas, projetos de capacitação tecnológica e demais ações voltadas ao fortalecimento das competências digitais dos alunos. Nesse contexto, considerando que a unidade já dispõe da infraestrutura necessária, conclui-se que a principal demanda atual consiste no fornecimento de, no mínimo, 20 computadores para composição do laboratório de informática. Dessa forma, sob o ponto de vista técnico, entende-se que a destinação dos referidos equipamentos é plenamente justificável e necessária, a fim de assegurar o adequado aproveitamento da estrutura existente e viabilizar o pleno funcionamento do laboratório. | M37: 46121.604 | N37: Gerar PDF
A38: c1ea01c8 | C38: 46118 | D38: 25063340 | E38: 16f6798d | F38: 14fb10d2 , 94f6e6b3 | G38: Relatorios_Images/c1ea01c8.Assinatura_Tecnico.190515.png | H38: Análise Técnica | J38: Após análise das condições estruturais da ECIT Monsenhor José Borges de Carvalho, localizada no município de Alagoa Nova, constatou-se que a unidade escolar dispõe de laboratório de informática devidamente instalado e pronto para utilização. O ambiente apresenta condições físicas adequadas para o desenvolvimento de atividades pedagógicas mediadas por tecnologia, contando inclusive com rack e switch já instalados para a distribuição de rede cabeada. Tal estrutura demonstra que a escola possui parte significativa dos requisitos necessários para o funcionamento regular do laboratório de informática, o que representa importante avanço no suporte às ações educacionais. Entretanto, foi verificada uma limitação de ordem técnica que impede o pleno funcionamento do espaço em sua capacidade total. A rede elétrica atualmente existente não comporta, de forma segura e eficiente, o funcionamento simultâneo de todos os computadores e do sistema de ar-condicionado do laboratório. Essa condição compromete a utilização integral do ambiente, gerando restrições operacionais que impactam diretamente o uso pedagógico adequado dos equipamentos. Dessa forma, torna-se necessária a realização de melhorias na infraestrutura elétrica da unidade, com vistas a garantir maior capacidade de carga, segurança no uso dos equipamentos e estabilidade no funcionamento do laboratório. Além da adequação da rede elétrica, verificou-se também a necessidade de disponibilização de um link de internet específico para o laboratório de informática. A implantação desse link é essencial para assegurar conectividade adequada às atividades educacionais, permitindo acesso a plataformas digitais, pesquisas, sistemas pedagógicos e demais recursos tecnológicos indispensáveis ao processo de ensino-aprendizagem. Ressalta-se que a existência prévia de rack e switch favorece a implementação da rede cabeada, restando, portanto, a disponibilização da conexão de internet para viabilizar o uso pleno dessa estrutura. Nesse contexto, conclui-se que, embora o laboratório esteja fisicamente pronto para uso, sua operação integral depende da execução de melhorias na parte elétrica e da instalação de link de internet adequado ao atendimento da demanda da unidade escolar. Sob o ponto de vista técnico, tais intervenções mostram-se indispensáveis para assegurar condições satisfatórias de funcionamento, segurança operacional e aproveitamento pleno do laboratório de informática. Diante do exposto, este parecer é favorável à realização das adequações necessárias, considerando que as medidas propostas contribuirão para a modernização do ambiente escolar, para a ampliação do acesso às tecnologias educacionais e para a melhoria da qualidade do ensino ofertado aos estudantes. | M38: 46120.671 | N38: Gerar PDF
A39: f9e703cf | C39: 46118 | D39: 25063421 | E39: 16f6798d | F39: 14fb10d2 , 94f6e6b3 | G39: Relatorios_Images/f9e703cf.Assinatura_Tecnico.172459.png | H39: Análise Técnica | J39: Após análise da situação apresentada pela EEEFM Profº Cardoso, localizada no município de Alagoa Nova, verificou-se que a unidade escolar, até o presente momento, não dispõe de laboratório de informática instalado e em funcionamento. Entretanto, em diálogo realizado com a gestão escolar, foi informado que a instituição possui um espaço passível de adequação para essa finalidade, sendo este atualmente utilizado como sala dos professores. De acordo com a avaliação preliminar, o referido ambiente apresenta dimensões compatíveis para a instalação de um laboratório de informática com capacidade estimada entre 10 e 15 computadores. Tal possibilidade demonstra viabilidade inicial para a implantação do espaço, desde que sejam executadas as intervenções estruturais e tecnológicas necessárias para sua adequada implementação. Ressalta-se que, para a transformação do ambiente em laboratório de informática, será indispensável a realização de toda a infraestrutura necessária ao funcionamento do setor. Entre os itens essenciais, destaca-se a necessidade de instalação de bancada apropriada para acomodação dos equipamentos, bem como a implantação de rack e switch com capacidade mínima de 24 portas Gigalan, de modo a garantir organização e eficiência na distribuição da rede. Além disso, será necessária a execução de cabeamento estruturado, contemplando pontos de rede e adequações compatíveis com a demanda prevista para o ambiente. No que se refere à conectividade, observa-se a possibilidade técnica de instalação de um novo link de internet no espaço designado para o laboratório, assegurando maior autonomia e desempenho no uso dos recursos digitais. Alternativamente, poderá ser avaliada a viabilidade de extensão do link atualmente existente na sala da secretaria, localizada ao lado do ambiente que possivelmente será destinado ao laboratório de informática. A definição da solução mais adequada deverá considerar critérios técnicos de estabilidade, desempenho da rede, segurança da informação e atendimento satisfatório às atividades pedagógicas a serem desenvolvidas no local. Dessa forma, conclui-se que a unidade escolar possui potencial para implantação de laboratório de informática, uma vez que há espaço físico disponível e com capacidade compatível para essa finalidade. Todavia, para que o ambiente possa entrar em funcionamento de forma adequada, será imprescindível a execução completa da infraestrutura física e lógica necessária ao projeto. Sob o ponto de vista técnico, a implantação do laboratório mostra-se plenamente justificável, considerando a importância da inclusão digital no ambiente escolar e a necessidade de ampliação do acesso dos estudantes às tecnologias educacionais. Assim, este parecer é favorável à implantação do laboratório de informática na unidade, condicionado à realização das adequações estruturais, elétricas, lógicas e de conectividade necessárias ao pleno funcionamento do espaço. Por fim, destaca-se que a concretização dessa ação contribuirá significativamente para o fortalecimento das práticas pedagógicas, para a modernização da escola e para a melhoria das condições de ensino e aprendizagem ofertadas à comunidade escolar. | M39: 46121.601 | N39: Gerar PDF
A40: 0e5dec56 | C40: 46118 | D40: 25062069 | E40: 16f6798d | F40: 14fb10d2 , 94f6e6b3 | G40: Relatorios_Images/0e5dec56.Assinatura_Tecnico.172711.png | H40: Análise Técnica | J40: Após verificação das condições apresentadas pela Escola ECI Maria José de Souza, localizada no município de Montadas, constatou-se que a unidade escolar dispõe de equipamentos de informática já disponíveis para utilização, sendo 7 computadores da marca HP e 18 computadores da marca Datem, além de link de internet instalado para atendimento das demandas do ambiente. Observa-se, portanto, que a escola já possui parte significativa dos recursos necessários para o funcionamento de um laboratório de informática, o que representa condição favorável para o desenvolvimento de atividades pedagógicas mediadas por tecnologia. Entretanto, durante a análise técnica, foram identificadas inconsistências na infraestrutura física e elétrica do espaço, as quais comprometem a utilização adequada, segura e funcional dos equipamentos disponíveis. No que se refere à instalação elétrica, verificou-se que foram disponibilizadas apenas 3 tomadas por bancada, quantitativo insuficiente para atender de forma satisfatória à demanda dos computadores a serem utilizados no ambiente, considerando que o adequado seria a disponibilização de 6 tomadas por bancada. Além da quantidade insuficiente, constatou-se também inadequação quanto ao local de instalação dessas tomadas, uma vez que foram fixadas na parede, quando tecnicamente o mais apropriado seria sua instalação diretamente nas bancadas, de modo a facilitar o uso dos equipamentos e garantir melhor organização do espaço. Situação semelhante foi observada na infraestrutura de rede cabeada, onde também foram instalados apenas 3 pontos por bancada, igualmente posicionados na parede, em vez de serem disponibilizados diretamente nas bancadas de trabalho. Tal configuração prejudica a funcionalidade do laboratório, dificulta a organização dos cabos e compromete a praticidade no uso cotidiano dos computadores pelos alunos e professores. Durante a vistoria, verificou-se ainda a utilização de extensões elétricas para possibilitar o funcionamento dos computadores, solução esta adotada em razão da ausência de tomadas instaladas nas bancadas e da insuficiência dos pontos elétricos disponíveis no local adequado. Ressalta-se que o uso contínuo de extensões elétricas não é a solução mais indicada para ambientes escolares de informática, tendo em vista os riscos relacionados à segurança, à sobrecarga elétrica, à durabilidade dos equipamentos e à organização do espaço físico. Diante desse cenário, conclui-se que, embora a unidade escolar já possua computadores e conectividade com a internet, a infraestrutura elétrica e de rede cabeada necessita de adequações para atender de forma correta e segura à demanda do laboratório. Faz-se necessária, portanto, a ampliação da quantidade de tomadas elétricas por bancada, com sua devida realocação para a estrutura das bancadas, bem como a readequação dos pontos de rede cabeada, observando a mesma lógica de distribuição e posicionamento. Tais intervenções são indispensáveis para assegurar melhores condições de funcionamento, maior segurança operacional, organização do ambiente e pleno aproveitamento dos recursos tecnológicos já existentes na escola. Sob o ponto de vista técnico, as adequações aqui apontadas mostram-se plenamente justificáveis e necessárias para a regularização da infraestrutura do laboratório de informática. Dessa forma, este parecer é favorável à realização das correções na parte elétrica e lógica do ambiente, a fim de viabilizar o uso adequado dos equipamentos já disponíveis e garantir melhores condições para o desenvolvimento das atividades pedagógicas. Por fim, destaca-se que a implementação dessas melhorias contribuirá diretamente para a modernização do espaço escolar, para a segurança no uso dos equipamentos e para o fortalecimento das ações de inclusão digital e apoio ao processo de ensino-aprendizagem. | M40: 46121.603 | N40: Gerar PDF
A41: 47568db9 | B41: d4897c65 | C41: 46119 | D41: 25080849 | F41: 4aca042e , 54d6fbb6 , be4898e6 | H41: Manutenção Corretiva , Cabeamento Estruturado | J41: Foi realizado a troca de rack de pé para um rack de parede, foi instalado dois swicht s de 24 portas um cisco e um Dlink, Identificamos q a escola tem 72 pontos de rede mas a escola só possui equipamento para 48 pontos de rede, informamos a escola para adquirir equipamento para conectar o resto dos pontos, foi feito a ativação dos cabos de rede da parte administrativa e do laboratório de informática, no laboratório ficou 2 computador no wi-fi, pois os conectores femia do RJ46 estavam danificado. Foi instalado um rotiador tp-link. | K41: 1766511 | L41: Relatorios_Images/47568db9.Assinatura_Escola.192847.png | M41: 46119.668
A42: 46e388fe | C42: 46121 | D42: 25087304 | E42: 16f6798d | F42: 14fb10d2 , 94f6e6b3 | G42: Relatorios_Images/46e388fe.Assinatura_Tecnico.112348.png | H42: Análise Técnica | J42: Este relatório tem como objetivo apresentar a situação atual do laboratório de informática da ECI José Wilson de Albuquerque Melo, localizada no município de Capim. A escola encontra-se com laboratório de informática, porém, até o presente momento, dispõe de apenas 7 computadores para compor esse espaço. A sala destinada ao laboratório já possui estrutura básica instalada, incluindo cabeamento adequado e acesso à internet, o que demonstra um avanço importante para o funcionamento do ambiente. Entretanto, apesar de a sala contar com essa estrutura, o espaço não está sendo utilizado exclusivamente como laboratório de informática. Em razão de problemas apresentados em outras salas da unidade escolar, o ambiente precisou ser utilizado temporariamente como sala de aula, a fim de atender às necessidades imediatas da escola. Diante dessa situação, os computadores que haviam sido instalados no local precisaram ser desmontados. Posteriormente, os equipamentos foram transferidos para o laboratório de ciências, onde permanecem armazenados de forma provisória, até que seja possível reorganizar os espaços escolares e restabelecer a finalidade original da sala. Assim, verifica-se que a implantação do laboratório de informática já está concluida, contando inclusive com parte da infraestrutura necessária. No entanto, seu funcionamento efetivo ainda depende da resolução dos problemas estruturais enfrentados pela escola, bem como da liberação definitiva da sala para uso exclusivo das atividades de informática. Dessa forma, conclui-se que a unidade escolar possui condições, mas ainda enfrenta limitações que impedem, neste momento, sua plena utilização. | M42: 46121.605 | N42: Gerar PDF
A43: d792546f | B43: bb85f3f0 | C43: 46154 | D43: 8 | F43: 2fc34ae3 , be4898e6 | H43: Manutenção Corretiva | J43: Indentificamos que a internet está oscilando, abrimos chamado com a operadora para q realize o reparo do sinal, Foi entregue um notebook Dell para a gerente Nayara Tombamento 01373435 | K43: 1935356 | L43: Relatorios_Images/d792546f.Assinatura_Escola.122156.png | M43: 46154.382

Sheet Fotos_Relatorio
A1: Id_Foto | B1: Id_Relatorio | C1: Imagem | D1: Legenda
A2: 5be47087 | B2: ec91dca7 | C2: Fotos_Relatorio_Images/5be47087.Imagem.125229.jpg | D2: Reinstalação do office
A3: c009545b | B3: ec91dca7 | C3: Fotos_Relatorio_Images/c009545b.Imagem.133109.jpg | D3: Computador levado para ser formatado, lentidão no HD e não instalando
A4: 788cc3bf | B4: 80d9fd4a | C4: Fotos_Relatorio_Images/788cc3bf.Imagem.135919.jpg | D4: Fonte queimada
A5: a7165815 | B5: d20ca6dd | C5: Fotos_Relatorio_Images/a7165815.Imagem.185344.jpg
A6: b6315974 | B6: 2d983fab | C6: Fotos_Relatorio_Images/b6315974.Imagem.123922.jpg | D6: Computador
A7: 36f0fcca | B7: 2d983fab | C7: Fotos_Relatorio_Images/36f0fcca.Imagem.124917.jpg
A8: 0050fca0 | B8: 4bc0c752 | C8: Fotos_Relatorio_Images/0050fca0.Imagem.143302.jpg | D8: Vídeo 4k
A9: 34c50708 | B9: be11ab15 | C9: Fotos_Relatorio_Images/34c50708.Imagem.131826.jpg | D9: Ponto rede
A10: 1e2b62f6 | B10: be11ab15 | C10: Fotos_Relatorio_Images/1e2b62f6.Imagem.131930.jpg | D10: DATEN 18 computadores lab01
A11: 1985d5e6 | B11: be11ab15 | C11: Fotos_Relatorio_Images/1985d5e6.Imagem.131938.jpg | D11: Rack
A12: af168f7a | B12: be11ab15 | C12: Fotos_Relatorio_Images/af168f7a.Imagem.132347.jpg | D12: Corredor a direita, visão do fundo (7 salas)
A13: 6bdfaf47 | B13: be11ab15 | C13: Fotos_Relatorio_Images/6bdfaf47.Imagem.132355.jpg | D13: Corredor a esquerda (4 salas)
A14: 48393e0b | B14: be11ab15 | C14: Fotos_Relatorio_Images/48393e0b.Imagem.132919.jpg | D14: Posição meio da escola
A15: 4f546966 | B15: be11ab15 | C15: Fotos_Relatorio_Images/4f546966.Imagem.133135.jpg | D15: Laboratório ao lado
A16: ef02121e | B16: be11ab15 | C16: Fotos_Relatorio_Images/ef02121e.Imagem.135613.jpg | D16: Tely na secretaria
A17: c456b249 | B17: 1b9303f3 | C17: Fotos_Relatorio_Images/c456b249.Imagem.183450.jpg | D17: Oi no pátio com a fibra desligada.
A18: a7f4d06a | B18: 1b9303f3 | C18: Fotos_Relatorio_Images/a7f4d06a.Imagem.183458.jpg | D18: Oi no laboratório de informática.
A19: 14ead9c9 | B19: 41746962 | C19: Fotos_Relatorio_Images/14ead9c9.Imagem.132547.jpg
A20: ca84e226 | B20: d7b2c7cf | C20: Fotos_Relatorio_Images/ca84e226.Imagem.141236.jpg | D20: Troca de usuário administrador
A21: 032e9c72 | B21: d7b2c7cf | C21: Fotos_Relatorio_Images/032e9c72.Imagem.141243.jpg | D21: Velocidade de internet
A22: fac634ae | B22: d7b2c7cf | C22: Fotos_Relatorio_Images/fac634ae.Imagem.141357.jpg | D22: Usuário criado
A23: 484ae5cc | B23: 2ddf654d | C23: Fotos_Relatorio_Images/484ae5cc.Imagem.174507.jpg | D23: Velocidade CODATA em computador via wi-fi.
A24: a99f9d67 | B24: 2ddf654d | C24: Fotos_Relatorio_Images/a99f9d67.Imagem.174517.jpg | D24: Velocidade CODATA
A25: 9ece570b | B25: 2ddf654d | C25: Fotos_Relatorio_Images/9ece570b.Imagem.174525.jpg | D25: Rede wi-fi da secretaria
A26: 266c2496 | B26: f5efc0ea | C26: Fotos_Relatorio_Images/266c2496.Imagem.123505.jpg | D26: Zte ligava no TP-Link, foi retirado e ligado o CODATA no mesmo
A27: db70d78b | B27: f5efc0ea | C27: Fotos_Relatorio_Images/db70d78b.Imagem.123513.jpg | D27: Link CODATA
A28: 00a7e006 | B28: f5efc0ea | C28: Fotos_Relatorio_Images/00a7e006.Imagem.123522.jpg | D28: Internet do link do ZTE,
A29: 1883d7b7 | B29: f5efc0ea | C29: Fotos_Relatorio_Images/1883d7b7.Imagem.123530.jpg | D29: Link pago com recursos próprios
A30: 2a18b376 | B30: 07af17fa | C30: Fotos_Relatorio_Images/2a18b376.Imagem.133527.jpg
A31: 0bb9743a | B31: 07af17fa | C31: Fotos_Relatorio_Images/0bb9743a.Imagem.133535.jpg
A32: 0f7a0dc6 | B32: 07af17fa | C32: Fotos_Relatorio_Images/0f7a0dc6.Imagem.133545.jpg | D32: Link com a fibra é a oi, porém fortinet foi retirado.
A33: 27fbf08c | B33: 07af17fa | C33: Fotos_Relatorio_Images/27fbf08c.Imagem.133554.jpg
A34: 13bd5b69 | B34: 2359b68b | C34: Fotos_Relatorio_Images/13bd5b69.Imagem.180012.jpg
A35: 436a620f | B35: 2359b68b | C35: Fotos_Relatorio_Images/436a620f.Imagem.122805.jpg
A36: 7e532f09 | B36: 2359b68b | C36: Fotos_Relatorio_Images/7e532f09.Imagem.122816.jpg
A37: ba8f9285 | B37: 035147c5 | C37: Fotos_Relatorio_Images/ba8f9285.Imagem.143551.jpg
A38: 71cb5388 | B38: 035147c5 | C38: Fotos_Relatorio_Images/71cb5388.Imagem.143559.jpg
A39: 33b640ce | B39: 035147c5 | C39: Fotos_Relatorio_Images/33b640ce.Imagem.143607.jpg
A40: 0ac47373 | B40: e4f5579b | C40: Fotos_Relatorio_Images/0ac47373.Imagem.134732.jpg | D40: Conversa com suporte da Tely
A41: 3aa63fcd | B41: d20ca6dd | C41: Fotos_Relatorio_Images/3aa63fcd.Imagem.185355.jpg
A42: b5ec0ef4 | B42: d20ca6dd | C42: Fotos_Relatorio_Images/b5ec0ef4.Imagem.185402.jpg
A43: 966799c0 | B43: bbf36504 | C43: Fotos_Relatorio_Images/966799c0.Imagem.154847.jpg
A44: 262f1f94 | B44: bbf36504 | C44: Fotos_Relatorio_Images/262f1f94.Imagem.154901.jpg
A45: d09d853d | B45: bbf36504 | C45: Fotos_Relatorio_Images/d09d853d.Imagem.154907.jpg
A46: ad0fec6a | B46: bbf36504 | C46: Fotos_Relatorio_Images/ad0fec6a.Imagem.154912.jpg
A47: 8390d4fb | B47: bbf36504 | C47: Fotos_Relatorio_Images/8390d4fb.Imagem.154919.jpg
A48: e04a2f88 | B48: bbf36504 | C48: Fotos_Relatorio_Images/e04a2f88.Imagem.154925.jpg
A49: ec86eaff | B49: bbf36504 | C49: Fotos_Relatorio_Images/ec86eaff.Imagem.154934.jpg
A50: 9b74aee2 | B50: bbf36504 | C50: Fotos_Relatorio_Images/9b74aee2.Imagem.154942.jpg
A51: 1321235a | B51: eb048320 | C51: Fotos_Relatorio_Images/1321235a.Imagem.125313.jpg
A52: 6e9a01ec | B52: 1d611201 | C52: Fotos_Relatorio_Images/6e9a01ec.Imagem.133634.jpg
... A54: 273f84f5 | B54: 6cf6e5cc | C54: Fotos_Relatorio_Images/273f84f5.Imagem.175154.jpg
A55: 4ad8018e | B55: f5abfe9c | C55: Fotos_Relatorio_Images/4ad8018e.Imagem.191550.jpg | D55: Tombamento DATEN com defeito
A56: cdc55ce3 | B56: f5abfe9c | C56: Fotos_Relatorio_Images/cdc55ce3.Imagem.191622.jpg | D56: Número de serie de DATEN com defeito
A57: a09f76a7 | B57: b889667d | C57: Fotos_Relatorio_Images/a09f76a7.Imagem.224925.jpg | D57: Roteador da operadora
A58: a3cc64c8 | B58: b889667d | C58: Fotos_Relatorio_Images/a3cc64c8.Imagem.225014.jpg | D58: Secretaria, porta a esquerda é a direção.
A59: 8f2435d1 | B59: b889667d | C59: Fotos_Relatorio_Images/8f2435d1.Imagem.225117.jpg
A60: 0155bb19 | B60: b889667d | C60: Fotos_Relatorio_Images/0155bb19.Imagem.225741.jpg
A61: e399bdbf | B61: bbf36504 | C61: Fotos_Relatorio_Images/e399bdbf.Imagem.104431.jpg
A62: c27f5539 | B62: bbf36504 | C62: Fotos_Relatorio_Images/c27f5539.Imagem.104435.jpg
A63: fc9e0faa | B63: bbf36504 | C63: Fotos_Relatorio_Images/fc9e0faa.Imagem.104439.jpg
A64: f85f1b7e | B64: bbf36504 | C64: Fotos_Relatorio_Images/f85f1b7e.Imagem.104442.jpg
A65: b386bf0a | B65: bbf36504 | C65: Fotos_Relatorio_Images/b386bf0a.Imagem.104447.jpg
A66: 37fabc1e | B66: 0c021bc1 | C66: Fotos_Relatorio_Images/37fabc1e.Imagem.105153.jpg
A67: 69ec5bc5 | B67: 0c021bc1 | C67: Fotos_Relatorio_Images/69ec5bc5.Imagem.105209.jpg
A68: b78e603a | B68: 0c021bc1 | C68: Fotos_Relatorio_Images/b78e603a.Imagem.105216.jpg
A69: 6f130ca7 | B69: 0c021bc1 | C69: Fotos_Relatorio_Images/6f130ca7.Imagem.105224.jpg
A70: e59b016a | B70: 0c021bc1 | C70: Fotos_Relatorio_Images/e59b016a.Imagem.105232.jpg
... A76: b8f5dad5 | B76: 0c021bc1 | C76: Fotos_Relatorio_Images/b8f5dad5.Imagem.105321.jpg
A77: 8314d2c9 | B77: 8c3937b9 | C77: Fotos_Relatorio_Images/8314d2c9.Imagem.151837.jpg | D77: Patrimônio
A78: b76c53b0 | B78: 8c3937b9 | C78: Fotos_Relatorio_Images/b76c53b0.Imagem.151845.jpg | D78: Backup
A79: 16d6e5fe | B79: de1a8cac | C79: Fotos_Relatorio_Images/16d6e5fe.Imagem.210557.jpg
A80: 3c7eea51 | B80: de1a8cac | C80: Fotos_Relatorio_Images/3c7eea51.Imagem.210610.jpg
A81: cc101bfc | B81: e244d3c1 | C81: Fotos_Relatorio_Images/cc101bfc.Imagem.141731.jpg | D81: Computador com defeito
A82: 744d49a6 | B82: e244d3c1 | C82: Fotos_Relatorio_Images/744d49a6.Imagem.141739.jpg | D82: Computador da coordenação
A83: ef5e82c2 | B83: d7d9cec5 | C83: Fotos_Relatorio_Images/ef5e82c2.Imagem.131011.jpg
A84: 0cdfdea8 | B84: d7d9cec5 | C84: Fotos_Relatorio_Images/0cdfdea8.Imagem.131018.jpg
A85: b0c06096 | B85: d7d9cec5 | C85: Fotos_Relatorio_Images/b0c06096.Imagem.131025.jpg
A86: bbfcbd34 | B86: d7d9cec5 | C86: Fotos_Relatorio_Images/bbfcbd34.Imagem.131033.jpg
A87: 2928e9ac | B87: 57da1445 | C87: Fotos_Relatorio_Images/2928e9ac.Imagem.133020.jpg
A88: b07f5a7d | B88: 57da1445 | C88: Fotos_Relatorio_Images/b07f5a7d.Imagem.133029.jpg
A89: 1cde4154 | B89: 57da1445 | C89: Fotos_Relatorio_Images/1cde4154.Imagem.133254.jpg
A90: d04241bb | B90: 57da1445 | C90: Fotos_Relatorio_Images/d04241bb.Imagem.133302.jpg
A91: 17a50980 | B91: 57da1445 | C91: Fotos_Relatorio_Images/17a50980.Imagem.133310.jpg
A92: 1fa441f8 | B92: aa8dc0c1 | C92: Fotos_Relatorio_Images/1fa441f8.Imagem.183746.jpg
A93: 957afa1f | B93: aa8dc0c1 | C93: Fotos_Relatorio_Images/957afa1f.Imagem.183755.jpg
A94: 56782dd0 | B94: aa8dc0c1 | C94: Fotos_Relatorio_Images/56782dd0.Imagem.183802.jpg
... A96: 708a90b9 | B96: aa8dc0c1 | C96: Fotos_Relatorio_Images/708a90b9.Imagem.183817.jpg
A97: c88984f9 | B97: 199da9cb | C97: Fotos_Relatorio_Images/c88984f9.Imagem.122756.jpg | D97: Rack do laboratório
A98: 01c0521b | B98: 199da9cb | C98: Fotos_Relatorio_Images/01c0521b.Imagem.122804.jpg | D98: Foto fachada
A99: 4bdb62af | B99: 199da9cb | C99: Fotos_Relatorio_Images/4bdb62af.Imagem.122836.jpg | D99: Vista de 3 dos 5 computadores que funcionam
A100: 1999dc32 | B100: 199da9cb | C100: Fotos_Relatorio_Images/1999dc32.Imagem.122903.jpg | D100: Vista de 2 dos 5 computadores que funcionam
A101: fa9a4c53 | B101: 199da9cb | C101: Fotos_Relatorio_Images/fa9a4c53.Imagem.122924.jpg | D101: Rack do laboratório
A102: ba89a718 | B102: 05b6971f | C102: Fotos_Relatorio_Images/ba89a718.Imagem.131443.jpg | D102: Vista do Laboratório
A103: e9577c33 | B103: 05b6971f | C103: Fotos_Relatorio_Images/e9577c33.Imagem.131451.jpg | D103: Roteador que distrui rede wifi
A104: 3d32f260 | B104: 05b6971f | C104: Fotos_Relatorio_Images/3d32f260.Imagem.131459.jpg | D104: Cabo de rede
A105: 056bf77e | B105: 05b6971f | C105: Fotos_Relatorio_Images/056bf77e.Imagem.131507.jpg | D105: Caixa com cabos pra distribuir no laboratório
A106: 08d57140 | B106: 05b6971f | C106: Fotos_Relatorio_Images/08d57140.Imagem.132100.jpg | D106: Vista do laboratório
A107: fa9c7efe | B107: 05b6971f | C107: Fotos_Relatorio_Images/fa9c7efe.Imagem.132052.jpg | D107: Vista do laboratório
...

Sheet FuncionariosSEE
A1: MATRICULA | B1: NOME
A2: 1862006 | B2: ALENE CANDIDO NASCIMENTO
A3: 6179797 | B3: ANA PAULA BARBOSA GUEDES
A4: 6262805 | B4: CASSIA RAYANA DO NASCIMENTO
A5: 1936387 | B5: CLARA ELLIS ADEILDE MARTINS FIGUEREDO
A6: 6267211 | B6: DAYANA NAYARA MARINHO DOS SANTOS
A7: 6273718 | B7: FRANCISCA JOSEANY OLIVEIRA SILVA
A8: 1936034 | B8: GISLEYNY FERREIRA DA COSTA
A9: 1959891 | B9: JOSE IDELTONIO MOREIRA JUNIOR
A10: 6420206 | B10: JOSELMA DOS SANTOS NASCIMENTO
A11: 6270948 | B11: LEONARDO ALBINO BORGES DE FIGUEREDO
A12: 6263372 | B12: LETICIA BARBOSA DA SILVA
A13: 1905970 | B13: MARCELO DRUMOND DE OLIVEIRA
... A26734: 6197817 | B26734: WIARA MARIA DA COSTA

Sheet Inicio
A1: Id | B1: Banner
A2: 1 | B2: Icons/Nexus_logo.png

Sheet Menu
A1: Id | B1: Menu | C1: Imagem
A2: 10 | B2: Escolas | C2: Icons/UnidadedeEnsino.png
A3: 20 | B3: Viagens | C3: Icons/ViagensTI.png
A4: 30 | B4: Relatorios | C4: Icons/Relatorios.png
A5: 40 | B5: Equipe | C5: Icons/Equipe.png

Sheet SubMenu
A1: ID | B1: Id_Menu | C1: Menu | D1: Nome | E1: View_Destino | F1: Imagem | G1: Permissoes
A2: 101 | B2: 10 | C2: 10 | D2: Mapa das Escolas | E2: Escolas | F2: Icons/EscolaNoMapa.png | G2: ADM, OPE, USR
A3: 102 | B3: 10 | C3: 10 | D3: Computadores Escola | E3: Inventario | F3: Icons/InventarioTI.png | G3: ADM, OPE, USR
A4: 103 | B4: 10 | C4: 10 | D4: Projeto DNS | E4: Projeto DNS | F4: Icons/DNSSeguro1.png | G4: ADM
A5: 104 | B5: 10 | C5: 10 | D5: Internet nas Escolas | E5: Internet nas Escolas | F5: Icons/InternetnasEscolas1.png | G5: ADM, OPE, USR
A6: 201 | B6: 20 | C6: 20 | D6: Viagens | E6: Viagens | F6: Icons/ViagensTI3.png | G6: ADM, OPE
A7: 202 | B7: 20 | C7: 20 | D7: Ranking das Viagens | E7: Ranking de Viagens | F7: Icons/RankingViagens.png | G7: ADM, OPE, USR
A8: 301 | B8: 30 | C8: 30 | D8: Relatorios | E8: Relatorios | F8: Icons/RelatoriosdeTI.png | G8: ADM, OPE, USR
A9: 302 | B9: 30 | C9: 30 | D9: Relatorios | E9: Avaliacao dos Tecnicos | F9: Icons/AvaliacaoTecnico.png | G9: ADM, LID
A10: 401 | B10: 40 | C10: 40 | D10: Técnicos | E10: Tecnicos | F10: Icons/EquipeTecnica.png | G10: ADM

Sheet Inventario_Links
A1: ID_Link | B1: ID_Escola | C1: Local_Instalacao | D1: Provedor | E1: Tipo_Conexao | F1: Velocidade | G1: Status

Sheet EscolaInternet
A1: =IFERROR(__xludf.DUMMYFUNCTION("IMPORTRANGE(""https://docs.google.com/spreadsheets/d/1MDcwV0m3rxQLxtGsKsGs2C2VZB1UmpXHiu-R8k9Kt6s/edit?gid=0#gid=0"", ""Geral!A1:Z1000"")"),"GRE") -> GRE | B1: =IFERROR(__xludf.DUMMYFUNCTION("""COMPUTED_VALUE"""),"Município") -> Município | C1: =IFERROR(__xludf.DUMMYFUNCTION("""COMPUTED_VALUE"""),"INEP") -> INEP | D1: =IFERROR(__xludf.DUMMYFUNCTION("""COMPUTED_VALUE"""),"Nome") -> Nome | E1: =IFERROR(__xludf.DUMMYFUNCTION("""COMPUTED_VALUE"""),"Zona Escolar") -> Zona Escolar | F1: =IFERROR(__xludf.DUMMYFUNCTION("""COMPUTED_VALUE"""),"PBLE") -> PBLE | G1: =IFERROR(__xludf.DUMMYFUNCTION("""COMPUTED_VALUE"""),"OI") -> OI | H1: =IFERROR(__xludf.DUMMYFUNCTION("""COMPUTED_VALUE"""),"XDSL") -> XDSL | I1: =IFERROR(__xludf.DUMMYFUNCTION("""COMPUTED_VALUE"""),"IPCONNECT") -> IPCONNECT | J1: =IFERROR(__xludf.DUMMYFUNCTION("""COMPUTED_VALUE"""),"RIX") -> RIX | K1: =IFERROR(__xludf.DUMMYFUNCTION("""COMPUTED_VALUE"""),"CODATA") -> CODATA | L1: =IFERROR(__xludf.DUMMYFUNCTION("""COMPUTED_VALUE"""),"MPLS") -> MPLS | M1: =IFERROR(__xludf.DUMMYFUNCTION("""COMPUTED_VALUE"""),"BRISANET") -> BRISANET | N1: =IFERROR(__xludf.DUMMYFUNCTION("""COMPUTED_VALUE"""),"VIVO") -> VIVO | O1: =IFERROR(__xludf.DUMMYFUNCTION("""COMPUTED_VALUE"""),"GESAC") -> GESAC | P1: =IFERROR(__xludf.DUMMYFUNCTION("""COMPUTED_VALUE"""),"MUNICIPALIZADA/FECHADA") -> MUNICIPALIZADA/FECHADA | Q1: =IFERROR(__xludf.DUMMYFUNCTION("""COMPUTED_VALUE"""),"CONFERIDA?") -> CONFERIDA?
A2: =IFERROR(__xludf.DUMMYFUNCTION("""COMPUTED_VALUE"""),"08ª GRE (Catolé do Rocha)") -> 08ª GRE (Catolé do Rocha) | B2: =IFERROR(__xludf.DUMMYFUNCTION("""COMPUTED_VALUE"""),"Belém do Brejo do Cruz") -> Belém do Brejo do Cruz | C2: =IFERROR(__xludf.DUMMYFUNCTION("""COMPUTED_VALUE"""),2.5000047E7) -> 25000047 | D2: =IFERROR(__xludf.DUMMYFUNCTION("""COMPUTED_VALUE"""),"Eci Nossa Senhora da Conceição") -> Eci Nossa Senhora da Conceição | E2: =IFERROR(__xludf.DUMMYFUNCTION("""COMPUTED_VALUE"""),"URBANA") -> URBANA | F2: =IFERROR(__xludf.DUMMYFUNCTION("""COMPUTED_VALUE"""),"-") -> - | G2: =IFERROR(__xludf.DUMMYFUNCTION("""COMPUTED_VALUE"""),"-") -> - | H2: =IFERROR(__xludf.DUMMYFUNCTION("""COMPUTED_VALUE"""),"-") -> - | I2: =IFERROR(__xludf.DUMMYFUNCTION("""COMPUTED_VALUE"""),"-") -> - | J2: =IFERROR(__xludf.DUMMYFUNCTION("""COMPUTED_VALUE"""),"30 Mbps") -> 30 Mbps | K2: =IFERROR(__xludf.DUMMYFUNCTION("""COMPUTED_VALUE"""),"-") -> - | L2: =IFERROR(__xludf.DUMMYFUNCTION("""COMPUTED_VALUE"""),"-") -> - | M2: =IFERROR(__xludf.DUMMYFUNCTION("""COMPUTED_VALUE"""),"-") -> - | N2: =IFERROR(__xludf.DUMMYFUNCTION("""COMPUTED_VALUE"""),"-") -> - | O2: =IFERROR(__xludf.DUMMYFUNCTION("""COMPUTED_VALUE"""),"-") -> -
A3: =IFERROR(__xludf.DUMMYFUNCTION("""COMPUTED_VALUE"""),"08ª GRE (Catolé do Rocha)") -> 08ª GRE (Catolé do Rocha) | B3: =IFERROR(__xludf.DUMMYFUNCTION("""COMPUTED_VALUE"""),"Belém do Brejo do Cruz") -> Belém do Brejo do Cruz | C3: =IFERROR(__xludf.DUMMYFUNCTION("""COMPUTED_VALUE"""),2.5000055E7) -> 25000055 | D3: =IFERROR(__xludf.DUMMYFUNCTION("""COMPUTED_VALUE"""),"EEEFM Américo Maia") -> EEEFM Américo Maia | E3: =IFERROR(__xludf.DUMMYFUNCTION("""COMPUTED_VALUE"""),"URBANA") -> URBANA | F3: =IFERROR(__xludf.DUMMYFUNCTION("""COMPUTED_VALUE"""),"2 Mbps") -> 2 Mbps | G3: =IFERROR(__xludf.DUMMYFUNCTION("""COMPUTED_VALUE"""),"-") -> - | H3: =IFERROR(__xludf.DUMMYFUNCTION("""COMPUTED_VALUE"""),"-") -> - | I3: =IFERROR(__xludf.DUMMYFUNCTION("""COMPUTED_VALUE"""),"-") -> - | J3: =IFERROR(__xludf.DUMMYFUNCTION("""COMPUTED_VALUE"""),"-") -> - | K3: =IFERROR(__xludf.DUMMYFUNCTION("""COMPUTED_VALUE"""),"-") -> - | L3: =IFERROR(__xludf.DUMMYFUNCTION("""COMPUTED_VALUE"""),"-") -> - | M3: =IFERROR(__xludf.DUMMYFUNCTION("""COMPUTED_VALUE"""),"100 Mbps") -> 100 Mbps | N3: =IFERROR(__xludf.DUMMYFUNCTION("""COMPUTED_VALUE"""),"-") -> - | O3: =IFERROR(__xludf.DUMMYFUNCTION("""COMPUTED_VALUE"""),"-") -> -
A4: =IFERROR(__xludf.DUMMYFUNCTION("""COMPUTED_VALUE"""),"08ª GRE (Catolé do Rocha)") -> 08ª GRE (Catolé do Rocha) | B4: =IFERROR(__xludf.DUMMYFUNCTION("""COMPUTED_VALUE"""),"Bom Sucesso") -> Bom Sucesso | C4: =IFERROR(__xludf.DUMMYFUNCTION("""COMPUTED_VALUE"""),2.5000349E7) -> 25000349 | D4: =IFERROR(__xludf.DUMMYFUNCTION("""COMPUTED_VALUE"""),"ECIT Padre Aristides") -> ECIT Padre Aristides | E4: =IFERROR(__xludf.DUMMYFUNCTION("""COMPUTED_VALUE"""),"URBANA") -> URBANA | F4: =IFERROR(__xludf.DUMMYFUNCTION("""COMPUTED_VALUE"""),"2 Mbps") -> 2 Mbps | G4: =IFERROR(__xludf.DUMMYFUNCTION("""COMPUTED_VALUE"""),"-") -> - | H4: =IFERROR(__xludf.DUMMYFUNCTION("""COMPUTED_VALUE"""),"-") -> - | I4: =IFERROR(__xludf.DUMMYFUNCTION("""COMPUTED_VALUE"""),"-") -> - | J4: =IFERROR(__xludf.DUMMYFUNCTION("""COMPUTED_VALUE"""),"-") -> - | K4: =IFERROR(__xludf.DUMMYFUNCTION("""COMPUTED_VALUE"""),"-") -> - | L4: =IFERROR(__xludf.DUMMYFUNCTION("""COMPUTED_VALUE"""),"-") -> - | M4: =IFERROR(__xludf.DUMMYFUNCTION("""COMPUTED_VALUE"""),"100 Mbps") -> 100 Mbps | N4: =IFERROR(__xludf.DUMMYFUNCTION("""COMPUTED_VALUE"""),"-") -> - | O4: =IFERROR(__xludf.DUMMYFUNCTION("""COMPUTED_VALUE"""),"-") -> -
A5: =IFERROR(__xludf.DUMMYFUNCTION("""COMPUTED_VALUE"""),"08ª GRE (Catolé do Rocha)") -> 08ª GRE (Catolé do Rocha) | B5: =IFERROR(__xludf.DUMMYFUNCTION("""COMPUTED_VALUE"""),"Bom Sucesso") -> Bom Sucesso | C5: =IFERROR(__xludf.DUMMYFUNCTION("""COMPUTED_VALUE"""),2.5000373E7) -> 25000373 | D5: =IFERROR(__xludf.DUMMYFUNCTION("""COMPUTED_VALUE"""),"EEEF Dr. José Paz de Lima") -> EEEF Dr. José Paz de Lima | E5: =IFERROR(__xludf.DUMMYFUNCTION("""COMPUTED_VALUE"""),"URBANA") -> URBANA | F5: =IFERROR(__xludf.DUMMYFUNCTION("""COMPUTED_VALUE"""),"2 Mbps") -> 2 Mbps | G5: =IFERROR(__xludf.DUMMYFUNCTION("""COMPUTED_VALUE"""),"-") -> - | H5: =IFERROR(__xludf.DUMMYFUNCTION("""COMPUTED_VALUE"""),"-") -> - | I5: =IFERROR(__xludf.DUMMYFUNCTION("""COMPUTED_VALUE"""),"-") -> - | J5: =IFERROR(__xludf.DUMMYFUNCTION("""COMPUTED_VALUE"""),"-") -> - | K5: =IFERROR(__xludf.DUMMYFUNCTION("""COMPUTED_VALUE"""),"-") -> - | L5: =IFERROR(__xludf.DUMMYFUNCTION("""COMPUTED_VALUE"""),"-") -> - | M5: =IFERROR(__xludf.DUMMYFUNCTION("""COMPUTED_VALUE"""),"100 Mbps") -> 100 Mbps | N5: =IFERROR(__xludf.DUMMYFUNCTION("""COMPUTED_VALUE"""),"-") -> - | O5: =IFERROR(__xludf.DUMMYFUNCTION("""COMPUTED_VALUE"""),"-") -> -
A6: =IFERROR(__xludf.DUMMYFUNCTION("""COMPUTED_VALUE"""),"08ª GRE (Catolé do Rocha)") -> 08ª GRE (Catolé do Rocha) | B6: =IFERROR(__xludf.DUMMYFUNCTION("""COMPUTED_VALUE"""),"Brejo do Cruz") -> Brejo do Cruz | C6: =IFERROR(__xludf.DUMMYFUNCTION("""COMPUTED_VALUE"""),2.500064E7) -> 25000640 | D6: =IFERROR(__xludf.DUMMYFUNCTION("""COMPUTED_VALUE"""),"ECIT Prof José Olímpio Maia") -> ECIT Prof José Olímpio Maia | E6: =IFERROR(__xludf.DUMMYFUNCTION("""COMPUTED_VALUE"""),"URBANA") -> URBANA | F6: =IFERROR(__xludf.DUMMYFUNCTION("""COMPUTED_VALUE"""),"2 Mbps") -> 2 Mbps | G6: =IFERROR(__xludf.DUMMYFUNCTION("""COMPUTED_VALUE"""),"10 Mbps") -> 10 Mbps | H6: =IFERROR(__xludf.DUMMYFUNCTION("""COMPUTED_VALUE"""),"-") -> - | I6: =IFERROR(__xludf.DUMMYFUNCTION("""COMPUTED_VALUE"""),"-") -> - | J6: =IFERROR(__xludf.DUMMYFUNCTION("""COMPUTED_VALUE"""),"-") -> - | K6: =IFERROR(__xludf.DUMMYFUNCTION("""COMPUTED_VALUE"""),"-") -> - | L6: =IFERROR(__xludf.DUMMYFUNCTION("""COMPUTED_VALUE"""),"-") -> - | M6: =IFERROR(__xludf.DUMMYFUNCTION("""COMPUTED_VALUE"""),"-") -> - | N6: =IFERROR(__xludf.DUMMYFUNCTION("""COMPUTED_VALUE"""),"-") -> - | O6: =IFERROR(__xludf.DUMMYFUNCTION("""COMPUTED_VALUE"""),"-") -> -
A7: =IFERROR(__xludf.DUMMYFUNCTION("""COMPUTED_VALUE"""),"08ª GRE (Catolé do Rocha)") -> 08ª GRE (Catolé do Rocha) | B7: =IFERROR(__xludf.DUMMYFUNCTION("""COMPUTED_VALUE"""),"Brejo do Cruz") -> Brejo do Cruz | C7: =IFERROR(__xludf.DUMMYFUNCTION("""COMPUTED_VALUE"""),2.5000659E7) -> 25000659 | D7: =IFERROR(__xludf.DUMMYFUNCTION("""COMPUTED_VALUE"""),"EEEFM Antonio Gomes") -> EEEFM Antonio Gomes | E7: =IFERROR(__xludf.DUMMYFUNCTION("""COMPUTED_VALUE"""),"URBANA") -> URBANA | F7: =IFERROR(__xludf.DUMMYFUNCTION("""COMPUTED_VALUE"""),"2 Mbps") -> 2 Mbps | G7: =IFERROR(__xludf.DUMMYFUNCTION("""COMPUTED_VALUE"""),"-") -> - | H7: =IFERROR(__xludf.DUMMYFUNCTION("""COMPUTED_VALUE"""),"-") -> - | I7: =IFERROR(__xludf.DUMMYFUNCTION("""COMPUTED_VALUE"""),"-") -> - | J7: =IFERROR(__xludf.DUMMYFUNCTION("""COMPUTED_VALUE"""),"-") -> - | K7: =IFERROR(__xludf.DUMMYFUNCTION("""COMPUTED_VALUE"""),"-") -> - | L7: =IFERROR(__xludf.DUMMYFUNCTION("""COMPUTED_VALUE"""),"-") -> - | M7: =IFERROR(__xludf.DUMMYFUNCTION("""COMPUTED_VALUE"""),"100 Mbps") -> 100 Mbps | N7: =IFERROR(__xludf.DUMMYFUNCTION("""COMPUTED_VALUE"""),"-") -> - | O7: =IFERROR(__xludf.DUMMYFUNCTION("""COMPUTED_VALUE"""),"-") -> -
A8: =IFERROR(__xludf.DUMMYFUNCTION("""COMPUTED_VALUE"""),"08ª GRE (Catolé do Rocha)") -> 08ª GRE (Catolé do Rocha) | B8: =IFERROR(__xludf.DUMMYFUNCTION("""COMPUTED_VALUE"""),"São José do Brejo do Cruz") -> São José do Brejo do Cruz | C8: =IFERROR(__xludf.DUMMYFUNCTION("""COMPUTED_VALUE"""),2.5001302E7) -> 25001302 | D8: =IFERROR(__xludf.DUMMYFUNCTION("""COMPUTED_VALUE"""),"ECI Olivia Saraiva Maia") -> ECI Olivia Saraiva Maia | E8: =IFERROR(__xludf.DUMMYFUNCTION("""COMPUTED_VALUE"""),"URBANA") -> URBANA | F8: =IFERROR(__xludf.DUMMYFUNCTION("""COMPUTED_VALUE"""),"2 Mbps") -> 2 Mbps | G8: =IFERROR(__xludf.DUMMYFUNCTION("""COMPUTED_VALUE"""),"-") -> - | H8: =IFERROR(__xludf.DUMMYFUNCTION("""COMPUTED_VALUE"""),"-") -> - | I8: =IFERROR(__xludf.DUMMYFUNCTION("""COMPUTED_VALUE"""),"-") -> - | J8: =IFERROR(__xludf.DUMMYFUNCTION("""COMPUTED_VALUE"""),"-") -> - | K8: =IFERROR(__xludf.DUMMYFUNCTION("""COMPUTED_VALUE"""),"-") -> - | L8: =IFERROR(__xludf.DUMMYFUNCTION("""COMPUTED_VALUE"""),"-") -> - | M8: =IFERROR(__xludf.DUMMYFUNCTION("""COMPUTED_VALUE"""),"100 Mbps") -> 100 Mbps | N8: =IFERROR(__xludf.DUMMYFUNCTION("""COMPUTED_VALUE"""),"-") -> - | O8: =IFERROR(__xludf.DUMMYFUNCTION("""COMPUTED_VALUE"""),"-") -> -
A9: =IFERROR(__xludf.DUMMYFUNCTION("""COMPUTED_VALUE"""),"08ª GRE (Catolé do Rocha)") -> 08ª GRE (Catolé do Rocha) | B9: =IFERROR(__xludf.DUMMYFUNCTION("""COMPUTED_VALUE"""),"Brejo dos Santos") -> Brejo dos Santos | C9: =IFERROR(__xludf.DUMMYFUNCTION("""COMPUTED_VALUE"""),2.5001477E7) -> 25001477 | D9: =IFERROR(__xludf.DUMMYFUNCTION("""COMPUTED_VALUE"""),"Eci EEFM Professora Diva Guedes de Araujo") -> Eci EEFM Professora Diva Guedes de Araujo | E9: =IFERROR(__xludf.DUMMYFUNCTION("""COMPUTED_VALUE"""),"URBANA") -> URBANA | F9: =IFERROR(__xludf.DUMMYFUNCTION("""COMPUTED_VALUE"""),"2 Mbps") -> 2 Mbps | G9: =IFERROR(__xludf.DUMMYFUNCTION("""COMPUTED_VALUE"""),"-") -> - | H9: =IFERROR(__xludf.DUMMYFUNCTION("""COMPUTED_VALUE"""),"-") -> - | I9: =IFERROR(__xludf.DUMMYFUNCTION("""COMPUTED_VALUE"""),"-") -> - | J9: =IFERROR(__xludf.DUMMYFUNCTION("""COMPUTED_VALUE"""),"-") -> - | K9: =IFERROR(__xludf.DUMMYFUNCTION("""COMPUTED_VALUE"""),"-") -> - | L9: =IFERROR(__xludf.DUMMYFUNCTION("""COMPUTED_VALUE"""),"-") -> - | M9: =IFERROR(__xludf.DUMMYFUNCTION("""COMPUTED_VALUE"""),"100 Mbps") -> 100 Mbps | N9: =IFERROR(__xludf.DUMMYFUNCTION("""COMPUTED_VALUE"""),"-") -> - | O9: =IFERROR(__xludf.DUMMYFUNCTION("""COMPUTED_VALUE"""),"-") -> -
A10: =IFERROR(__xludf.DUMMYFUNCTION("""COMPUTED_VALUE"""),"-") -> - | B10: =IFERROR(__xludf.DUMMYFUNCTION("""COMPUTED_VALUE"""),"Catolé do Rocha") -> Catolé do Rocha | C10: =IFERROR(__xludf.DUMMYFUNCTION("""COMPUTED_VALUE"""),2.5001825E7) -> 25001825 | D10: =IFERROR(__xludf.DUMMYFUNCTION("""COMPUTED_VALUE"""),"Esc Agrotecnica do Cajueiro Campus Iv - Uepb") -> Esc Agrotecnica do Cajueiro Campus Iv - Uepb | E10: =IFERROR(__xludf.DUMMYFUNCTION("""COMPUTED_VALUE"""),"-") -> - | F10: =IFERROR(__xludf.DUMMYFUNCTION("""COMPUTED_VALUE"""),"-") -> - | G10: =IFERROR(__xludf.DUMMYFUNCTION("""COMPUTED_VALUE"""),"-") -> - | H10: =IFERROR(__xludf.DUMMYFUNCTION("""COMPUTED_VALUE"""),"-") -> - | I10: =IFERROR(__xludf.DUMMYFUNCTION("""COMPUTED_VALUE"""),"-") -> - | J10: =IFERROR(__xludf.DUMMYFUNCTION("""COMPUTED_VALUE"""),"50 Mbps") -> 50 Mbps | K10: =IFERROR(__xludf.DUMMYFUNCTION("""COMPUTED_VALUE"""),"-") -> - | L10: =IFERROR(__xludf.DUMMYFUNCTION("""COMPUTED_VALUE"""),"-") -> - | M10: =IFERROR(__xludf.DUMMYFUNCTION("""COMPUTED_VALUE"""),"-") -> - | N10: =IFERROR(__xludf.DUMMYFUNCTION("""COMPUTED_VALUE"""),"-") -> - | O10: =IFERROR(__xludf.DUMMYFUNCTION("""COMPUTED_VALUE"""),"-") -> -
A11: =IFERROR(__xludf.DUMMYFUNCTION("""COMPUTED_VALUE"""),"08ª GRE (Catolé do Rocha)") -> 08ª GRE (Catolé do Rocha) | B11: =IFERROR(__xludf.DUMMYFUNCTION("""COMPUTED_VALUE"""),"Catolé do Rocha") -> Catolé do Rocha | C11: =IFERROR(__xludf.DUMMYFUNCTION("""COMPUTED_VALUE"""),2.5001833E7) -> 25001833 | D11: =IFERROR(__xludf.DUMMYFUNCTION("""COMPUTED_VALUE"""),"Eci Obdulia Dantas") -> Eci Obdulia Dantas | E11: =IFERROR(__xludf.DUMMYFUNCTION("""COMPUTED_VALUE"""),"URBANA") -> URBANA | F11: =IFERROR(__xludf.DUMMYFUNCTION("""COMPUTED_VALUE"""),"2 Mbps") -> 2 Mbps | G11: =IFERROR(__xludf.DUMMYFUNCTION("""COMPUTED_VALUE"""),"-") -> - | H11: =IFERROR(__xludf.DUMMYFUNCTION("""COMPUTED_VALUE"""),"-") -> - | I11: =IFERROR(__xludf.DUMMYFUNCTION("""COMPUTED_VALUE"""),"-") -> - | J11: =IFERROR(__xludf.DUMMYFUNCTION("""COMPUTED_VALUE"""),"50 Mbps") -> 50 Mbps | K11: =IFERROR(__xludf.DUMMYFUNCTION("""COMPUTED_VALUE"""),"-") -> - | L11: =IFERROR(__xludf.DUMMYFUNCTION("""COMPUTED_VALUE"""),"-") -> - | M11: =IFERROR(__xludf.DUMMYFUNCTION("""COMPUTED_VALUE"""),"-") -> - | N11: =IFERROR(__xludf.DUMMYFUNCTION("""COMPUTED_VALUE"""),"-") -> - | O11: =IFERROR(__xludf.DUMMYFUNCTION("""COMPUTED_VALUE"""),"-") -> -
A12: =IFERROR(__xludf.DUMMYFUNCTION("""COMPUTED_VALUE"""),"08ª GRE (Catolé do Rocha)") -> 08ª GRE (Catolé do Rocha) | B12: =IFERROR(__xludf.DUMMYFUNCTION("""COMPUTED_VALUE"""),"Catolé do Rocha") -> Catolé do Rocha | C12: =IFERROR(__xludf.DUMMYFUNCTION("""COMPUTED_VALUE"""),2.5001868E7) -> 25001868 | D12: =IFERROR(__xludf.DUMMYFUNCTION("""COMPUTED_VALUE"""),"EEEF Joaquim Valdevino de Lima") -> EEEF Joaquim Valdevino de Lima | E12: =IFERROR(__xludf.DUMMYFUNCTION("""COMPUTED_VALUE"""),"RURAL") -> RURAL | F12: =IFERROR(__xludf.DUMMYFUNCTION("""COMPUTED_VALUE"""),"-") -> - | G12: =IFERROR(__xludf.DUMMYFUNCTION("""COMPUTED_VALUE"""),"-") -> - | H12: =IFERROR(__xludf.DUMMYFUNCTION("""COMPUTED_VALUE"""),"-") -> - | I12: =IFERROR(__xludf.DUMMYFUNCTION("""COMPUTED_VALUE"""),"-") -> - | J12: =IFERROR(__xludf.DUMMYFUNCTION("""COMPUTED_VALUE"""),"-") -> - | K12: =IFERROR(__xludf.DUMMYFUNCTION("""COMPUTED_VALUE"""),"-") -> - | L12: =IFERROR(__xludf.DUMMYFUNCTION("""COMPUTED_VALUE"""),"-") -> - | M12: =IFERROR(__xludf.DUMMYFUNCTION("""COMPUTED_VALUE"""),"-") -> - | N12: =IFERROR(__xludf.DUMMYFUNCTION("""COMPUTED_VALUE"""),"Satélite") -> Satélite | O12: =IFERROR(__xludf.DUMMYFUNCTION("""COMPUTED_VALUE"""),"-") -> -
A13: =IFERROR(__xludf.DUMMYFUNCTION("""COMPUTED_VALUE"""),"08ª GRE (Catolé do Rocha)") -> 08ª GRE (Catolé do Rocha) | B13: =IFERROR(__xludf.DUMMYFUNCTION("""COMPUTED_VALUE"""),"Catolé do Rocha") -> Catolé do Rocha | C13: =IFERROR(__xludf.DUMMYFUNCTION("""COMPUTED_VALUE"""),2.5001876E7) -> 25001876 | D13: =IFERROR(__xludf.DUMMYFUNCTION("""COMPUTED_VALUE"""),"Escola Estadual de Ensino Fundamental José de Sá Cavalcante") -> Escola Estadual de Ensino Fundamental José de Sá Cavalcante | E13: =IFERROR(__xludf.DUMMYFUNCTION("""COMPUTED_VALUE"""),"RURAL") -> RURAL | F13: =IFERROR(__xludf.DUMMYFUNCTION("""COMPUTED_VALUE"""),"-") -> - | G13: =IFERROR(__xludf.DUMMYFUNCTION("""COMPUTED_VALUE"""),"-") -> - | H13: =IFERROR(__xludf.DUMMYFUNCTION("""COMPUTED_VALUE"""),"-") -> - | I13: =IFERROR(__xludf.DUMMYFUNCTION("""COMPUTED_VALUE"""),"-") -> - | J13: =IFERROR(__xludf.DUMMYFUNCTION("""COMPUTED_VALUE"""),"-") -> - | K13: =IFERROR(__xludf.DUMMYFUNCTION("""COMPUTED_VALUE"""),"-") -> - | L13: =IFERROR(__xludf.DUMMYFUNCTION("""COMPUTED_VALUE"""),"-") -> - | M13: =IFERROR(__xludf.DUMMYFUNCTION("""COMPUTED_VALUE"""),"-") -> - | N13: =IFERROR(__xludf.DUMMYFUNCTION("""COMPUTED_VALUE"""),"Black Box (3G)") -> Black Box (3G) | O13: =IFERROR(__xludf.DUMMYFUNCTION("""COMPUTED_VALUE"""),"-") -> -
A14: =IFERROR(__xludf.DUMMYFUNCTION("""COMPUTED_VALUE"""),"08ª GRE (Catolé do Rocha)") -> 08ª GRE (Catolé do Rocha) | B14: =IFERROR(__xludf.DUMMYFUNCTION("""COMPUTED_VALUE"""),"Catolé do Rocha") -> Catolé do Rocha | C14: =IFERROR(__xludf.DUMMYFUNCTION("""COMPUTED_VALUE"""),2.5001906E7) -> 25001906 | D14: =IFERROR(__xludf.DUMMYFUNCTION("""COMPUTED_VALUE"""),"ESCOLA CIDADÃ INTEGRAL JOÃO SUASSUNA") -> ESCOLA CIDADÃ INTEGRAL JOÃO SUASSUNA | E14: =IFERROR(__xludf.DUMMYFUNCTION("""COMPUTED_VALUE"""),"URBANA") -> URBANA | F14: =IFERROR(__xludf.DUMMYFUNCTION("""COMPUTED_VALUE"""),"2 Mbps") -> 2 Mbps | G14: =IFERROR(__xludf.DUMMYFUNCTION("""COMPUTED_VALUE"""),"-") -> - | H14: =IFERROR(__xludf.DUMMYFUNCTION("""COMPUTED_VALUE"""),"-") -> - | I14: =IFERROR(__xludf.DUMMYFUNCTION("""COMPUTED_VALUE"""),"-") -> - | J14: =IFERROR(__xludf.DUMMYFUNCTION("""COMPUTED_VALUE"""),"-") -> - | K14: =IFERROR(__xludf.DUMMYFUNCTION("""COMPUTED_VALUE"""),"-") -> - | L14: =IFERROR(__xludf.DUMMYFUNCTION("""COMPUTED_VALUE"""),"-") -> - | M14: =IFERROR(__xludf.DUMMYFUNCTION("""COMPUTED_VALUE"""),"100 Mbps") -> 100 Mbps | N14: =IFERROR(__xludf.DUMMYFUNCTION("""COMPUTED_VALUE"""),"-") -> - | O14: =IFERROR(__xludf.DUMMYFUNCTION("""COMPUTED_VALUE"""),"-") -> -
A15: =IFERROR(__xludf.DUMMYFUNCTION("""COMPUTED_VALUE"""),"08ª GRE (Catolé do Rocha)") -> 08ª GRE (Catolé do Rocha) | B15: =IFERROR(__xludf.DUMMYFUNCTION("""COMPUTED_VALUE"""),"Catolé do Rocha") -> Catolé do Rocha | C15: =IFERROR(__xludf.DUMMYFUNCTION("""COMPUTED_VALUE"""),2.5001914E7) -> 25001914 | D15: =IFERROR(__xludf.DUMMYFUNCTION("""COMPUTED_VALUE"""),"EEEFM E EJA Sergina Laura Dantas") -> EEEFM E EJA Sergina Laura Dantas | E15: =IFERROR(__xludf.DUMMYFUNCTION("""COMPUTED_VALUE"""),"URBANA") -> URBANA | F15: =IFERROR(__xludf.DUMMYFUNCTION("""COMPUTED_VALUE"""),"2 Mbps") -> 2 Mbps | G15: =IFERROR(__xludf.DUMMYFUNCTION("""COMPUTED_VALUE"""),"-") -> - | H15: =IFERROR(__xludf.DUMMYFUNCTION("""COMPUTED_VALUE"""),"-") -> - | I15: =IFERROR(__xludf.DUMMYFUNCTION("""COMPUTED_VALUE"""),"-") -> - | J15: =IFERROR(__xludf.DUMMYFUNCTION("""COMPUTED_VALUE"""),"-") -> - | K15: =IFERROR(__xludf.DUMMYFUNCTION("""COMPUTED_VALUE"""),"-") -> - | L15: =IFERROR(__xludf.DUMMYFUNCTION("""COMPUTED_VALUE"""),"-") -> - | M15: =IFERROR(__xludf.DUMMYFUNCTION("""COMPUTED_VALUE"""),"100 Mbps") -> 100 Mbps | N15: =IFERROR(__xludf.DUMMYFUNCTION("""COMPUTED_VALUE"""),"-") -> - | O15: =IFERROR(__xludf.DUMMYFUNCTION("""COMPUTED_VALUE"""),"-") -> -
A16: =IFERROR(__xludf.DUMMYFUNCTION("""COMPUTED_VALUE"""),"08ª GRE (Catolé do Rocha)") -> 08ª GRE (Catolé do Rocha) | B16: =IFERROR(__xludf.DUMMYFUNCTION("""COMPUTED_VALUE"""),"Catolé do Rocha") -> Catolé do Rocha | C16: =IFERROR(__xludf.DUMMYFUNCTION("""COMPUTED_VALUE"""),2.5002376E7) -> 25002376 | D16: =IFERROR(__xludf.DUMMYFUNCTION("""COMPUTED_VALUE"""),"EEEF Fabio Mariz Maia") -> EEEF Fabio Mariz Maia | E16: =IFERROR(__xludf.DUMMYFUNCTION("""COMPUTED_VALUE"""),"RURAL") -> RURAL | F16: =IFERROR(__xludf.DUMMYFUNCTION("""COMPUTED_VALUE"""),"-") -> - | G16: =IFERROR(__xludf.DUMMYFUNCTION("""COMPUTED_VALUE"""),"-") -> - | H16: =IFERROR(__xludf.DUMMYFUNCTION("""COMPUTED_VALUE"""),"-") -> - | I16: =IFERROR(__xludf.DUMMYFUNCTION("""COMPUTED_VALUE"""),"-") -> - | J16: =IFERROR(__xludf.DUMMYFUNCTION("""COMPUTED_VALUE"""),"-") -> - | K16: =IFERROR(__xludf.DUMMYFUNCTION("""COMPUTED_VALUE"""),"-") -> - | L16: =IFERROR(__xludf.DUMMYFUNCTION("""COMPUTED_VALUE"""),"-") -> - | M16: =IFERROR(__xludf.DUMMYFUNCTION("""COMPUTED_VALUE"""),"-") -> - | N16: =IFERROR(__xludf.DUMMYFUNCTION("""COMPUTED_VALUE"""),"Satélite") -> Satélite | O16: =IFERROR(__xludf.DUMMYFUNCTION("""COMPUTED_VALUE"""),20.0) -> 20
A17: =IFERROR(__xludf.DUMMYFUNCTION("""COMPUTED_VALUE"""),"08ª GRE (Catolé do Rocha)") -> 08ª GRE (Catolé do Rocha) | B17: =IFERROR(__xludf.DUMMYFUNCTION("""COMPUTED_VALUE"""),"Jericó") -> Jericó | C17: =IFERROR(__xludf.DUMMYFUNCTION("""COMPUTED_VALUE"""),2.5002422E7) -> 25002422 | D17: =IFERROR(__xludf.DUMMYFUNCTION("""COMPUTED_VALUE"""),"Eci EEFM Francisco Maia") -> Eci EEFM Francisco Maia | E17: =IFERROR(__xludf.DUMMYFUNCTION("""COMPUTED_VALUE"""),"URBANA") -> URBANA | F17: =IFERROR(__xludf.DUMMYFUNCTION("""COMPUTED_VALUE"""),"2 Mbps") -> 2 Mbps | G17: =IFERROR(__xludf.DUMMYFUNCTION("""COMPUTED_VALUE"""),"-") -> - | H17: =IFERROR(__xludf.DUMMYFUNCTION("""COMPUTED_VALUE"""),"-") -> - | I17: =IFERROR(__xludf.DUMMYFUNCTION("""COMPUTED_VALUE"""),"-") -> - | J17: =IFERROR(__xludf.DUMMYFUNCTION("""COMPUTED_VALUE"""),"-") -> - | K17: =IFERROR(__xludf.DUMMYFUNCTION("""COMPUTED_VALUE"""),"-") -> - | L17: =IFERROR(__xludf.DUMMYFUNCTION("""COMPUTED_VALUE"""),"-") -> - | M17: =IFERROR(__xludf.DUMMYFUNCTION("""COMPUTED_VALUE"""),"100 Mbps") -> 100 Mbps | N17: =IFERROR(__xludf.DUMMYFUNCTION("""COMPUTED_VALUE"""),"-") -> - | O17: =IFERROR(__xludf.DUMMYFUNCTION("""COMPUTED_VALUE"""),"-") -> -
A18: =IFERROR(__xludf.DUMMYFUNCTION("""COMPUTED_VALUE"""),"08ª GRE (Catolé do Rocha)") -> 08ª GRE (Catolé do Rocha) | B18: =IFERROR(__xludf.DUMMYFUNCTION("""COMPUTED_VALUE"""),"Mato Grosso") -> Mato Grosso | C18: =IFERROR(__xludf.DUMMYFUNCTION("""COMPUTED_VALUE"""),2.5002457E7) -> 25002457 | D18: =IFERROR(__xludf.DUMMYFUNCTION("""COMPUTED_VALUE"""),"ECIEEM JOSÉ SERAFIM DE LIMA") -> ECIEEM JOSÉ SERAFIM DE LIMA | E18: =IFERROR(__xludf.DUMMYFUNCTION("""COMPUTED_VALUE"""),"URBANA") -> URBANA | F18: =IFERROR(__xludf.DUMMYFUNCTION("""COMPUTED_VALUE"""),"2 Mbps") -> 2 Mbps | G18: =IFERROR(__xludf.DUMMYFUNCTION("""COMPUTED_VALUE"""),"-") -> - | H18: =IFERROR(__xludf.DUMMYFUNCTION("""COMPUTED_VALUE"""),"-") -> - | I18: =IFERROR(__xludf.DUMMYFUNCTION("""COMPUTED_VALUE"""),"-") -> - | J18: =IFERROR(__xludf.DUMMYFUNCTION("""COMPUTED_VALUE"""),"-") -> - | K18: =IFERROR(__xludf.DUMMYFUNCTION("""COMPUTED_VALUE"""),"-") -> - | L18: =IFERROR(__xludf.DUMMYFUNCTION("""COMPUTED_VALUE"""),"-") -> - | M18: =IFERROR(__xludf.DUMMYFUNCTION("""COMPUTED_VALUE"""),"100 Mbps") -> 100 Mbps | N18: =IFERROR(__xludf.DUMMYFUNCTION("""COMPUTED_VALUE"""),"-") -> - | O18: =IFERROR(__xludf.DUMMYFUNCTION("""COMPUTED_VALUE"""),"-") -> -
A19: =IFERROR(__xludf.DUMMYFUNCTION("""COMPUTED_VALUE"""),"08ª GRE (Catolé do Rocha)") -> 08ª GRE (Catolé do Rocha) | B19: =IFERROR(__xludf.DUMMYFUNCTION("""COMPUTED_VALUE"""),"Lagoa") -> Lagoa | C19: =IFERROR(__xludf.DUMMYFUNCTION("""COMPUTED_VALUE"""),2.5003038E7) -> 25003038 | D19: =IFERROR(__xludf.DUMMYFUNCTION("""COMPUTED_VALUE"""),"EEEFM Mons Valeriano Pereira") -> EEEFM Mons Valeriano Pereira | E19: =IFERROR(__xludf.DUMMYFUNCTION("""COMPUTED_VALUE"""),"URBANA") -> URBANA | F19: =IFERROR(__xludf.DUMMYFUNCTION("""COMPUTED_VALUE"""),"2 Mbps") -> 2 Mbps | G19: =IFERROR(__xludf.DUMMYFUNCTION("""COMPUTED_VALUE"""),"-") -> - | H19: =IFERROR(__xludf.DUMMYFUNCTION("""COMPUTED_VALUE"""),"-") -> - | I19: =IFERROR(__xludf.DUMMYFUNCTION("""COMPUTED_VALUE"""),"-") -> - | J19: =IFERROR(__xludf.DUMMYFUNCTION("""COMPUTED_VALUE"""),"-") -> - | K19: =IFERROR(__xludf.DUMMYFUNCTION("""COMPUTED_VALUE"""),"-") -> - | L19: =IFERROR(__xludf.DUMMYFUNCTION("""COMPUTED_VALUE"""),"-") -> - | M19: =IFERROR(__xludf.DUMMYFUNCTION("""COMPUTED_VALUE"""),"100 Mbps") -> 100 Mbps | N19: =IFERROR(__xludf.DUMMYFUNCTION("""COMPUTED_VALUE"""),"-") -> - | O19: =IFERROR(__xludf.DUMMYFUNCTION("""COMPUTED_VALUE"""),"-") -> -
A20: =IFERROR(__xludf.DUMMYFUNCTION("""COMPUTED_VALUE"""),"08ª GRE (Catolé do Rocha)") -> 08ª GRE (Catolé do Rocha) | B20: =IFERROR(__xludf.DUMMYFUNCTION("""COMPUTED_VALUE"""),"Lagoa") -> Lagoa | C20: =IFERROR(__xludf.DUMMYFUNCTION("""COMPUTED_VALUE"""),2.5003054E7) -> 25003054 | D20: =IFERROR(__xludf.DUMMYFUNCTION("""COMPUTED_VALUE"""),"EEEFM Frei Bruno") -> EEEFM Frei Bruno | E20: =IFERROR(__xludf.DUMMYFUNCTION("""COMPUTED_VALUE"""),"URBANA") -> URBANA | F20: =IFERROR(__xludf.DUMMYFUNCTION("""COMPUTED_VALUE"""),"2 Mbps") -> 2 Mbps | G20: =IFERROR(__xludf.DUMMYFUNCTION("""COMPUTED_VALUE"""),"-") -> - | H20: =IFERROR(__xludf.DUMMYFUNCTION("""COMPUTED_VALUE"""),"-") -> - | I20: =IFERROR(__xludf.DUMMYFUNCTION("""COMPUTED_VALUE"""),"-") -> - | J20: =IFERROR(__xludf.DUMMYFUNCTION("""COMPUTED_VALUE"""),"-") -> - | K20: =IFERROR(__xludf.DUMMYFUNCTION("""COMPUTED_VALUE"""),"-") -> - | L20: =IFERROR(__xludf.DUMMYFUNCTION("""COMPUTED_VALUE"""),"-") -> - | M20: =IFERROR(__xludf.DUMMYFUNCTION("""COMPUTED_VALUE"""),"100 Mbps") -> 100 Mbps | N20: =IFERROR(__xludf.DUMMYFUNCTION("""COMPUTED_VALUE"""),"-") -> - | O20: =IFERROR(__xludf.DUMMYFUNCTION("""COMPUTED_VALUE"""),"-") -> -
A21: =IFERROR(__xludf.DUMMYFUNCTION("""COMPUTED_VALUE"""),"08ª GRE (Catolé do Rocha)") -> 08ª GRE (Catolé do Rocha) | B21: =IFERROR(__xludf.DUMMYFUNCTION("""COMPUTED_VALUE"""),"Riacho dos Cavalos") -> Riacho dos Cavalos | C21: =IFERROR(__xludf.DUMMYFUNCTION("""COMPUTED_VALUE"""),2.500341E7) -> 25003410 | D21: =IFERROR(__xludf.DUMMYFUNCTION("""COMPUTED_VALUE"""),"ECIT EEM Daniel Carneiro") -> ECIT EEM Daniel Carneiro | E21: =IFERROR(__xludf.DUMMYFUNCTION("""COMPUTED_VALUE"""),"URBANA") -> URBANA | F21: =IFERROR(__xludf.DUMMYFUNCTION("""COMPUTED_VALUE"""),"5 Mbps") -> 5 Mbps | G21: =IFERROR(__xludf.DUMMYFUNCTION("""COMPUTED_VALUE"""),"-") -> - | H21: =IFERROR(__xludf.DUMMYFUNCTION("""COMPUTED_VALUE"""),"-") -> - | I21: =IFERROR(__xludf.DUMMYFUNCTION("""COMPUTED_VALUE"""),"-") -> - | J21: =IFERROR(__xludf.DUMMYFUNCTION("""COMPUTED_VALUE"""),"-") -> - | K21: =IFERROR(__xludf.DUMMYFUNCTION("""COMPUTED_VALUE"""),"-") -> - | L21: =IFERROR(__xludf.DUMMYFUNCTION("""COMPUTED_VALUE"""),"-") -> - | M21: =IFERROR(__xludf.DUMMYFUNCTION("""COMPUTED_VALUE"""),"100 Mbps") -> 100 Mbps | N21: =IFERROR(__xludf.DUMMYFUNCTION("""COMPUTED_VALUE"""),"-") -> - | O21: =IFERROR(__xludf.DUMMYFUNCTION("""COMPUTED_VALUE"""),"-") -> -
A22: =IFERROR(__xludf.DUMMYFUNCTION("""COMPUTED_VALUE"""),"08ª GRE (Catolé do Rocha)") -> 08ª GRE (Catolé do Rocha) | B22: =IFERROR(__xludf.DUMMYFUNCTION("""COMPUTED_VALUE"""),"São Bento") -> São Bento | C22: =IFERROR(__xludf.DUMMYFUNCTION("""COMPUTED_VALUE"""),2.5003844E7) -> 25003844 | D22: =IFERROR(__xludf.DUMMYFUNCTION("""COMPUTED_VALUE"""),"EEEFM Joao Silveira Guimaraes") -> EEEFM Joao Silveira Guimaraes | E22: =IFERROR(__xludf.DUMMYFUNCTION("""COMPUTED_VALUE"""),"URBANA") -> URBANA | F22: =IFERROR(__xludf.DUMMYFUNCTION("""COMPUTED_VALUE"""),"2 Mbps") -> 2 Mbps | G22: =IFERROR(__xludf.DUMMYFUNCTION("""COMPUTED_VALUE"""),"-") -> - | H22: =IFERROR(__xludf.DUMMYFUNCTION("""COMPUTED_VALUE"""),"-") -> - | I22: =IFERROR(__xludf.DUMMYFUNCTION("""COMPUTED_VALUE"""),"-") -> - | J22: =IFERROR(__xludf.DUMMYFUNCTION("""COMPUTED_VALUE"""),"30 Mbps") -> 30 Mbps | K22: =IFERROR(__xludf.DUMMYFUNCTION("""COMPUTED_VALUE"""),"-") -> - | L22: =IFERROR(__xludf.DUMMYFUNCTION("""COMPUTED_VALUE"""),"-") -> - | M22: =IFERROR(__xludf.DUMMYFUNCTION("""COMPUTED_VALUE"""),"-") -> - | N22: =IFERROR(__xludf.DUMMYFUNCTION("""COMPUTED_VALUE"""),"-") -> - | O22: =IFERROR(__xludf.DUMMYFUNCTION("""COMPUTED_VALUE"""),"-") -> -
A23: =IFERROR(__xludf.DUMMYFUNCTION("""COMPUTED_VALUE"""),"-") -> - | B23: =IFERROR(__xludf.DUMMYFUNCTION("""COMPUTED_VALUE"""),"São Bento") -> São Bento | C23: =IFERROR(__xludf.DUMMYFUNCTION("""COMPUTED_VALUE"""),2.5003852E7) -> 25003852 | D23: =IFERROR(__xludf.DUMMYFUNCTION("""COMPUTED_VALUE"""),"EEEIF Fausto Meira (MUNICIPALIZADA)") -> EEEIF Fausto Meira (MUNICIPALIZADA) | E23: =IFERROR(__xludf.DUMMYFUNCTION("""COMPUTED_VALUE"""),"-") -> - | F23: =IFERROR(__xludf.DUMMYFUNCTION("""COMPUTED_VALUE"""),"2 Mbps") -> 2 Mbps | G23: =IFERROR(__xludf.DUMMYFUNCTION("""COMPUTED_VALUE"""),"-") -> - | H23: =IFERROR(__xludf.DUMMYFUNCTION("""COMPUTED_VALUE"""),"-") -> - | I23: =IFERROR(__xludf.DUMMYFUNCTION("""COMPUTED_VALUE"""),"-") -> - | J23: =IFERROR(__xludf.DUMMYFUNCTION("""COMPUTED_VALUE"""),"-") -> - | K23: =IFERROR(__xludf.DUMMYFUNCTION("""COMPUTED_VALUE"""),"-") -> - | L23: =IFERROR(__xludf.DUMMYFUNCTION("""COMPUTED_VALUE"""),"-") -> - | N23: =IFERROR(__xludf.DUMMYFUNCTION("""COMPUTED_VALUE"""),"-") -> - | O23: =IFERROR(__xludf.DUMMYFUNCTION("""COMPUTED_VALUE"""),"-") -> - | P23: =IFERROR(__xludf.DUMMYFUNCTION("""COMPUTED_VALUE"""),"MUNICIPALIZADA") -> MUNICIPALIZADA | Q23: =IFERROR(__xludf.DUMMYFUNCTION("""COMPUTED_VALUE"""),"S") -> S
A24: =IFERROR(__xludf.DUMMYFUNCTION("""COMPUTED_VALUE"""),"-") -> - | B24: =IFERROR(__xludf.DUMMYFUNCTION("""COMPUTED_VALUE"""),"São Bento") -> São Bento | C24: =IFERROR(__xludf.DUMMYFUNCTION("""COMPUTED_VALUE"""),2.5003887E7) -> 25003887 | D24: =IFERROR(__xludf.DUMMYFUNCTION("""COMPUTED_VALUE"""),"EEEF Milton Lucio da Silva") -> EEEF Milton Lucio da Silva | E24: =IFERROR(__xludf.DUMMYFUNCTION("""COMPUTED_VALUE"""),"-") -> - | F24: =IFERROR(__xludf.DUMMYFUNCTION("""COMPUTED_VALUE"""),"2 Mbps") -> 2 Mbps | G24: =IFERROR(__xludf.DUMMYFUNCTION("""COMPUTED_VALUE"""),"-") -> - | H24: =IFERROR(__xludf.DUMMYFUNCTION("""COMPUTED_VALUE"""),"-") -> - | I24: =IFERROR(__xludf.DUMMYFUNCTION("""COMPUTED_VALUE"""),"-") -> - | J24: =IFERROR(__xludf.DUMMYFUNCTION("""COMPUTED_VALUE"""),"-") -> - | K24: =IFERROR(__xludf.DUMMYFUNCTION("""COMPUTED_VALUE"""),"-") -> - | L24: =IFERROR(__xludf.DUMMYFUNCTION("""COMPUTED_VALUE"""),"-") -> - | N24: =IFERROR(__xludf.DUMMYFUNCTION("""COMPUTED_VALUE"""),"-") -> - | O24: =IFERROR(__xludf.DUMMYFUNCTION("""COMPUTED_VALUE"""),"-") -> -
A25: =IFERROR(__xludf.DUMMYFUNCTION("""COMPUTED_VALUE"""),"09ª GRE (Cajazeiras)") -> 09ª GRE (Cajazeiras) | B25: =IFERROR(__xludf.DUMMYFUNCTION("""COMPUTED_VALUE"""),"São João do Rio do Peixe") -> São João do Rio do Peixe | C25: =IFERROR(__xludf.DUMMYFUNCTION("""COMPUTED_VALUE"""),2.5004875E7) -> 25004875 | D25: =IFERROR(__xludf.DUMMYFUNCTION("""COMPUTED_VALUE"""),"EEEFM Ministro José Américo de Almeida") -> EEEFM Ministro José Américo de Almeida | E25: =IFERROR(__xludf.DUMMYFUNCTION("""COMPUTED_VALUE"""),"URBANA") -> URBANA | F25: =IFERROR(__xludf.DUMMYFUNCTION("""COMPUTED_VALUE"""),"2 Mbps") -> 2 Mbps | G25: =IFERROR(__xludf.DUMMYFUNCTION("""COMPUTED_VALUE"""),"10 Mbps") -> 10 Mbps | H25: =IFERROR(__xludf.DUMMYFUNCTION("""COMPUTED_VALUE"""),"-") -> - | I25: =IFERROR(__xludf.DUMMYFUNCTION("""COMPUTED_VALUE"""),"-") -> - | J25: =IFERROR(__xludf.DUMMYFUNCTION("""COMPUTED_VALUE"""),"-") -> - | K25: =IFERROR(__xludf.DUMMYFUNCTION("""COMPUTED_VALUE"""),"-") -> - | L25: =IFERROR(__xludf.DUMMYFUNCTION("""COMPUTED_VALUE"""),"-") -> - | M25: =IFERROR(__xludf.DUMMYFUNCTION("""COMPUTED_VALUE"""),"100 Mbps") -> 100 Mbps | N25: =IFERROR(__xludf.DUMMYFUNCTION("""COMPUTED_VALUE"""),"-") -> - | O25: =IFERROR(__xludf.DUMMYFUNCTION("""COMPUTED_VALUE"""),"-") -> -
A26: =IFERROR(__xludf.DUMMYFUNCTION("""COMPUTED_VALUE"""),"09ª GRE (Cajazeiras)") -> 09ª GRE (Cajazeiras) | B26: =IFERROR(__xludf.DUMMYFUNCTION("""COMPUTED_VALUE"""),"São João do Rio do Peixe") -> São João do Rio do Peixe | C26: =IFERROR(__xludf.DUMMYFUNCTION("""COMPUTED_VALUE"""),2.5004883E7) -> 25004883 | D26: =IFERROR(__xludf.DUMMYFUNCTION("""COMPUTED_VALUE"""),"ECIT Coronel Jacob Guilherme Frantz") -> ECIT Coronel Jacob Guilherme Frantz | E26: =IFERROR(__xludf.DUMMYFUNCTION("""COMPUTED_VALUE"""),"URBANA") -> URBANA | F26: =IFERROR(__xludf.DUMMYFUNCTION("""COMPUTED_VALUE"""),"2 Mbps") -> 2 Mbps | G26: =IFERROR(__xludf.DUMMYFUNCTION("""COMPUTED_VALUE"""),"-") -> - | H26: =IFERROR(__xludf.DUMMYFUNCTION("""COMPUTED_VALUE"""),"-") -> - | I26: =IFERROR(__xludf.DUMMYFUNCTION("""COMPUTED_VALUE"""),"-") -> - | J26: =IFERROR(__xludf.DUMMYFUNCTION("""COMPUTED_VALUE"""),"50 Mbps") -> 50 Mbps | K26: =IFERROR(__xludf.DUMMYFUNCTION("""COMPUTED_VALUE"""),"-") -> - | L26: =IFERROR(__xludf.DUMMYFUNCTION("""COMPUTED_VALUE"""),"-") -> - | M26: =IFERROR(__xludf.DUMMYFUNCTION("""COMPUTED_VALUE"""),"-") -> - | N26: =IFERROR(__xludf.DUMMYFUNCTION("""COMPUTED_VALUE"""),"-") -> - | O26: =IFERROR(__xludf.DUMMYFUNCTION("""COMPUTED_VALUE"""),"-") -> -
A27: =IFERROR(__xludf.DUMMYFUNCTION("""COMPUTED_VALUE"""),"-") -> - | B27: =IFERROR(__xludf.DUMMYFUNCTION("""COMPUTED_VALUE"""),"São João do Rio do Peixe") -> São João do Rio do Peixe | C27: =IFERROR(__xludf.DUMMYFUNCTION("""COMPUTED_VALUE"""),2.5004972E7) -> 25004972 | D27: =IFERROR(__xludf.DUMMYFUNCTION("""COMPUTED_VALUE"""),"EEEF Conego Manoel Jacome (MUNICIPALIZADA) (Solicitado remanejamento do link para a Sede da GRE08 em 25/04/2025)") -> EEEF Conego Manoel Jacome (MUNICIPALIZADA) (Solicitado remanejamento do link para a Sede da GRE08 em 25/04/2025) | E27: =IFERROR(__xludf.DUMMYFUNCTION("""COMPUTED_VALUE"""),"-") -> - | F27: =IFERROR(__xludf.DUMMYFUNCTION("""COMPUTED_VALUE"""),"2 Mbps") -> 2 Mbps | G27: =IFERROR(__xludf.DUMMYFUNCTION("""COMPUTED_VALUE"""),"-") -> - | H27: =IFERROR(__xludf.DUMMYFUNCTION("""COMPUTED_VALUE"""),"-") -> - | I27: =IFERROR(__xludf.DUMMYFUNCTION("""COMPUTED_VALUE"""),"-") -> - | J27: =IFERROR(__xludf.DUMMYFUNCTION("""COMPUTED_VALUE"""),"-") -> - | K27: =IFERROR(__xludf.DUMMYFUNCTION("""COMPUTED_VALUE"""),"-") -> - | L27: =IFERROR(__xludf.DUMMYFUNCTION("""COMPUTED_VALUE"""),"-") -> - | M27: =IFERROR(__xludf.DUMMYFUNCTION("""COMPUTED_VALUE"""),"-") -> - | N27: =IFERROR(__xludf.DUMMYFUNCTION("""COMPUTED_VALUE"""),"-") -> - | O27: =IFERROR(__xludf.DUMMYFUNCTION("""COMPUTED_VALUE"""),"-") -> - | P27: =IFERROR(__xludf.DUMMYFUNCTION("""COMPUTED_VALUE"""),"MUNICIPALIZADA") -> MUNICIPALIZADA | Q27: =IFERROR(__xludf.DUMMYFUNCTION("""COMPUTED_VALUE"""),"S") -> S
A28: =IFERROR(__xludf.DUMMYFUNCTION("""COMPUTED_VALUE"""),"09ª GRE (Cajazeiras)") -> 09ª GRE (Cajazeiras) | B28: =IFERROR(__xludf.DUMMYFUNCTION("""COMPUTED_VALUE"""),"São João do Rio do Peixe") -> São João do Rio do Peixe | C28: =IFERROR(__xludf.DUMMYFUNCTION("""COMPUTED_VALUE"""),2.5004999E7) -> 25004999 | D28: =IFERROR(__xludf.DUMMYFUNCTION("""COMPUTED_VALUE"""),"EEEF de Bandarra") -> EEEF de Bandarra | E28: =IFERROR(__xludf.DUMMYFUNCTION("""COMPUTED_VALUE"""),"RURAL") -> RURAL | F28: =IFERROR(__xludf.DUMMYFUNCTION("""COMPUTED_VALUE"""),"-") -> - | G28: =IFERROR(__xludf.DUMMYFUNCTION("""COMPUTED_VALUE"""),"-") -> - | H28: =IFERROR(__xludf.DUMMYFUNCTION("""COMPUTED_VALUE"""),"-") -> - | I28: =IFERROR(__xludf.DUMMYFUNCTION("""COMPUTED_VALUE"""),"-") -> - | J28: =IFERROR(__xludf.DUMMYFUNCTION("""COMPUTED_VALUE"""),"-") -> - | K28: =IFERROR(__xludf.DUMMYFUNCTION("""COMPUTED_VALUE"""),"-") -> - | L28: =IFERROR(__xludf.DUMMYFUNCTION("""COMPUTED_VALUE"""),"-") -> - | M28: =IFERROR(__xludf.DUMMYFUNCTION("""COMPUTED_VALUE"""),"-") -> - | N28: =IFERROR(__xludf.DUMMYFUNCTION("""COMPUTED_VALUE"""),"Satélite") -> Satélite | O28: =IFERROR(__xludf.DUMMYFUNCTION("""COMPUTED_VALUE"""),"-") -> -
A29: =IFERROR(__xludf.DUMMYFUNCTION("""COMPUTED_VALUE"""),"09ª GRE (Cajazeiras)") -> 09ª GRE (Cajazeiras) | B29: =IFERROR(__xludf.DUMMYFUNCTION("""COMPUTED_VALUE"""),"Poço de José de Moura") -> Poço de José de Moura | C29: =IFERROR(__xludf.DUMMYFUNCTION("""COMPUTED_VALUE"""),2.5005995E7) -> 25005995 | D29: =IFERROR(__xludf.DUMMYFUNCTION("""COMPUTED_VALUE"""),"ECI EEFM Professora Francisca Fonseca Matias") -> ECI EEFM Professora Francisca Fonseca Matias | E29: =IFERROR(__xludf.DUMMYFUNCTION("""COMPUTED_VALUE"""),"URBANA") -> URBANA | F29: =IFERROR(__xludf.DUMMYFUNCTION("""COMPUTED_VALUE"""),"2 Mbps") -> 2 Mbps | G29: =IFERROR(__xludf.DUMMYFUNCTION("""COMPUTED_VALUE"""),"-") -> - | H29: =IFERROR(__xludf.DUMMYFUNCTION("""COMPUTED_VALUE"""),"-") -> - | I29: =IFERROR(__xludf.DUMMYFUNCTION("""COMPUTED_VALUE"""),"-") -> - | J29: =IFERROR(__xludf.DUMMYFUNCTION("""COMPUTED_VALUE"""),"-") -> - | K29: =IFERROR(__xludf.DUMMYFUNCTION("""COMPUTED_VALUE"""),"-") -> - | L29: =IFERROR(__xludf.DUMMYFUNCTION("""COMPUTED_VALUE"""),"-") -> - | M29: =IFERROR(__xludf.DUMMYFUNCTION("""COMPUTED_VALUE"""),"100 Mbps") -> 100 Mbps | N29: =IFERROR(__xludf.DUMMYFUNCTION("""COMPUTED_VALUE"""),"-") -> - | O29: =IFERROR(__xludf.DUMMYFUNCTION("""COMPUTED_VALUE"""),"-") -> -
A30: =IFERROR(__xludf.DUMMYFUNCTION("""COMPUTED_VALUE"""),"09ª GRE (Cajazeiras)") -> 09ª GRE (Cajazeiras) | B30: =IFERROR(__xludf.DUMMYFUNCTION("""COMPUTED_VALUE"""),"Bom Jesus") -> Bom Jesus | C30: =IFERROR(__xludf.DUMMYFUNCTION("""COMPUTED_VALUE"""),2.5006029E7) -> 25006029 | D30: =IFERROR(__xludf.DUMMYFUNCTION("""COMPUTED_VALUE"""),"EEEFM Prof Joaquim Umbelino") -> EEEFM Prof Joaquim Umbelino | E30: =IFERROR(__xludf.DUMMYFUNCTION("""COMPUTED_VALUE"""),"URBANA") -> URBANA | F30: =IFERROR(__xludf.DUMMYFUNCTION("""COMPUTED_VALUE"""),"2 Mbps") -> 2 Mbps | G30: =IFERROR(__xludf.DUMMYFUNCTION("""COMPUTED_VALUE"""),"-") -> - | H30: =IFERROR(__xludf.DUMMYFUNCTION("""COMPUTED_VALUE"""),"-") -> - | I30: =IFERROR(__xludf.DUMMYFUNCTION("""COMPUTED_VALUE"""),"-") -> - | J30: =IFERROR(__xludf.DUMMYFUNCTION("""COMPUTED_VALUE"""),"-") -> - | K30: =IFERROR(__xludf.DUMMYFUNCTION("""COMPUTED_VALUE"""),"-") -> - | L30: =IFERROR(__xludf.DUMMYFUNCTION("""COMPUTED_VALUE"""),"-") -> - | M30: =IFERROR(__xludf.DUMMYFUNCTION("""COMPUTED_VALUE"""),"100 Mbps") -> 100 Mbps | N30: =IFERROR(__xludf.DUMMYFUNCTION("""COMPUTED_VALUE"""),"-") -> - | O30: =IFERROR(__xludf.DUMMYFUNCTION("""COMPUTED_VALUE"""),"-") -> -
A31: =IFERROR(__xludf.DUMMYFUNCTION("""COMPUTED_VALUE"""),"09ª GRE (Cajazeiras)") -> 09ª GRE (Cajazeiras) | B31: =IFERROR(__xludf.DUMMYFUNCTION("""COMPUTED_VALUE"""),"Bonito de Santa Fé") -> Bonito de Santa Fé | C31: =IFERROR(__xludf.DUMMYFUNCTION("""COMPUTED_VALUE"""),2.5006223E7) -> 25006223 | D31: =IFERROR(__xludf.DUMMYFUNCTION("""COMPUTED_VALUE"""),"Ecit Monsenhor Morais") -> Ecit Monsenhor Morais | E31: =IFERROR(__xludf.DUMMYFUNCTION("""COMPUTED_VALUE"""),"URBANA") -> URBANA | F31: =IFERROR(__xludf.DUMMYFUNCTION("""COMPUTED_VALUE"""),"2 Mbps") -> 2 Mbps | G31: =IFERROR(__xludf.DUMMYFUNCTION("""COMPUTED_VALUE"""),"-") -> - | H31: =IFERROR(__xludf.DUMMYFUNCTION("""COMPUTED_VALUE"""),"-") -> - | I31: =IFERROR(__xludf.DUMMYFUNCTION("""COMPUTED_VALUE"""),"-") -> - | J31: =IFERROR(__xludf.DUMMYFUNCTION("""COMPUTED_VALUE"""),"-") -> - | K31: =IFERROR(__xludf.DUMMYFUNCTION("""COMPUTED_VALUE"""),"-") -> - | L31: =IFERROR(__xludf.DUMMYFUNCTION("""COMPUTED_VALUE"""),"-") -> - | M31: =IFERROR(__xludf.DUMMYFUNCTION("""COMPUTED_VALUE"""),"100 Mbps") -> 100 Mbps | N31: =IFERROR(__xludf.DUMMYFUNCTION("""COMPUTED_VALUE"""),"-") -> - | O31: =IFERROR(__xludf.DUMMYFUNCTION("""COMPUTED_VALUE"""),"-") -> -
A32: =IFERROR(__xludf.DUMMYFUNCTION("""COMPUTED_VALUE"""),"09ª GRE (Cajazeiras)") -> 09ª GRE (Cajazeiras) | B32: =IFERROR(__xludf.DUMMYFUNCTION("""COMPUTED_VALUE"""),"Bonito de Santa Fé") -> Bonito de Santa Fé | C32: =IFERROR(__xludf.DUMMYFUNCTION("""COMPUTED_VALUE"""),2.5006231E7) -> 25006231 | D32: =IFERROR(__xludf.DUMMYFUNCTION("""COMPUTED_VALUE"""),"EEEF Joaquim Nabuco") -> EEEF Joaquim Nabuco | E32: =IFERROR(__xludf.DUMMYFUNCTION("""COMPUTED_VALUE"""),"URBANA") -> URBANA | F32: =IFERROR(__xludf.DUMMYFUNCTION("""COMPUTED_VALUE"""),"2 Mbps") -> 2 Mbps | G32: =IFERROR(__xludf.DUMMYFUNCTION("""COMPUTED_VALUE"""),"-") -> - | H32: =IFERROR(__xludf.DUMMYFUNCTION("""COMPUTED_VALUE"""),"-") -> - | I32: =IFERROR(__xludf.DUMMYFUNCTION("""COMPUTED_VALUE"""),"-") -> - | J32: =IFERROR(__xludf.DUMMYFUNCTION("""COMPUTED_VALUE"""),"-") -> - | K32: =IFERROR(__xludf.DUMMYFUNCTION("""COMPUTED_VALUE"""),"-") -> - | L32: =IFERROR(__xludf.DUMMYFUNCTION("""COMPUTED_VALUE"""),"-") -> - | M32: =IFERROR(__xludf.DUMMYFUNCTION("""COMPUTED_VALUE"""),"100 Mbps") -> 100 Mbps | N32: =IFERROR(__xludf.DUMMYFUNCTION("""COMPUTED_VALUE"""),"-") -> - | O32: =IFERROR(__xludf.DUMMYFUNCTION("""COMPUTED_VALUE"""),"-") -> -
A33: =IFERROR(__xludf.DUMMYFUNCTION("""COMPUTED_VALUE"""),"09ª GRE (Cajazeiras)") -> 09ª GRE (Cajazeiras) | B33: =IFERROR(__xludf.DUMMYFUNCTION("""COMPUTED_VALUE"""),"Cachoeira dos Índios") -> Cachoeira dos Índios | C33: =IFERROR(__xludf.DUMMYFUNCTION("""COMPUTED_VALUE"""),2.5007092E7) -> 25007092 | D33: =IFERROR(__xludf.DUMMYFUNCTION("""COMPUTED_VALUE"""),"Eci EEFM Professor Adalberto de Sousa Oliveira") -> Eci EEFM Professor Adalberto de Sousa Oliveira | E33: =IFERROR(__xludf.DUMMYFUNCTION("""COMPUTED_VALUE"""),"URBANA") -> URBANA | F33: =IFERROR(__xludf.DUMMYFUNCTION("""COMPUTED_VALUE"""),"2 Mbps") -> 2 Mbps | G33: =IFERROR(__xludf.DUMMYFUNCTION("""COMPUTED_VALUE"""),"-") -> - | H33: =IFERROR(__xludf.DUMMYFUNCTION("""COMPUTED_VALUE"""),"-") -> - | I33: =IFERROR(__xludf.DUMMYFUNCTION("""COMPUTED_VALUE"""),"-") -> - | J33: =IFERROR(__xludf.DUMMYFUNCTION("""COMPUTED_VALUE"""),"-") -> - | K33: =IFERROR(__xludf.DUMMYFUNCTION("""COMPUTED_VALUE"""),"-") -> - | L33: =IFERROR(__xludf.DUMMYFUNCTION("""COMPUTED_VALUE"""),"-") -> - | M33: =IFERROR(__xludf.DUMMYFUNCTION("""COMPUTED_VALUE"""),"100 Mbps") -> 100 Mbps | N33: =IFERROR(__xludf.DUMMYFUNCTION("""COMPUTED_VALUE"""),"-") -> - | O33: =IFERROR(__xludf.DUMMYFUNCTION("""COMPUTED_VALUE"""),"-") -> -
A34: =IFERROR(__xludf.DUMMYFUNCTION("""COMPUTED_VALUE"""),"09ª GRE (Cajazeiras)") -> 09ª GRE (Cajazeiras) | B34: =IFERROR(__xludf.DUMMYFUNCTION("""COMPUTED_VALUE"""),"Cajazeiras") -> Cajazeiras | C34: =IFERROR(__xludf.DUMMYFUNCTION("""COMPUTED_VALUE"""),2.5007718E7) -> 25007718 | D34: =IFERROR(__xludf.DUMMYFUNCTION("""COMPUTED_VALUE"""),"EEEFM Prof Manoel Mangueira Lima") -> EEEFM Prof Manoel Mangueira Lima | E34: =IFERROR(__xludf.DUMMYFUNCTION("""COMPUTED_VALUE"""),"URBANA") -> URBANA | F34: =IFERROR(__xludf.DUMMYFUNCTION("""COMPUTED_VALUE"""),"2 Mbps") -> 2 Mbps | G34: =IFERROR(__xludf.DUMMYFUNCTION("""COMPUTED_VALUE"""),"-") -> - | H34: =IFERROR(__xludf.DUMMYFUNCTION("""COMPUTED_VALUE"""),"-") -> - | I34: =IFERROR(__xludf.DUMMYFUNCTION("""COMPUTED_VALUE"""),"-") -> - | J34: =IFERROR(__xludf.DUMMYFUNCTION("""COMPUTED_VALUE"""),"100 Mbps") -> 100 Mbps | K34: =IFERROR(__xludf.DUMMYFUNCTION("""COMPUTED_VALUE"""),"-") -> - | L34: =IFERROR(__xludf.DUMMYFUNCTION("""COMPUTED_VALUE"""),"-") -> - | M34: =IFERROR(__xludf.DUMMYFUNCTION("""COMPUTED_VALUE"""),"-") -> - | N34: =IFERROR(__xludf.DUMMYFUNCTION("""COMPUTED_VALUE"""),"-") -> - | O34: =IFERROR(__xludf.DUMMYFUNCTION("""COMPUTED_VALUE"""),"-") -> -
A35: =IFERROR(__xludf.DUMMYFUNCTION("""COMPUTED_VALUE"""),"09ª GRE (Cajazeiras)") -> 09ª GRE (Cajazeiras) | B35: =IFERROR(__xludf.DUMMYFUNCTION("""COMPUTED_VALUE"""),"Cajazeiras") -> Cajazeiras | C35: =IFERROR(__xludf.DUMMYFUNCTION("""COMPUTED_VALUE"""),2.5007726E7) -> 25007726 | D35: =IFERROR(__xludf.DUMMYFUNCTION("""COMPUTED_VALUE"""),"Eci Professor Crispim Coelho") -> Eci Professor Crispim Coelho | E35: =IFERROR(__xludf.DUMMYFUNCTION("""COMPUTED_VALUE"""),"URBANA") -> URBANA | F35: =IFERROR(__xludf.DUMMYFUNCTION("""COMPUTED_VALUE"""),"2 Mbps") -> 2 Mbps | G35: =IFERROR(__xludf.DUMMYFUNCTION("""COMPUTED_VALUE"""),"10 Mbps") -> 10 Mbps | H35: =IFERROR(__xludf.DUMMYFUNCTION("""COMPUTED_VALUE"""),"-") -> - | I35: =IFERROR(__xludf.DUMMYFUNCTION("""COMPUTED_VALUE"""),"-") -> - | J35: =IFERROR(__xludf.DUMMYFUNCTION("""COMPUTED_VALUE"""),"100 Mbps") -> 100 Mbps | K35: =IFERROR(__xludf.DUMMYFUNCTION("""COMPUTED_VALUE"""),"-") -> - | L35: =IFERROR(__xludf.DUMMYFUNCTION("""COMPUTED_VALUE"""),"-") -> - | M35: =IFERROR(__xludf.DUMMYFUNCTION("""COMPUTED_VALUE"""),"-") -> - | N35: =IFERROR(__xludf.DUMMYFUNCTION("""COMPUTED_VALUE"""),"-") -> - | O35: =IFERROR(__xludf.DUMMYFUNCTION("""COMPUTED_VALUE"""),"-") -> -
A36: =IFERROR(__xludf.DUMMYFUNCTION("""COMPUTED_VALUE"""),"09ª GRE (Cajazeiras)") -> 09ª GRE (Cajazeiras) | B36: =IFERROR(__xludf.DUMMYFUNCTION("""COMPUTED_VALUE"""),"Cajazeiras") -> Cajazeiras | C36: =IFERROR(__xludf.DUMMYFUNCTION("""COMPUTED_VALUE"""),2.5007742E7) -> 25007742 | D36: =IFERROR(__xludf.DUMMYFUNCTION("""COMPUTED_VALUE"""),"EEEF Dom Moises Coelho") -> EEEF Dom Moises Coelho | E36: =IFERROR(__xludf.DUMMYFUNCTION("""COMPUTED_VALUE"""),"URBANA") -> URBANA | F36: =IFERROR(__xludf.DUMMYFUNCTION("""COMPUTED_VALUE"""),"2 Mbps") -> 2 Mbps | G36: =IFERROR(__xludf.DUMMYFUNCTION("""COMPUTED_VALUE"""),"-") -> - | H36: =IFERROR(__xludf.DUMMYFUNCTION("""COMPUTED_VALUE"""),"-") -> - | I36: =IFERROR(__xludf.DUMMYFUNCTION("""COMPUTED_VALUE"""),"-") -> - | J36: =IFERROR(__xludf.DUMMYFUNCTION("""COMPUTED_VALUE"""),"-") -> - | K36: =IFERROR(__xludf.DUMMYFUNCTION("""COMPUTED_VALUE"""),"-") -> - | L36: =IFERROR(__xludf.DUMMYFUNCTION("""COMPUTED_VALUE"""),"-") -> - | M36: =IFERROR(__xludf.DUMMYFUNCTION("""COMPUTED_VALUE"""),"100 Mbps") -> 100 Mbps | N36: =IFERROR(__xludf.DUMMYFUNCTION("""COMPUTED_VALUE"""),"-") -> - | O36: =IFERROR(__xludf.DUMMYFUNCTION("""COMPUTED_VALUE"""),"-") -> -
A37: =IFERROR(__xludf.DUMMYFUNCTION("""COMPUTED_VALUE"""),"-") -> - | B37: =IFERROR(__xludf.DUMMYFUNCTION("""COMPUTED_VALUE"""),"Queimadas") -> Queimadas | C37: =IFERROR(__xludf.DUMMYFUNCTION("""COMPUTED_VALUE"""),2.500775E7) -> 25007750 | E37: =IFERROR(__xludf.DUMMYFUNCTION("""COMPUTED_VALUE"""),"-") -> - | F37: =IFERROR(__xludf.DUMMYFUNCTION("""COMPUTED_VALUE"""),"2 Mbps") -> 2 Mbps | G37: =IFERROR(__xludf.DUMMYFUNCTION("""COMPUTED_VALUE"""),"-") -> - | H37: =IFERROR(__xludf.DUMMYFUNCTION("""COMPUTED_VALUE"""),"-") -> - | I37: =IFERROR(__xludf.DUMMYFUNCTION("""COMPUTED_VALUE"""),"-") -> - | J37: =IFERROR(__xludf.DUMMYFUNCTION("""COMPUTED_VALUE"""),"-") -> - | K37: =IFERROR(__xludf.DUMMYFUNCTION("""COMPUTED_VALUE"""),"-") -> - | L37: =IFERROR(__xludf.DUMMYFUNCTION("""COMPUTED_VALUE"""),"-") -> - | M37: =IFERROR(__xludf.DUMMYFUNCTION("""COMPUTED_VALUE"""),"-") -> - | N37: =IFERROR(__xludf.DUMMYFUNCTION("""COMPUTED_VALUE"""),"-") -> - | O37: =IFERROR(__xludf.DUMMYFUNCTION("""COMPUTED_VALUE"""),"-") -> - | P37: =IFERROR(__xludf.DUMMYFUNCTION("""COMPUTED_VALUE"""),"MUNICIPALIZADA") -> MUNICIPALIZADA | Q37: =IFERROR(__xludf.DUMMYFUNCTION("""COMPUTED_VALUE"""),"S") -> S
A38: =IFERROR(__xludf.DUMMYFUNCTION("""COMPUTED_VALUE"""),"-") -> - | B38: =IFERROR(__xludf.DUMMYFUNCTION("""COMPUTED_VALUE"""),"Cajazeiras") -> Cajazeiras | C38: =IFERROR(__xludf.DUMMYFUNCTION("""COMPUTED_VALUE"""),2.5007777E7) -> 25007777 | D38: =IFERROR(__xludf.DUMMYFUNCTION("""COMPUTED_VALUE"""),"EEEF Cel Joaquim Matos (MUNICIPALIZADA) (Solicitado remanejamento do link para a Sede da GRE16 em 25/04/2025)") -> EEEF Cel Joaquim Matos (MUNICIPALIZADA) (Solicitado remanejamento do link para a Sede da GRE16 em 25/04/2025) | E38: =IFERROR(__xludf.DUMMYFUNCTION("""COMPUTED_VALUE"""),"-") -> - | F38: =IFERROR(__xludf.DUMMYFUNCTION("""COMPUTED_VALUE"""),"2 Mbps") -> 2 Mbps | G38: =IFERROR(__xludf.DUMMYFUNCTION("""COMPUTED_VALUE"""),"-") -> - | H38: =IFERROR(__xludf.DUMMYFUNCTION("""COMPUTED_VALUE"""),"-") -> - | I38: =IFERROR(__xludf.DUMMYFUNCTION("""COMPUTED_VALUE"""),"-") -> - | J38: =IFERROR(__xludf.DUMMYFUNCTION("""COMPUTED_VALUE"""),"-") -> - | K38: =IFERROR(__xludf.DUMMYFUNCTION("""COMPUTED_VALUE"""),"-") -> - | L38: =IFERROR(__xludf.DUMMYFUNCTION("""COMPUTED_VALUE"""),"-") -> - | M38: =IFERROR(__xludf.DUMMYFUNCTION("""COMPUTED_VALUE"""),"-") -> - | N38: =IFERROR(__xludf.DUMMYFUNCTION("""COMPUTED_VALUE"""),"-") -> - | O38: =IFERROR(__xludf.DUMMYFUNCTION("""COMPUTED_VALUE"""),"-") -> - | P38: =IFERROR(__xludf.DUMMYFUNCTION("""COMPUTED_VALUE"""),"MUNICIPALIZADA") -> MUNICIPALIZADA | Q38: =IFERROR(__xludf.DUMMYFUNCTION("""COMPUTED_VALUE"""),"S") -> S
A39: =IFERROR(__xludf.DUMMYFUNCTION("""COMPUTED_VALUE"""),"09ª GRE (Cajazeiras)") -> 09ª GRE (Cajazeiras) | B39: =IFERROR(__xludf.DUMMYFUNCTION("""COMPUTED_VALUE"""),"Cajazeiras") -> Cajazeiras | C39: =IFERROR(__xludf.DUMMYFUNCTION("""COMPUTED_VALUE"""),2.5007785E7) -> 25007785 | D39: =IFERROR(__xludf.DUMMYFUNCTION("""COMPUTED_VALUE"""),"ECIT Cristiano Cartaxo") -> ECIT Cristiano Cartaxo | E39: =IFERROR(__xludf.DUMMYFUNCTION("""COMPUTED_VALUE"""),"URBANA") -> URBANA | F39: =IFERROR(__xludf.DUMMYFUNCTION("""COMPUTED_VALUE"""),"2 Mbps") -> 2 Mbps | G39: =IFERROR(__xludf.DUMMYFUNCTION("""COMPUTED_VALUE"""),"10 Mbps") -> 10 Mbps | H39: =IFERROR(__xludf.DUMMYFUNCTION("""COMPUTED_VALUE"""),"-") -> - | I39: =IFERROR(__xludf.DUMMYFUNCTION("""COMPUTED_VALUE"""),"-") -> - | J39: =IFERROR(__xludf.DUMMYFUNCTION("""COMPUTED_VALUE"""),"100 Mbps") -> 100 Mbps | K39: =IFERROR(__xludf.DUMMYFUNCTION("""COMPUTED_VALUE"""),"-") -> - | L39: =IFERROR(__xludf.DUMMYFUNCTION("""COMPUTED_VALUE"""),"-") -> - | M39: =IFERROR(__xludf.DUMMYFUNCTION("""COMPUTED_VALUE"""),"-") -> - | N39: =IFERROR(__xludf.DUMMYFUNCTION("""COMPUTED_VALUE"""),"-") -> - | O39: =IFERROR(__xludf.DUMMYFUNCTION("""COMPUTED_VALUE"""),"-") -> -
A40: =IFERROR(__xludf.DUMMYFUNCTION("""COMPUTED_VALUE"""),"-") -> - | B40: =IFERROR(__xludf.DUMMYFUNCTION("""COMPUTED_VALUE"""),"Cajazeiras") -> Cajazeiras | C40: =IFERROR(__xludf.DUMMYFUNCTION("""COMPUTED_VALUE"""),2.5007807E7) -> 25007807 | D40: =IFERROR(__xludf.DUMMYFUNCTION("""COMPUTED_VALUE"""),"EEEF Joaquim Victor Jurema (MUNICIPALIZADA) (Solicitado remanejamento do link para a EEEF Frei Alberto - Fagundes em 25/04/2025)") -> EEEF Joaquim Victor Jurema (MUNICIPALIZADA) (Solicitado remanejamento do link para a EEEF Frei Alberto - Fagundes em 25/04/2025) | E40: =IFERROR(__xludf.DUMMYFUNCTION("""COMPUTED_VALUE"""),"-") -> - | F40: =IFERROR(__xludf.DUMMYFUNCTION("""COMPUTED_VALUE"""),"2 Mbps") -> 2 Mbps | G40: =IFERROR(__xludf.DUMMYFUNCTION("""COMPUTED_VALUE"""),"-") -> - | H40: =IFERROR(__xludf.DUMMYFUNCTION("""COMPUTED_VALUE"""),"-") -> - | I40: =IFERROR(__xludf.DUMMYFUNCTION("""COMPUTED_VALUE"""),"-") -> - | J40: =IFERROR(__xludf.DUMMYFUNCTION("""COMPUTED_VALUE"""),"-") -> - | K40: =IFERROR(__xludf.DUMMYFUNCTION("""COMPUTED_VALUE"""),"-") -> - | L40: =IFERROR(__xludf.DUMMYFUNCTION("""COMPUTED_VALUE"""),"-") -> - | M40: =IFERROR(__xludf.DUMMYFUNCTION("""COMPUTED_VALUE"""),"-") -> - | N40: =IFERROR(__xludf.DUMMYFUNCTION("""COMPUTED_VALUE"""),"-") -> - | O40: =IFERROR(__xludf.DUMMYFUNCTION("""COMPUTED_VALUE"""),"-") -> - | P40: =IFERROR(__xludf.DUMMYFUNCTION("""COMPUTED_VALUE"""),"MUNICIPALIZADA") -> MUNICIPALIZADA | Q40: =IFERROR(__xludf.DUMMYFUNCTION("""COMPUTED_VALUE"""),"S") -> S
A41: =IFERROR(__xludf.DUMMYFUNCTION("""COMPUTED_VALUE"""),"09ª GRE (Cajazeiras)") -> 09ª GRE (Cajazeiras) | B41: =IFERROR(__xludf.DUMMYFUNCTION("""COMPUTED_VALUE"""),"Cajazeiras") -> Cajazeiras | C41: =IFERROR(__xludf.DUMMYFUNCTION("""COMPUTED_VALUE"""),2.500784E7) -> 25007840 | D41: =IFERROR(__xludf.DUMMYFUNCTION("""COMPUTED_VALUE"""),"E.E.E.F. Monsenhor Joao Milanes") -> E.E.E.F. Monsenhor Joao Milanes | E41: =IFERROR(__xludf.DUMMYFUNCTION("""COMPUTED_VALUE"""),"URBANA") -> URBANA | F41: =IFERROR(__xludf.DUMMYFUNCTION("""COMPUTED_VALUE"""),"2 Mbps") -> 2 Mbps | G41: =IFERROR(__xludf.DUMMYFUNCTION("""COMPUTED_VALUE"""),"-") -> - | H41: =IFERROR(__xludf.DUMMYFUNCTION("""COMPUTED_VALUE"""),"-") -> - | I41: =IFERROR(__xludf.DUMMYFUNCTION("""COMPUTED_VALUE"""),"-") -> - | J41: =IFERROR(__xludf.DUMMYFUNCTION("""COMPUTED_VALUE"""),"-") -> - | K41: =IFERROR(__xludf.DUMMYFUNCTION("""COMPUTED_VALUE"""),"-") -> - | L41: =IFERROR(__xludf.DUMMYFUNCTION("""COMPUTED_VALUE"""),"-") -> - | M41: =IFERROR(__xludf.DUMMYFUNCTION("""COMPUTED_VALUE"""),"100 Mbps") -> 100 Mbps | N41: =IFERROR(__xludf.DUMMYFUNCTION("""COMPUTED_VALUE"""),"-") -> - | O41: =IFERROR(__xludf.DUMMYFUNCTION("""COMPUTED_VALUE"""),"-") -> -
A42: =IFERROR(__xludf.DUMMYFUNCTION("""COMPUTED_VALUE"""),"09ª GRE (Cajazeiras)") -> 09ª GRE (Cajazeiras) | B42: =IFERROR(__xludf.DUMMYFUNCTION("""COMPUTED_VALUE"""),"Cajazeiras") -> Cajazeiras | C42: =IFERROR(__xludf.DUMMYFUNCTION("""COMPUTED_VALUE"""),2.5007904E7) -> 25007904 | D42: =IFERROR(__xludf.DUMMYFUNCTION("""COMPUTED_VALUE"""),"EEEFM Mons Constantino Vieira") -> EEEFM Mons Constantino Vieira | E42: =IFERROR(__xludf.DUMMYFUNCTION("""COMPUTED_VALUE"""),"URBANA") -> URBANA | F42: =IFERROR(__xludf.DUMMYFUNCTION("""COMPUTED_VALUE"""),"2 Mbps") -> 2 Mbps | G42: =IFERROR(__xludf.DUMMYFUNCTION("""COMPUTED_VALUE"""),"-") -> - | H42: =IFERROR(__xludf.DUMMYFUNCTION("""COMPUTED_VALUE"""),"-") -> - | I42: =IFERROR(__xludf.DUMMYFUNCTION("""COMPUTED_VALUE"""),"-") -> - | J42: =IFERROR(__xludf.DUMMYFUNCTION("""COMPUTED_VALUE"""),"100 Mbps") -> 100 Mbps | K42: =IFERROR(__xludf.DUMMYFUNCTION("""COMPUTED_VALUE"""),"-") -> - | L42: =IFERROR(__xludf.DUMMYFUNCTION("""COMPUTED_VALUE"""),"-") -> - | M42: =IFERROR(__xludf.DUMMYFUNCTION("""COMPUTED_VALUE"""),"-") -> - | N42: =IFERROR(__xludf.DUMMYFUNCTION("""COMPUTED_VALUE"""),"-") -> - | O42: =IFERROR(__xludf.DUMMYFUNCTION("""COMPUTED_VALUE"""),"-") -> -
A43: =IFERROR(__xludf.DUMMYFUNCTION("""COMPUTED_VALUE"""),"09ª GRE (Cajazeiras)") -> 09ª GRE (Cajazeiras) | B43: =IFERROR(__xludf.DUMMYFUNCTION("""COMPUTED_VALUE"""),"Cajazeiras") -> Cajazeiras | C43: =IFERROR(__xludf.DUMMYFUNCTION("""COMPUTED_VALUE"""),2.5008951E7) -> 25008951 | D43: =IFERROR(__xludf.DUMMYFUNCTION("""COMPUTED_VALUE"""),"Esc Profissional Monte Carmelo") -> Esc Profissional Monte Carmelo | E43: =IFERROR(__xludf.DUMMYFUNCTION("""COMPUTED_VALUE"""),"URBANA") -> URBANA | F43: =IFERROR(__xludf.DUMMYFUNCTION("""COMPUTED_VALUE"""),"2 Mbps") -> 2 Mbps | G43: =IFERROR(__xludf.DUMMYFUNCTION("""COMPUTED_VALUE"""),"-") -> - | H43: =IFERROR(__xludf.DUMMYFUNCTION("""COMPUTED_VALUE"""),"-") -> - | I43: =IFERROR(__xludf.DUMMYFUNCTION("""COMPUTED_VALUE"""),"-") -> - | J43: =IFERROR(__xludf.DUMMYFUNCTION("""COMPUTED_VALUE"""),"-") -> - | K43: =IFERROR(__xludf.DUMMYFUNCTION("""COMPUTED_VALUE"""),"-") -> - | L43: =IFERROR(__xludf.DUMMYFUNCTION("""COMPUTED_VALUE"""),"-") -> - | M43: =IFERROR(__xludf.DUMMYFUNCTION("""COMPUTED_VALUE"""),"100 Mbps") -> 100 Mbps | N43: =IFERROR(__xludf.DUMMYFUNCTION("""COMPUTED_VALUE"""),"-") -> - | O43: =IFERROR(__xludf.DUMMYFUNCTION("""COMPUTED_VALUE"""),"-") -> -
A44: =IFERROR(__xludf.DUMMYFUNCTION("""COMPUTED_VALUE"""),"09ª GRE (Cajazeiras)") -> 09ª GRE (Cajazeiras) | B44: =IFERROR(__xludf.DUMMYFUNCTION("""COMPUTED_VALUE"""),"Carrapateira") -> Carrapateira | C44: =IFERROR(__xludf.DUMMYFUNCTION("""COMPUTED_VALUE"""),2.5009192E7) -> 25009192 | D44: =IFERROR(__xludf.DUMMYFUNCTION("""COMPUTED_VALUE"""),"Eci EEM Joel Pereira da Silva") -> Eci EEM Joel Pereira da Silva | E44: =IFERROR(__xludf.DUMMYFUNCTION("""COMPUTED_VALUE"""),"URBANA") -> URBANA | F44: =IFERROR(__xludf.DUMMYFUNCTION("""COMPUTED_VALUE"""),"2 Mbps") -> 2 Mbps | G44: =IFERROR(__xludf.DUMMYFUNCTION("""COMPUTED_VALUE"""),"-") -> - | H44: =IFERROR(__xludf.DUMMYFUNCTION("""COMPUTED_VALUE"""),"-") -> - | I44: =IFERROR(__xludf.DUMMYFUNCTION("""COMPUTED_VALUE"""),"-") -> - | J44: =IFERROR(__xludf.DUMMYFUNCTION("""COMPUTED_VALUE"""),"-") -> - | K44: =IFERROR(__xludf.DUMMYFUNCTION("""COMPUTED_VALUE"""),"-") -> - | L44: =IFERROR(__xludf.DUMMYFUNCTION("""COMPUTED_VALUE"""),"-") -> - | M44: =IFERROR(__xludf.DUMMYFUNCTION("""COMPUTED_VALUE"""),"100 Mbps") -> 100 Mbps | N44: =IFERROR(__xludf.DUMMYFUNCTION("""COMPUTED_VALUE"""),"-") -> - | O44: =IFERROR(__xludf.DUMMYFUNCTION("""COMPUTED_VALUE"""),"-") -> -
A45: =IFERROR(__xludf.DUMMYFUNCTION("""COMPUTED_VALUE"""),"09ª GRE (Cajazeiras)") -> 09ª GRE (Cajazeiras) | B45: =IFERROR(__xludf.DUMMYFUNCTION("""COMPUTED_VALUE"""),"Carrapateira") -> Carrapateira | C45: =IFERROR(__xludf.DUMMYFUNCTION("""COMPUTED_VALUE"""),2.5009214E7) -> 25009214 | D45: =IFERROR(__xludf.DUMMYFUNCTION("""COMPUTED_VALUE"""),"EEEIF de Ave Maria") -> EEEIF de Ave Maria | E45: =IFERROR(__xludf.DUMMYFUNCTION("""COMPUTED_VALUE"""),"RURAL") -> RURAL | F45: =IFERROR(__xludf.DUMMYFUNCTION("""COMPUTED_VALUE"""),"-") -> - | G45: =IFERROR(__xludf.DUMMYFUNCTION("""COMPUTED_VALUE"""),"-") -> - | H45: =IFERROR(__xludf.DUMMYFUNCTION("""COMPUTED_VALUE"""),"-") -> - | I45: =IFERROR(__xludf.DUMMYFUNCTION("""COMPUTED_VALUE"""),"-") -> - | J45: =IFERROR(__xludf.DUMMYFUNCTION("""COMPUTED_VALUE"""),"-") -> - | K45: =IFERROR(__xludf.DUMMYFUNCTION("""COMPUTED_VALUE"""),"-") -> - | L45: =IFERROR(__xludf.DUMMYFUNCTION("""COMPUTED_VALUE"""),"-") -> - | M45: =IFERROR(__xludf.DUMMYFUNCTION("""COMPUTED_VALUE"""),"-") -> - | N45: =IFERROR(__xludf.DUMMYFUNCTION("""COMPUTED_VALUE"""),"Satélite") -> Satélite | O45: =IFERROR(__xludf.DUMMYFUNCTION("""COMPUTED_VALUE"""),"-") -> -
A46: =IFERROR(__xludf.DUMMYFUNCTION("""COMPUTED_VALUE"""),"09ª GRE (Cajazeiras)") -> 09ª GRE (Cajazeiras) | B46: =IFERROR(__xludf.DUMMYFUNCTION("""COMPUTED_VALUE"""),"Monte Horebe") -> Monte Horebe | C46: =IFERROR(__xludf.DUMMYFUNCTION("""COMPUTED_VALUE"""),2.5009559E7) -> 25009559 | D46: =IFERROR(__xludf.DUMMYFUNCTION("""COMPUTED_VALUE"""),"ECIEEFM Bonifácio Saraiva de Moura") -> ECIEEFM Bonifácio Saraiva de Moura | E46: =IFERROR(__xludf.DUMMYFUNCTION("""COMPUTED_VALUE"""),"URBANA") -> URBANA | F46: =IFERROR(__xludf.DUMMYFUNCTION("""COMPUTED_VALUE"""),"2 Mbps") -> 2 Mbps | G46: =IFERROR(__xludf.DUMMYFUNCTION("""COMPUTED_VALUE"""),"-") -> - | H46: =IFERROR(__xludf.DUMMYFUNCTION("""COMPUTED_VALUE"""),"-") -> - | I46: =IFERROR(__xludf.DUMMYFUNCTION("""COMPUTED_VALUE"""),"-") -> - | J46: =IFERROR(__xludf.DUMMYFUNCTION("""COMPUTED_VALUE"""),"-") -> - | K46: =IFERROR(__xludf.DUMMYFUNCTION("""COMPUTED_VALUE"""),"-") -> - | L46: =IFERROR(__xludf.DUMMYFUNCTION("""COMPUTED_VALUE"""),"-") -> - | M46: =IFERROR(__xludf.DUMMYFUNCTION("""COMPUTED_VALUE"""),"100 Mbps") -> 100 Mbps | N46: =IFERROR(__xludf.DUMMYFUNCTION("""COMPUTED_VALUE"""),"-") -> - | O46: =IFERROR(__xludf.DUMMYFUNCTION("""COMPUTED_VALUE"""),"-") -> -
A47: =IFERROR(__xludf.DUMMYFUNCTION("""COMPUTED_VALUE"""),"09ª GRE (Cajazeiras)") -> 09ª GRE (Cajazeiras) | B47: =IFERROR(__xludf.DUMMYFUNCTION("""COMPUTED_VALUE"""),"Santa Helena") -> Santa Helena | C47: =IFERROR(__xludf.DUMMYFUNCTION("""COMPUTED_VALUE"""),2.5009923E7) -> 25009923 | D47: =IFERROR(__xludf.DUMMYFUNCTION("""COMPUTED_VALUE"""),"EEEFM Prof Jose Bento") -> EEEFM Prof Jose Bento | E47: =IFERROR(__xludf.DUMMYFUNCTION("""COMPUTED_VALUE"""),"URBANA") -> URBANA | F47: =IFERROR(__xludf.DUMMYFUNCTION("""COMPUTED_VALUE"""),"2 Mbps") -> 2 Mbps | G47: =IFERROR(__xludf.DUMMYFUNCTION("""COMPUTED_VALUE"""),"-") -> - | H47: =IFERROR(__xludf.DUMMYFUNCTION("""COMPUTED_VALUE"""),"-") -> - | I47: =IFERROR(__xludf.DUMMYFUNCTION("""COMPUTED_VALUE"""),"-") -> - | J47: =IFERROR(__xludf.DUMMYFUNCTION("""COMPUTED_VALUE"""),"-") -> - | K47: =IFERROR(__xludf.DUMMYFUNCTION("""COMPUTED_VALUE"""),"-") -> - | L47: =IFERROR(__xludf.DUMMYFUNCTION("""COMPUTED_VALUE"""),"-") -> - | M47: =IFERROR(__xludf.DUMMYFUNCTION("""COMPUTED_VALUE"""),"100 Mbps") -> 100 Mbps | N47: =IFERROR(__xludf.DUMMYFUNCTION("""COMPUTED_VALUE"""),"-") -> - | O47: =IFERROR(__xludf.DUMMYFUNCTION("""COMPUTED_VALUE"""),"-") -> -
A48: =IFERROR(__xludf.DUMMYFUNCTION("""COMPUTED_VALUE"""),"09ª GRE (Cajazeiras)") -> 09ª GRE (Cajazeiras) | B48: =IFERROR(__xludf.DUMMYFUNCTION("""COMPUTED_VALUE"""),"Santa Helena") -> Santa Helena | C48: =IFERROR(__xludf.DUMMYFUNCTION("""COMPUTED_VALUE"""),2.5009931E7) -> 25009931 | D48: =IFERROR(__xludf.DUMMYFUNCTION("""COMPUTED_VALUE"""),"Eci Elaine Soares Brasileiro") -> Eci Elaine Soares Brasileiro | E48: =IFERROR(__xludf.DUMMYFUNCTION("""COMPUTED_VALUE"""),"URBANA") -> URBANA | F48: =IFERROR(__xludf.DUMMYFUNCTION("""COMPUTED_VALUE"""),"2 Mbps") -> 2 Mbps | G48: =IFERROR(__xludf.DUMMYFUNCTION("""COMPUTED_VALUE"""),"-") -> - | H48: =IFERROR(__xludf.DUMMYFUNCTION("""COMPUTED_VALUE"""),"-") -> - | I48: =IFERROR(__xludf.DUMMYFUNCTION("""COMPUTED_VALUE"""),"-") -> - | J48: =IFERROR(__xludf.DUMMYFUNCTION("""COMPUTED_VALUE"""),"-") -> - | K48: =IFERROR(__xludf.DUMMYFUNCTION("""COMPUTED_VALUE"""),"-") -> - | L48: =IFERROR(__xludf.DUMMYFUNCTION("""COMPUTED_VALUE"""),"-") -> - | M48: =IFERROR(__xludf.DUMMYFUNCTION("""COMPUTED_VALUE"""),"100 Mbps") -> 100 Mbps | N48: =IFERROR(__xludf.DUMMYFUNCTION("""COMPUTED_VALUE"""),"-") -> - | O48: =IFERROR(__xludf.DUMMYFUNCTION("""COMPUTED_VALUE"""),"-") -> -
A49: =IFERROR(__xludf.DUMMYFUNCTION("""COMPUTED_VALUE"""),"09ª GRE (Cajazeiras)") -> 09ª GRE (Cajazeiras) | B49: =IFERROR(__xludf.DUMMYFUNCTION("""COMPUTED_VALUE"""),"São José de Piranhas") -> São José de Piranhas | C49: =IFERROR(__xludf.DUMMYFUNCTION("""COMPUTED_VALUE"""),2.5010565E7) -> 25010565 | D49: =IFERROR(__xludf.DUMMYFUNCTION("""COMPUTED_VALUE"""),"Ecit Prefeito Joaquim Lacerda Leite") -> Ecit Prefeito Joaquim Lacerda Leite | E49: =IFERROR(__xludf.DUMMYFUNCTION("""COMPUTED_VALUE"""),"URBANA") -> URBANA | F49: =IFERROR(__xludf.DUMMYFUNCTION("""COMPUTED_VALUE"""),"5 Mbps") -> 5 Mbps | G49: =IFERROR(__xludf.DUMMYFUNCTION("""COMPUTED_VALUE"""),"-") -> - | H49: =IFERROR(__xludf.DUMMYFUNCTION("""COMPUTED_VALUE"""),"-") -> - | I49: =IFERROR(__xludf.DUMMYFUNCTION("""COMPUTED_VALUE"""),"-") -> - | J49: =IFERROR(__xludf.DUMMYFUNCTION("""COMPUTED_VALUE"""),"50 Mbps") -> 50 Mbps | K49: =IFERROR(__xludf.DUMMYFUNCTION("""COMPUTED_VALUE"""),"-") -> - | L49: =IFERROR(__xludf.DUMMYFUNCTION("""COMPUTED_VALUE"""),"-") -> - | M49: =IFERROR(__xludf.DUMMYFUNCTION("""COMPUTED_VALUE"""),"-") -> - | N49: =IFERROR(__xludf.DUMMYFUNCTION("""COMPUTED_VALUE"""),"-") -> - | O49: =IFERROR(__xludf.DUMMYFUNCTION("""COMPUTED_VALUE"""),"-") -> -
A50: =IFERROR(__xludf.DUMMYFUNCTION("""COMPUTED_VALUE"""),"-") -> - | B50: =IFERROR(__xludf.DUMMYFUNCTION("""COMPUTED_VALUE"""),"São José de Piranhas") -> São José de Piranhas | C50: =IFERROR(__xludf.DUMMYFUNCTION("""COMPUTED_VALUE"""),2.501067E7) -> 25010670 | D50: =IFERROR(__xludf.DUMMYFUNCTION("""COMPUTED_VALUE"""),"EEEF Bairro Santo Antonio") -> EEEF Bairro Santo Antonio | E50: =IFERROR(__xludf.DUMMYFUNCTION("""COMPUTED_VALUE"""),"-") -> - | F50: =IFERROR(__xludf.DUMMYFUNCTION("""COMPUTED_VALUE"""),"5 Mbps") -> 5 Mbps | G50: =IFERROR(__xludf.DUMMYFUNCTION("""COMPUTED_VALUE"""),"-") -> - | H50: =IFERROR(__xludf.DUMMYFUNCTION("""COMPUTED_VALUE"""),"-") -> - | I50: =IFERROR(__xludf.DUMMYFUNCTION("""COMPUTED_VALUE"""),"-") -> - | J50: =IFERROR(__xludf.DUMMYFUNCTION("""COMPUTED_VALUE"""),"-") -> - | K50: =IFERROR(__xludf.DUMMYFUNCTION("""COMPUTED_VALUE"""),"-") -> - | L50: =IFERROR(__xludf.DUMMYFUNCTION("""COMPUTED_VALUE"""),"-") -> - | N50: =IFERROR(__xludf.DUMMYFUNCTION("""COMPUTED_VALUE"""),"-") -> - | O50: =IFERROR(__xludf.DUMMYFUNCTION("""COMPUTED_VALUE"""),"-") -> -
A51: =IFERROR(__xludf.DUMMYFUNCTION("""COMPUTED_VALUE"""),"-") -> - | B51: =IFERROR(__xludf.DUMMYFUNCTION("""COMPUTED_VALUE"""),"São José de Piranhas") -> São José de Piranhas | C51: =IFERROR(__xludf.DUMMYFUNCTION("""COMPUTED_VALUE"""),2.5010727E7) -> 25010727 | D51: =IFERROR(__xludf.DUMMYFUNCTION("""COMPUTED_VALUE"""),"EEEF SANTA MARIA GORETE") -> EEEF SANTA MARIA GORETE | E51: =IFERROR(__xludf.DUMMYFUNCTION("""COMPUTED_VALUE"""),"-") -> - | F51: =IFERROR(__xludf.DUMMYFUNCTION("""COMPUTED_VALUE"""),"5 Mbps") -> 5 Mbps | G51: =IFERROR(__xludf.DUMMYFUNCTION("""COMPUTED_VALUE"""),"-") -> - | H51: =IFERROR(__xludf.DUMMYFUNCTION("""COMPUTED_VALUE"""),"-") -> - | I51: =IFERROR(__xludf.DUMMYFUNCTION("""COMPUTED_VALUE"""),"-") -> - | J51: =IFERROR(__xludf.DUMMYFUNCTION("""COMPUTED_VALUE"""),"-") -> - | K51: =IFERROR(__xludf.DUMMYFUNCTION("""COMPUTED_VALUE"""),"-") -> - | L51: =IFERROR(__xludf.DUMMYFUNCTION("""COMPUTED_VALUE"""),"-") -> - | N51: =IFERROR(__xludf.DUMMYFUNCTION("""COMPUTED_VALUE"""),"-") -> - | O51: =IFERROR(__xludf.DUMMYFUNCTION("""COMPUTED_VALUE"""),"-") -> -
A52: =IFERROR(__xludf.DUMMYFUNCTION("""COMPUTED_VALUE"""),"09ª GRE (Cajazeiras)") -> 09ª GRE (Cajazeiras) | B52: =IFERROR(__xludf.DUMMYFUNCTION("""COMPUTED_VALUE"""),"São José de Piranhas") -> São José de Piranhas | C52: =IFERROR(__xludf.DUMMYFUNCTION("""COMPUTED_VALUE"""),2.5011669E7) -> 25011669 | D52: =IFERROR(__xludf.DUMMYFUNCTION("""COMPUTED_VALUE"""),"E EST DE CURSO NORMAL EM NIVEL MEDIO SAO JOSE") -> E EST DE CURSO NORMAL EM NIVEL MEDIO SAO JOSE | E52: =IFERROR(__xludf.DUMMYFUNCTION("""COMPUTED_VALUE"""),"URBANA") -> URBANA | F52: =IFERROR(__xludf.DUMMYFUNCTION("""COMPUTED_VALUE"""),"5 Mbps") -> 5 Mbps | G52: =IFERROR(__xludf.DUMMYFUNCTION("""COMPUTED_VALUE"""),"-") -> - | H52: =IFERROR(__xludf.DUMMYFUNCTION("""COMPUTED_VALUE"""),"-") -> - | I52: =IFERROR(__xludf.DUMMYFUNCTION("""COMPUTED_VALUE"""),"-") -> - | J52: =IFERROR(__xludf.DUMMYFUNCTION("""COMPUTED_VALUE"""),"-") -> - | K52: =IFERROR(__xludf.DUMMYFUNCTION("""COMPUTED_VALUE"""),"-") -> - | L52: =IFERROR(__xludf.DUMMYFUNCTION("""COMPUTED_VALUE"""),"-") -> - | M52: =IFERROR(__xludf.DUMMYFUNCTION("""COMPUTED_VALUE"""),"100 Mbps") -> 100 Mbps | N52: =IFERROR(__xludf.DUMMYFUNCTION("""COMPUTED_VALUE"""),"-") -> - | O52: =IFERROR(__xludf.DUMMYFUNCTION("""COMPUTED_VALUE"""),"-") -> -
A53: =IFERROR(__xludf.DUMMYFUNCTION("""COMPUTED_VALUE"""),"09ª GRE (Cajazeiras)") -> 09ª GRE (Cajazeiras) | B53: =IFERROR(__xludf.DUMMYFUNCTION("""COMPUTED_VALUE"""),"Triunfo") -> Triunfo | C53: =IFERROR(__xludf.DUMMYFUNCTION("""COMPUTED_VALUE"""),2.5012185E7) -> 25012185 | D53: =IFERROR(__xludf.DUMMYFUNCTION("""COMPUTED_VALUE"""),"EEEF Antonio Francisco Duarte") -> EEEF Antonio Francisco Duarte | E53: =IFERROR(__xludf.DUMMYFUNCTION("""COMPUTED_VALUE"""),"URBANA") -> URBANA | F53: =IFERROR(__xludf.DUMMYFUNCTION("""COMPUTED_VALUE"""),"2 Mbps") -> 2 Mbps | G53: =IFERROR(__xludf.DUMMYFUNCTION("""COMPUTED_VALUE"""),"-") -> - | H53: =IFERROR(__xludf.DUMMYFUNCTION("""COMPUTED_VALUE"""),"-") -> - | I53: =IFERROR(__xludf.DUMMYFUNCTION("""COMPUTED_VALUE"""),"-") -> - | J53: =IFERROR(__xludf.DUMMYFUNCTION("""COMPUTED_VALUE"""),"-") -> - | K53: =IFERROR(__xludf.DUMMYFUNCTION("""COMPUTED_VALUE"""),"-") -> - | L53: =IFERROR(__xludf.DUMMYFUNCTION("""COMPUTED_VALUE"""),"-") -> - | M53: =IFERROR(__xludf.DUMMYFUNCTION("""COMPUTED_VALUE"""),"100 Mbps") -> 100 Mbps | N53: =IFERROR(__xludf.DUMMYFUNCTION("""COMPUTED_VALUE"""),"-") -> - | O53: =IFERROR(__xludf.DUMMYFUNCTION("""COMPUTED_VALUE"""),"-") -> -
A54: =IFERROR(__xludf.DUMMYFUNCTION("""COMPUTED_VALUE"""),"09ª GRE (Cajazeiras)") -> 09ª GRE (Cajazeiras) | B54: =IFERROR(__xludf.DUMMYFUNCTION("""COMPUTED_VALUE"""),"Bernardino Batista") -> Bernardino Batista | C54: =IFERROR(__xludf.DUMMYFUNCTION("""COMPUTED_VALUE"""),2.5012193E7) -> 25012193 | D54: =IFERROR(__xludf.DUMMYFUNCTION("""COMPUTED_VALUE"""),"EEEFM Nelson Batista Alves") -> EEEFM Nelson Batista Alves | E54: =IFERROR(__xludf.DUMMYFUNCTION("""COMPUTED_VALUE"""),"URBANA") -> URBANA | F54: =IFERROR(__xludf.DUMMYFUNCTION("""COMPUTED_VALUE"""),"2 Mbps") -> 2 Mbps | G54: =IFERROR(__xludf.DUMMYFUNCTION("""COMPUTED_VALUE"""),"-") -> - | H54: =IFERROR(__xludf.DUMMYFUNCTION("""COMPUTED_VALUE"""),"-") -> - | I54: =IFERROR(__xludf.DUMMYFUNCTION("""COMPUTED_VALUE"""),"-") -> - | J54: =IFERROR(__xludf.DUMMYFUNCTION("""COMPUTED_VALUE"""),"-") -> - | K54: =IFERROR(__xludf.DUMMYFUNCTION("""COMPUTED_VALUE"""),"-") -> - | L54: =IFERROR(__xludf.DUMMYFUNCTION("""COMPUTED_VALUE"""),"-") -> - | N54: =IFERROR(__xludf.DUMMYFUNCTION("""COMPUTED_VALUE"""),"-") -> - | O54: =IFERROR(__xludf.DUMMYFUNCTION("""COMPUTED_VALUE"""),"-") -> -
A55: =IFERROR(__xludf.DUMMYFUNCTION("""COMPUTED_VALUE"""),"09ª GRE (Cajazeiras)") -> 09ª GRE (Cajazeiras) | B55: =IFERROR(__xludf.DUMMYFUNCTION("""COMPUTED_VALUE"""),"Triunfo") -> Triunfo | C55: =IFERROR(__xludf.DUMMYFUNCTION("""COMPUTED_VALUE"""),2.5012207E7) -> 25012207 | D55: =IFERROR(__xludf.DUMMYFUNCTION("""COMPUTED_VALUE"""),"Eci EEM Bernardino Jose Batista") -> Eci EEM Bernardino Jose Batista | E55: =IFERROR(__xludf.DUMMYFUNCTION("""COMPUTED_VALUE"""),"URBANA") -> URBANA | F55: =IFERROR(__xludf.DUMMYFUNCTION("""COMPUTED_VALUE"""),"2 Mbps") -> 2 Mbps | G55: =IFERROR(__xludf.DUMMYFUNCTION("""COMPUTED_VALUE"""),"-") -> - | H55: =IFERROR(__xludf.DUMMYFUNCTION("""COMPUTED_VALUE"""),"-") -> - | I55: =IFERROR(__xludf.DUMMYFUNCTION("""COMPUTED_VALUE"""),"-") -> - | J55: =IFERROR(__xludf.DUMMYFUNCTION("""COMPUTED_VALUE"""),"-") -> - | K55: =IFERROR(__xludf.DUMMYFUNCTION("""COMPUTED_VALUE"""),"-") -> - | L55: =IFERROR(__xludf.DUMMYFUNCTION("""COMPUTED_VALUE"""),"-") -> - | M55: =IFERROR(__xludf.DUMMYFUNCTION("""COMPUTED_VALUE"""),"100 Mbps") -> 100 Mbps | N55: =IFERROR(__xludf.DUMMYFUNCTION("""COMPUTED_VALUE"""),"-") -> - | O55: =IFERROR(__xludf.DUMMYFUNCTION("""COMPUTED_VALUE"""),"-") -> -
A56: =IFERROR(__xludf.DUMMYFUNCTION("""COMPUTED_VALUE"""),"09ª GRE (Cajazeiras)") -> 09ª GRE (Cajazeiras) | B56: =IFERROR(__xludf.DUMMYFUNCTION("""COMPUTED_VALUE"""),"Uiraúna") -> Uiraúna | C56: =IFERROR(__xludf.DUMMYFUNCTION("""COMPUTED_VALUE"""),2.5012916E7) -> 25012916 | D56: =IFERROR(__xludf.DUMMYFUNCTION("""COMPUTED_VALUE"""),"Ecit Doutor Jose Duarte Filho") -> Ecit Doutor Jose Duarte Filho | E56: =IFERROR(__xludf.DUMMYFUNCTION("""COMPUTED_VALUE"""),"URBANA") -> URBANA | F56: =IFERROR(__xludf.DUMMYFUNCTION("""COMPUTED_VALUE"""),"2 Mbps") -> 2 Mbps | G56: =IFERROR(__xludf.DUMMYFUNCTION("""COMPUTED_VALUE"""),"-") -> - | H56: =IFERROR(__xludf.DUMMYFUNCTION("""COMPUTED_VALUE"""),"-") -> - | I56: =IFERROR(__xludf.DUMMYFUNCTION("""COMPUTED_VALUE"""),"-") -> - | J56: =IFERROR(__xludf.DUMMYFUNCTION("""COMPUTED_VALUE"""),"-") -> - | K56: =IFERROR(__xludf.DUMMYFUNCTION("""COMPUTED_VALUE"""),"-") -> - | L56: =IFERROR(__xludf.DUMMYFUNCTION("""COMPUTED_VALUE"""),"-") -> - | M56: =IFERROR(__xludf.DUMMYFUNCTION("""COMPUTED_VALUE"""),"100 Mbps") -> 100 Mbps | N56: =IFERROR(__xludf.DUMMYFUNCTION("""COMPUTED_VALUE"""),"-") -> - | O56: =IFERROR(__xludf.DUMMYFUNCTION("""COMPUTED_VALUE"""),"-") -> -
A57: =IFERROR(__xludf.DUMMYFUNCTION("""COMPUTED_VALUE"""),"09ª GRE (Cajazeiras)") -> 09ª GRE (Cajazeiras) | B57: =IFERROR(__xludf.DUMMYFUNCTION("""COMPUTED_VALUE"""),"Uiraúna") -> Uiraúna | C57: =IFERROR(__xludf.DUMMYFUNCTION("""COMPUTED_VALUE"""),2.5012924E7) -> 25012924 | D57: =IFERROR(__xludf.DUMMYFUNCTION("""COMPUTED_VALUE"""),"EEEFM Jovelina Gomes") -> EEEFM Jovelina Gomes | E57: =IFERROR(__xludf.DUMMYFUNCTION("""COMPUTED_VALUE"""),"URBANA") -> URBANA | F57: =IFERROR(__xludf.DUMMYFUNCTION("""COMPUTED_VALUE"""),"2 Mbps") -> 2 Mbps | G57: =IFERROR(__xludf.DUMMYFUNCTION("""COMPUTED_VALUE"""),"-") -> - | H57: =IFERROR(__xludf.DUMMYFUNCTION("""COMPUTED_VALUE"""),"-") -> - | I57: =IFERROR(__xludf.DUMMYFUNCTION("""COMPUTED_VALUE"""),"-") -> - | J57: =IFERROR(__xludf.DUMMYFUNCTION("""COMPUTED_VALUE"""),"-") -> - | K57: =IFERROR(__xludf.DUMMYFUNCTION("""COMPUTED_VALUE"""),"-") -> - | L57: =IFERROR(__xludf.DUMMYFUNCTION("""COMPUTED_VALUE"""),"-") -> - | M57: =IFERROR(__xludf.DUMMYFUNCTION("""COMPUTED_VALUE"""),"100 Mbps") -> 100 Mbps | N57: =IFERROR(__xludf.DUMMYFUNCTION("""COMPUTED_VALUE"""),"-") -> - | O57: =IFERROR(__xludf.DUMMYFUNCTION("""COMPUTED_VALUE"""),"-") -> -
A58: =IFERROR(__xludf.DUMMYFUNCTION("""COMPUTED_VALUE"""),"09ª GRE (Cajazeiras)") -> 09ª GRE (Cajazeiras) | B58: =IFERROR(__xludf.DUMMYFUNCTION("""COMPUTED_VALUE"""),"Joca Claudino") -> Joca Claudino | C58: =IFERROR(__xludf.DUMMYFUNCTION("""COMPUTED_VALUE"""),2.5012932E7) -> 25012932 | D58: =IFERROR(__xludf.DUMMYFUNCTION("""COMPUTED_VALUE"""),"ESCOLA ESTADUAL CIDADÃ INTEGRAL SÃO JOSÉ OPERÁRIO") -> ESCOLA ESTADUAL CIDADÃ INTEGRAL SÃO JOSÉ OPERÁRIO | E58: =IFERROR(__xludf.DUMMYFUNCTION("""COMPUTED_VALUE"""),"URBANA") -> URBANA | F58: =IFERROR(__xludf.DUMMYFUNCTION("""COMPUTED_VALUE"""),"2 Mbps") -> 2 Mbps | G58: =IFERROR(__xludf.DUMMYFUNCTION("""COMPUTED_VALUE"""),"-") -> - | H58: =IFERROR(__xludf.DUMMYFUNCTION("""COMPUTED_VALUE"""),"-") -> - | I58: =IFERROR(__xludf.DUMMYFUNCTION("""COMPUTED_VALUE"""),"-") -> - | J58: =IFERROR(__xludf.DUMMYFUNCTION("""COMPUTED_VALUE"""),"-") -> - | K58: =IFERROR(__xludf.DUMMYFUNCTION("""COMPUTED_VALUE"""),"-") -> - | L58: =IFERROR(__xludf.DUMMYFUNCTION("""COMPUTED_VALUE"""),"-") -> - | N58: =IFERROR(__xludf.DUMMYFUNCTION("""COMPUTED_VALUE"""),"-") -> - | O58: =IFERROR(__xludf.DUMMYFUNCTION("""COMPUTED_VALUE"""),"-") -> -
A59: =IFERROR(__xludf.DUMMYFUNCTION("""COMPUTED_VALUE"""),"09ª GRE (Cajazeiras)") -> 09ª GRE (Cajazeiras) | B59: =IFERROR(__xludf.DUMMYFUNCTION("""COMPUTED_VALUE"""),"Poço Dantas") -> Poço Dantas | C59: =IFERROR(__xludf.DUMMYFUNCTION("""COMPUTED_VALUE"""),2.501294E7) -> 25012940 | D59: =IFERROR(__xludf.DUMMYFUNCTION("""COMPUTED_VALUE"""),"Eci EEM Jose Nilson Santiago") -> Eci EEM Jose Nilson Santiago | E59: =IFERROR(__xludf.DUMMYFUNCTION("""COMPUTED_VALUE"""),"URBANA") -> URBANA | F59: =IFERROR(__xludf.DUMMYFUNCTION("""COMPUTED_VALUE"""),"2 Mbps") -> 2 Mbps | G59: =IFERROR(__xludf.DUMMYFUNCTION("""COMPUTED_VALUE"""),"-") -> - | H59: =IFERROR(__xludf.DUMMYFUNCTION("""COMPUTED_VALUE"""),"-") -> - | I59: =IFERROR(__xludf.DUMMYFUNCTION("""COMPUTED_VALUE"""),"-") -> - | J59: =IFERROR(__xludf.DUMMYFUNCTION("""COMPUTED_VALUE"""),"-") -> - | K59: =IFERROR(__xludf.DUMMYFUNCTION("""COMPUTED_VALUE"""),"-") -> - | L59: =IFERROR(__xludf.DUMMYFUNCTION("""COMPUTED_VALUE"""),"-") -> - | N59: =IFERROR(__xludf.DUMMYFUNCTION("""COMPUTED_VALUE"""),"-") -> - | O59: =IFERROR(__xludf.DUMMYFUNCTION("""COMPUTED_VALUE"""),"-") -> -
A60: =IFERROR(__xludf.DUMMYFUNCTION("""COMPUTED_VALUE"""),"09ª GRE (Cajazeiras)") -> 09ª GRE (Cajazeiras) | B60: =IFERROR(__xludf.DUMMYFUNCTION("""COMPUTED_VALUE"""),"Uiraúna") -> Uiraúna | C60: =IFERROR(__xludf.DUMMYFUNCTION("""COMPUTED_VALUE"""),2.5012959E7) -> 25012959 | D60: =IFERROR(__xludf.DUMMYFUNCTION("""COMPUTED_VALUE"""),"EEEF Ernani Satiro") -> EEEF Ernani Satiro | E60: =IFERROR(__xludf.DUMMYFUNCTION("""COMPUTED_VALUE"""),"URBANA") -> URBANA | F60: =IFERROR(__xludf.DUMMYFUNCTION("""COMPUTED_VALUE"""),"2 Mbps") -> 2 Mbps | G60: =IFERROR(__xludf.DUMMYFUNCTION("""COMPUTED_VALUE"""),"-") -> - | H60: =IFERROR(__xludf.DUMMYFUNCTION("""COMPUTED_VALUE"""),"-") -> - | I60: =IFERROR(__xludf.DUMMYFUNCTION("""COMPUTED_VALUE"""),"-") -> - | J60: =IFERROR(__xludf.DUMMYFUNCTION("""COMPUTED_VALUE"""),"-") -> - | K60: =IFERROR(__xludf.DUMMYFUNCTION("""COMPUTED_VALUE"""),"-") -> - | L60: =IFERROR(__xludf.DUMMYFUNCTION("""COMPUTED_VALUE"""),"-") -> - | M60: =IFERROR(__xludf.DUMMYFUNCTION("""COMPUTED_VALUE"""),"100 Mbps") -> 100 Mbps | N60: =IFERROR(__xludf.DUMMYFUNCTION("""COMPUTED_VALUE"""),"-") -> - | O60: =IFERROR(__xludf.DUMMYFUNCTION("""COMPUTED_VALUE"""),"-") -> -
A61: =IFERROR(__xludf.DUMMYFUNCTION("""COMPUTED_VALUE"""),"09ª GRE (Cajazeiras)") -> 09ª GRE (Cajazeiras) | B61: =IFERROR(__xludf.DUMMYFUNCTION("""COMPUTED_VALUE"""),"Uiraúna") -> Uiraúna | C61: =IFERROR(__xludf.DUMMYFUNCTION("""COMPUTED_VALUE"""),2.5012967E7) -> 25012967 | D61: =IFERROR(__xludf.DUMMYFUNCTION("""COMPUTED_VALUE"""),"EEEF Mons Constantino Vieira") -> EEEF Mons Constantino Vieira | E61: =IFERROR(__xludf.DUMMYFUNCTION("""COMPUTED_VALUE"""),"RURAL") -> RURAL | F61: =IFERROR(__xludf.DUMMYFUNCTION("""COMPUTED_VALUE"""),"-") -> - | G61: =IFERROR(__xludf.DUMMYFUNCTION("""COMPUTED_VALUE"""),"-") -> - | H61: =IFERROR(__xludf.DUMMYFUNCTION("""COMPUTED_VALUE"""),"-") -> - | I61: =IFERROR(__xludf.DUMMYFUNCTION("""COMPUTED_VALUE"""),"-") -> - | J61: =IFERROR(__xludf.DUMMYFUNCTION("""COMPUTED_VALUE"""),"-") -> - | K61: =IFERROR(__xludf.DUMMYFUNCTION("""COMPUTED_VALUE"""),"-") -> - | L61: =IFERROR(__xludf.DUMMYFUNCTION("""COMPUTED_VALUE"""),"-") -> - | M61: =IFERROR(__xludf.DUMMYFUNCTION("""COMPUTED_VALUE"""),"-") -> - | O61: =IFERROR(__xludf.DUMMYFUNCTION("""COMPUTED_VALUE"""),"-") -> -
A62: =IFERROR(__xludf.DUMMYFUNCTION("""COMPUTED_VALUE"""),"13ª GRE (Pombal)") -> 13ª GRE (Pombal) | B62: =IFERROR(__xludf.DUMMYFUNCTION("""COMPUTED_VALUE"""),"Condado") -> Condado | C62: =IFERROR(__xludf.DUMMYFUNCTION("""COMPUTED_VALUE"""),2.501384E7) -> 25013840 | D62: =IFERROR(__xludf.DUMMYFUNCTION("""COMPUTED_VALUE"""),"ECIT Doutor Trajano Pires da Nóbrega") -> ECIT Doutor Trajano Pires da Nóbrega | E62: =IFERROR(__xludf.DUMMYFUNCTION("""COMPUTED_VALUE"""),"URBANA") -> URBANA | F62: =IFERROR(__xludf.DUMMYFUNCTION("""COMPUTED_VALUE"""),"2 Mbps") -> 2 Mbps | G62: =IFERROR(__xludf.DUMMYFUNCTION("""COMPUTED_VALUE"""),"-") -> - | H62: =IFERROR(__xludf.DUMMYFUNCTION("""COMPUTED_VALUE"""),"-") -> - | I62: =IFERROR(__xludf.DUMMYFUNCTION("""COMPUTED_VALUE"""),"-") -> - | J62: =IFERROR(__xludf.DUMMYFUNCTION("""COMPUTED_VALUE"""),"50 Mbps") -> 50 Mbps | K62: =IFERROR(__xludf.DUMMYFUNCTION("""COMPUTED_VALUE"""),"-") -> - | L62: =IFERROR(__xludf.DUMMYFUNCTION("""COMPUTED_VALUE"""),"-") -> - | M62: =IFERROR(__xludf.DUMMYFUNCTION("""COMPUTED_VALUE"""),"-") -> - | N62: =IFERROR(__xludf.DUMMYFUNCTION("""COMPUTED_VALUE"""),"-") -> - | O62: =IFERROR(__xludf.DUMMYFUNCTION("""COMPUTED_VALUE"""),"-") -> -
A63: =IFERROR(__xludf.DUMMYFUNCTION("""COMPUTED_VALUE"""),"13ª GRE (Pombal)") -> 13ª GRE (Pombal) | B63: =IFERROR(__xludf.DUMMYFUNCTION("""COMPUTED_VALUE"""),"Vista Serrana") -> Vista Serrana | C63: =IFERROR(__xludf.DUMMYFUNCTION("""COMPUTED_VALUE"""),2.5014226E7) -> 25014226 | D63: =IFERROR(__xludf.DUMMYFUNCTION("""COMPUTED_VALUE"""),"Escola Cidadã Integral Estadual de Ensino Médio Manoel Medeiros de Araújo") -> Escola Cidadã Integral Estadual de Ensino Médio Manoel Medeiros de Araújo | E63: =IFERROR(__xludf.DUMMYFUNCTION("""COMPUTED_VALUE"""),"URBANA") -> URBANA | F63: =IFERROR(__xludf.DUMMYFUNCTION("""COMPUTED_VALUE"""),"2 Mbps") -> 2 Mbps | G63: =IFERROR(__xludf.DUMMYFUNCTION("""COMPUTED_VALUE"""),"-") -> - | H63: =IFERROR(__xludf.DUMMYFUNCTION("""COMPUTED_VALUE"""),"-") -> - | I63: =IFERROR(__xludf.DUMMYFUNCTION("""COMPUTED_VALUE"""),"-") -> - | J63: =IFERROR(__xludf.DUMMYFUNCTION("""COMPUTED_VALUE"""),"-") -> - | K63: =IFERROR(__xludf.DUMMYFUNCTION("""COMPUTED_VALUE"""),"-") -> - | L63: =IFERROR(__xludf.DUMMYFUNCTION("""COMPUTED_VALUE"""),"-") -> - | M63: =IFERROR(__xludf.DUMMYFUNCTION("""COMPUTED_VALUE"""),"100 Mbps") -> 100 Mbps | N63: =IFERROR(__xludf.DUMMYFUNCTION("""COMPUTED_VALUE"""),"-") -> - | O63: =IFERROR(__xludf.DUMMYFUNCTION("""COMPUTED_VALUE"""),"-") -> -
A64: =IFERROR(__xludf.DUMMYFUNCTION("""COMPUTED_VALUE"""),"10ª GRE (Sousa)") -> 10ª GRE (Sousa) | B64: =IFERROR(__xludf.DUMMYFUNCTION("""COMPUTED_VALUE"""),"Lastro") -> Lastro | C64: =IFERROR(__xludf.DUMMYFUNCTION("""COMPUTED_VALUE"""),2.5014412E7) -> 25014412 | D64: =IFERROR(__xludf.DUMMYFUNCTION("""COMPUTED_VALUE"""),"ECI EEM Nestorina Abrantes") -> ECI EEM Nestorina Abrantes | E64: =IFERROR(__xludf.DUMMYFUNCTION("""COMPUTED_VALUE"""),"URBANA") -> URBANA | F64: =IFERROR(__xludf.DUMMYFUNCTION("""COMPUTED_VALUE"""),"2 Mbps") -> 2 Mbps | G64: =IFERROR(__xludf.DUMMYFUNCTION("""COMPUTED_VALUE"""),"-") -> - | H64: =IFERROR(__xludf.DUMMYFUNCTION("""COMPUTED_VALUE"""),"-") -> - | I64: =IFERROR(__xludf.DUMMYFUNCTION("""COMPUTED_VALUE"""),"-") -> - | J64: =IFERROR(__xludf.DUMMYFUNCTION("""COMPUTED_VALUE"""),"-") -> - | K64: =IFERROR(__xludf.DUMMYFUNCTION("""COMPUTED_VALUE"""),"-") -> - | L64: =IFERROR(__xludf.DUMMYFUNCTION("""COMPUTED_VALUE"""),"-") -> - | M64: =IFERROR(__xludf.DUMMYFUNCTION("""COMPUTED_VALUE"""),"100 Mbps") -> 100 Mbps | N64: =IFERROR(__xludf.DUMMYFUNCTION("""COMPUTED_VALUE"""),"-") -> - | O64: =IFERROR(__xludf.DUMMYFUNCTION("""COMPUTED_VALUE"""),"-") -> -
A65: =IFERROR(__xludf.DUMMYFUNCTION("""COMPUTED_VALUE"""),"06ª GRE (Patos)") -> 06ª GRE (Patos) | B65: =IFERROR(__xludf.DUMMYFUNCTION("""COMPUTED_VALUE"""),"Malta") -> Malta | C65: =IFERROR(__xludf.DUMMYFUNCTION("""COMPUTED_VALUE"""),2.5014692E7) -> 25014692 | D65: =IFERROR(__xludf.DUMMYFUNCTION("""COMPUTED_VALUE"""),"Ecit Doutor Antonio Fernandes Medeiros") -> Ecit Doutor Antonio Fernandes Medeiros | E65: =IFERROR(__xludf.DUMMYFUNCTION("""COMPUTED_VALUE"""),"URBANA") -> URBANA | F65: =IFERROR(__xludf.DUMMYFUNCTION("""COMPUTED_VALUE"""),"2 Mbps") -> 2 Mbps | G65: =IFERROR(__xludf.DUMMYFUNCTION("""COMPUTED_VALUE"""),"-") -> - | H65: =IFERROR(__xludf.DUMMYFUNCTION("""COMPUTED_VALUE"""),"-") -> - | I65: =IFERROR(__xludf.DUMMYFUNCTION("""COMPUTED_VALUE"""),"-") -> - | J65: =IFERROR(__xludf.DUMMYFUNCTION("""COMPUTED_VALUE"""),"-") -> - | K65: =IFERROR(__xludf.DUMMYFUNCTION("""COMPUTED_VALUE"""),"-") -> - | L65: =IFERROR(__xludf.DUMMYFUNCTION("""COMPUTED_VALUE"""),"-") -> - | M65: =IFERROR(__xludf.DUMMYFUNCTION("""COMPUTED_VALUE"""),"100 Mbps") -> 100 Mbps | N65: =IFERROR(__xludf.DUMMYFUNCTION("""COMPUTED_VALUE"""),"-") -> - | O65: =IFERROR(__xludf.DUMMYFUNCTION("""COMPUTED_VALUE"""),"-") -> -
A66: =IFERROR(__xludf.DUMMYFUNCTION("""COMPUTED_VALUE"""),"10ª GRE (Sousa)") -> 10ª GRE (Sousa) | B66: =IFERROR(__xludf.DUMMYFUNCTION("""COMPUTED_VALUE"""),"Nazarezinho") -> Nazarezinho | C66: =IFERROR(__xludf.DUMMYFUNCTION("""COMPUTED_VALUE"""),2.5014951E7) -> 25014951 | D66: =IFERROR(__xludf.DUMMYFUNCTION("""COMPUTED_VALUE"""),"ECIEEM Francisco Augusto Campos") -> ECIEEM Francisco Augusto Campos | E66: =IFERROR(__xludf.DUMMYFUNCTION("""COMPUTED_VALUE"""),"URBANA") -> URBANA | F66: =IFERROR(__xludf.DUMMYFUNCTION("""COMPUTED_VALUE"""),"2 Mbps") -> 2 Mbps | G66: =IFERROR(__xludf.DUMMYFUNCTION("""COMPUTED_VALUE"""),"-") -> - | H66: =IFERROR(__xludf.DUMMYFUNCTION("""COMPUTED_VALUE"""),"-") -> - | I66: =IFERROR(__xludf.DUMMYFUNCTION("""COMPUTED_VALUE"""),"-") -> - | J66: =IFERROR(__xludf.DUMMYFUNCTION("""COMPUTED_VALUE"""),"-") -> - | K66: =IFERROR(__xludf.DUMMYFUNCTION("""COMPUTED_VALUE"""),"-") -> - | L66: =IFERROR(__xludf.DUMMYFUNCTION("""COMPUTED_VALUE"""),"-") -> - | N66: =IFERROR(__xludf.DUMMYFUNCTION("""COMPUTED_VALUE"""),"-") -> - | O66: =IFERROR(__xludf.DUMMYFUNCTION("""COMPUTED_VALUE"""),"-") -> -
A67: =IFERROR(__xludf.DUMMYFUNCTION("""COMPUTED_VALUE"""),"10ª GRE (Sousa)") -> 10ª GRE (Sousa) | B67: =IFERROR(__xludf.DUMMYFUNCTION("""COMPUTED_VALUE"""),"Nazarezinho") -> Nazarezinho | C67: =IFERROR(__xludf.DUMMYFUNCTION("""COMPUTED_VALUE"""),2.501496E7) -> 25014960 | D67: =IFERROR(__xludf.DUMMYFUNCTION("""COMPUTED_VALUE"""),"EEEF Manoel Mendes") -> EEEF Manoel Mendes | E67: =IFERROR(__xludf.DUMMYFUNCTION("""COMPUTED_VALUE"""),"URBANA") -> URBANA | F67: =IFERROR(__xludf.DUMMYFUNCTION("""COMPUTED_VALUE"""),"2 Mbps") -> 2 Mbps | G67: =IFERROR(__xludf.DUMMYFUNCTION("""COMPUTED_VALUE"""),"-") -> - | H67: =IFERROR(__xludf.DUMMYFUNCTION("""COMPUTED_VALUE"""),"-") -> - | I67: =IFERROR(__xludf.DUMMYFUNCTION("""COMPUTED_VALUE"""),"-") -> - | J67: =IFERROR(__xludf.DUMMYFUNCTION("""COMPUTED_VALUE"""),"-") -> - | K67: =IFERROR(__xludf.DUMMYFUNCTION("""COMPUTED_VALUE"""),"-") -> - | L67: =IFERROR(__xludf.DUMMYFUNCTION("""COMPUTED_VALUE"""),"-") -> - | N67: =IFERROR(__xludf.DUMMYFUNCTION("""COMPUTED_VALUE"""),"-") -> - | O67: =IFERROR(__xludf.DUMMYFUNCTION("""COMPUTED_VALUE"""),"-") -> -
A68: =IFERROR(__xludf.DUMMYFUNCTION("""COMPUTED_VALUE"""),"13ª GRE (Pombal)") -> 13ª GRE (Pombal) | B68: =IFERROR(__xludf.DUMMYFUNCTION("""COMPUTED_VALUE"""),"Paulista") -> Paulista | C68: =IFERROR(__xludf.DUMMYFUNCTION("""COMPUTED_VALUE"""),2.501532E7) -> 25015320 | D68: =IFERROR(__xludf.DUMMYFUNCTION("""COMPUTED_VALUE"""),"ECIT EST FRANCISCO DE SÁ CAVALCANTE") -> ECIT EST FRANCISCO DE SÁ CAVALCANTE | E68: =IFERROR(__xludf.DUMMYFUNCTION("""COMPUTED_VALUE"""),"URBANA") -> URBANA | F68: =IFERROR(__xludf.DUMMYFUNCTION("""COMPUTED_VALUE"""),"2 Mbps") -> 2 Mbps | G68: =IFERROR(__xludf.DUMMYFUNCTION("""COMPUTED_VALUE"""),"-") -> - | H68: =IFERROR(__xludf.DUMMYFUNCTION("""COMPUTED_VALUE"""),"-") -> - | I68: =IFERROR(__xludf.DUMMYFUNCTION("""COMPUTED_VALUE"""),"-") -> - | J68: =IFERROR(__xludf.DUMMYFUNCTION("""COMPUTED_VALUE"""),"-") -> - | K68: =IFERROR(__xludf.DUMMYFUNCTION("""COMPUTED_VALUE"""),"-") -> - | L68: =IFERROR(__xludf.DUMMYFUNCTION("""COMPUTED_VALUE"""),"-") -> - | M68: =IFERROR(__xludf.DUMMYFUNCTION("""COMPUTED_VALUE"""),"100 Mbps") -> 100 Mbps | N68: =IFERROR(__xludf.DUMMYFUNCTION("""COMPUTED_VALUE"""),"-") -> - | O68: =IFERROR(__xludf.DUMMYFUNCTION("""COMPUTED_VALUE"""),"-") -> -
A69: =IFERROR(__xludf.DUMMYFUNCTION("""COMPUTED_VALUE"""),"13ª GRE (Pombal)") -> 13ª GRE (Pombal) | B69: =IFERROR(__xludf.DUMMYFUNCTION("""COMPUTED_VALUE"""),"Pombal") -> Pombal | C69: =IFERROR(__xludf.DUMMYFUNCTION("""COMPUTED_VALUE"""),2.5015869E7) -> 25015869 | D69: =IFERROR(__xludf.DUMMYFUNCTION("""COMPUTED_VALUE"""),"ECITEEFM Monsenhor Vicente Freitas") -> ECITEEFM Monsenhor Vicente Freitas | E69: =IFERROR(__xludf.DUMMYFUNCTION("""COMPUTED_VALUE"""),"URBANA") -> URBANA | F69: =IFERROR(__xludf.DUMMYFUNCTION("""COMPUTED_VALUE"""),"2 Mbps") -> 2 Mbps | G69: =IFERROR(__xludf.DUMMYFUNCTION("""COMPUTED_VALUE"""),"-") -> - | H69: =IFERROR(__xludf.DUMMYFUNCTION("""COMPUTED_VALUE"""),"-") -> - | I69: =IFERROR(__xludf.DUMMYFUNCTION("""COMPUTED_VALUE"""),"-") -> - | J69: =IFERROR(__xludf.DUMMYFUNCTION("""COMPUTED_VALUE"""),"30 Mbps") -> 30 Mbps | K69: =IFERROR(__xludf.DUMMYFUNCTION("""COMPUTED_VALUE"""),"-") -> - | L69: =IFERROR(__xludf.DUMMYFUNCTION("""COMPUTED_VALUE"""),"-") -> - | M69: =IFERROR(__xludf.DUMMYFUNCTION("""COMPUTED_VALUE"""),"-") -> - | N69: =IFERROR(__xludf.DUMMYFUNCTION("""COMPUTED_VALUE"""),"-") -> - | O69: =IFERROR(__xludf.DUMMYFUNCTION("""COMPUTED_VALUE"""),"-") -> -
A70: =IFERROR(__xludf.DUMMYFUNCTION("""COMPUTED_VALUE"""),"13ª GRE (Pombal)") -> 13ª GRE (Pombal) | B70: =IFERROR(__xludf.DUMMYFUNCTION("""COMPUTED_VALUE"""),"Pombal") -> Pombal | C70: =IFERROR(__xludf.DUMMYFUNCTION("""COMPUTED_VALUE"""),2.5015885E7) -> 25015885 | D70: =IFERROR(__xludf.DUMMYFUNCTION("""COMPUTED_VALUE"""),"EEEFM João da Mata") -> EEEFM João da Mata | E70: =IFERROR(__xludf.DUMMYFUNCTION("""COMPUTED_VALUE"""),"URBANA") -> URBANA | F70: =IFERROR(__xludf.DUMMYFUNCTION("""COMPUTED_VALUE"""),"2 Mbps") -> 2 Mbps | G70: =IFERROR(__xludf.DUMMYFUNCTION("""COMPUTED_VALUE"""),"-") -> - | H70: =IFERROR(__xludf.DUMMYFUNCTION("""COMPUTED_VALUE"""),"-") -> - | I70: =IFERROR(__xludf.DUMMYFUNCTION("""COMPUTED_VALUE"""),"-") -> - | J70: =IFERROR(__xludf.DUMMYFUNCTION("""COMPUTED_VALUE"""),"-") -> - | K70: =IFERROR(__xludf.DUMMYFUNCTION("""COMPUTED_VALUE"""),"-") -> - | L70: =IFERROR(__xludf.DUMMYFUNCTION("""COMPUTED_VALUE"""),"-") -> - | M70: =IFERROR(__xludf.DUMMYFUNCTION("""COMPUTED_VALUE"""),"100 Mbps") -> 100 Mbps | N70: =IFERROR(__xludf.DUMMYFUNCTION("""COMPUTED_VALUE"""),"-") -> - | O70: =IFERROR(__xludf.DUMMYFUNCTION("""COMPUTED_VALUE"""),"-") -> -
A71: =IFERROR(__xludf.DUMMYFUNCTION("""COMPUTED_VALUE"""),"13ª GRE (Pombal)") -> 13ª GRE (Pombal) | B71: =IFERROR(__xludf.DUMMYFUNCTION("""COMPUTED_VALUE"""),"Pombal") -> Pombal | C71: =IFERROR(__xludf.DUMMYFUNCTION("""COMPUTED_VALUE"""),2.5015893E7) -> 25015893 | D71: =IFERROR(__xludf.DUMMYFUNCTION("""COMPUTED_VALUE"""),"EEEFM Arruda Câmara") -> EEEFM Arruda Câmara | E71: =IFERROR(__xludf.DUMMYFUNCTION("""COMPUTED_VALUE"""),"URBANA") -> URBANA | F71: =IFERROR(__xludf.DUMMYFUNCTION("""COMPUTED_VALUE"""),"2 Mbps") -> 2 Mbps | G71: =IFERROR(__xludf.DUMMYFUNCTION("""COMPUTED_VALUE"""),"-") -> - | H71: =IFERROR(__xludf.DUMMYFUNCTION("""COMPUTED_VALUE"""),"-") -> - | I71: =IFERROR(__xludf.DUMMYFUNCTION("""COMPUTED_VALUE"""),"-") -> - | J71: =IFERROR(__xludf.DUMMYFUNCTION("""COMPUTED_VALUE"""),"-") -> - | K71: =IFERROR(__xludf.DUMMYFUNCTION("""COMPUTED_VALUE"""),"-") -> - | L71: =IFERROR(__xludf.DUMMYFUNCTION("""COMPUTED_VALUE"""),"-") -> - | M71: =IFERROR(__xludf.DUMMYFUNCTION("""COMPUTED_VALUE"""),"100 Mbps") -> 100 Mbps | N71: =IFERROR(__xludf.DUMMYFUNCTION("""COMPUTED_VALUE"""),"-") -> - | O71: =IFERROR(__xludf.DUMMYFUNCTION("""COMPUTED_VALUE"""),"-") -> -
A72: =IFERROR(__xludf.DUMMYFUNCTION("""COMPUTED_VALUE"""),"13ª GRE (Pombal)") -> 13ª GRE (Pombal) | B72: =IFERROR(__xludf.DUMMYFUNCTION("""COMPUTED_VALUE"""),"Pombal") -> Pombal | C72: =IFERROR(__xludf.DUMMYFUNCTION("""COMPUTED_VALUE"""),2.5016024E7) -> 25016024 | D72: =IFERROR(__xludf.DUMMYFUNCTION("""COMPUTED_VALUE"""),"EEEF Oito de Julho") -> EEEF Oito de Julho | E72: =IFERROR(__xludf.DUMMYFUNCTION("""COMPUTED_VALUE"""),"URBANA") -> URBANA | F72: =IFERROR(__xludf.DUMMYFUNCTION("""COMPUTED_VALUE"""),"2 Mbps") -> 2 Mbps | G72: =IFERROR(__xludf.DUMMYFUNCTION("""COMPUTED_VALUE"""),"-") -> - | H72: =IFERROR(__xludf.DUMMYFUNCTION("""COMPUTED_VALUE"""),"-") -> - | I72: =IFERROR(__xludf.DUMMYFUNCTION("""COMPUTED_VALUE"""),"-") -> - | J72: =IFERROR(__xludf.DUMMYFUNCTION("""COMPUTED_VALUE"""),"-") -> - | K72: =IFERROR(__xludf.DUMMYFUNCTION("""COMPUTED_VALUE"""),"-") -> - | L72: =IFERROR(__xludf.DUMMYFUNCTION("""COMPUTED_VALUE"""),"-") -> - | M72: =IFERROR(__xludf.DUMMYFUNCTION("""COMPUTED_VALUE"""),"100 Mbps") -> 100 Mbps | N72: =IFERROR(__xludf.DUMMYFUNCTION("""COMPUTED_VALUE"""),"-") -> - | O72: =IFERROR(__xludf.DUMMYFUNCTION("""COMPUTED_VALUE"""),"-") -> -
A73: =IFERROR(__xludf.DUMMYFUNCTION("""COMPUTED_VALUE"""),"13ª GRE (Pombal)") -> 13ª GRE (Pombal) | B73: =IFERROR(__xludf.DUMMYFUNCTION("""COMPUTED_VALUE"""),"Pombal") -> Pombal | C73: =IFERROR(__xludf.DUMMYFUNCTION("""COMPUTED_VALUE"""),2.5016032E7) -> 25016032 | D73: =IFERROR(__xludf.DUMMYFUNCTION("""COMPUTED_VALUE"""),"EEEF Amelia Maria da Luz") -> EEEF Amelia Maria da Luz | E73: =IFERROR(__xludf.DUMMYFUNCTION("""COMPUTED_VALUE"""),"URBANA") -> URBANA | F73: =IFERROR(__xludf.DUMMYFUNCTION("""COMPUTED_VALUE"""),"2 Mbps") -> 2 Mbps | G73: =IFERROR(__xludf.DUMMYFUNCTION("""COMPUTED_VALUE"""),"-") -> - | H73: =IFERROR(__xludf.DUMMYFUNCTION("""COMPUTED_VALUE"""),"-") -> - | I73: =IFERROR(__xludf.DUMMYFUNCTION("""COMPUTED_VALUE"""),"-") -> - | J73: =IFERROR(__xludf.DUMMYFUNCTION("""COMPUTED_VALUE"""),"-") -> - | K73: =IFERROR(__xludf.DUMMYFUNCTION("""COMPUTED_VALUE"""),"-") -> - | L73: =IFERROR(__xludf.DUMMYFUNCTION("""COMPUTED_VALUE"""),"-") -> - | M73: =IFERROR(__xludf.DUMMYFUNCTION("""COMPUTED_VALUE"""),"100 Mbps") -> 100 Mbps | N73: =IFERROR(__xludf.DUMMYFUNCTION("""COMPUTED_VALUE"""),"-") -> - | O73: =IFERROR(__xludf.DUMMYFUNCTION("""COMPUTED_VALUE"""),"-") -> -
A74: =IFERROR(__xludf.DUMMYFUNCTION("""COMPUTED_VALUE"""),"13ª GRE (Pombal)") -> 13ª GRE (Pombal) | B74: =IFERROR(__xludf.DUMMYFUNCTION("""COMPUTED_VALUE"""),"Cajazeirinhas") -> Cajazeirinhas | C74: =IFERROR(__xludf.DUMMYFUNCTION("""COMPUTED_VALUE"""),2.5016059E7) -> 25016059 | D74: =IFERROR(__xludf.DUMMYFUNCTION("""COMPUTED_VALUE"""),"EEEFM MARIA SOLEDADE ASSIS FREITAS") -> EEEFM MARIA SOLEDADE ASSIS FREITAS | E74: =IFERROR(__xludf.DUMMYFUNCTION("""COMPUTED_VALUE"""),"URBANA") -> URBANA | F74: =IFERROR(__xludf.DUMMYFUNCTION("""COMPUTED_VALUE"""),"2 Mbps") -> 2 Mbps | G74: =IFERROR(__xludf.DUMMYFUNCTION("""COMPUTED_VALUE"""),"-") -> - | H74: =IFERROR(__xludf.DUMMYFUNCTION("""COMPUTED_VALUE"""),"-") -> - | I74: =IFERROR(__xludf.DUMMYFUNCTION("""COMPUTED_VALUE"""),"-") -> - | J74: =IFERROR(__xludf.DUMMYFUNCTION("""COMPUTED_VALUE"""),"-") -> - | K74: =IFERROR(__xludf.DUMMYFUNCTION("""COMPUTED_VALUE"""),"-") -> - | L74: =IFERROR(__xludf.DUMMYFUNCTION("""COMPUTED_VALUE"""),"-") -> - | M74: =IFERROR(__xludf.DUMMYFUNCTION("""COMPUTED_VALUE"""),"100 Mbps") -> 100 Mbps | N74: =IFERROR(__xludf.DUMMYFUNCTION("""COMPUTED_VALUE"""),"-") -> - | O74: =IFERROR(__xludf.DUMMYFUNCTION("""COMPUTED_VALUE"""),"-") -> -
A75: =IFERROR(__xludf.DUMMYFUNCTION("""COMPUTED_VALUE"""),"13ª GRE (Pombal)") -> 13ª GRE (Pombal) | B75: =IFERROR(__xludf.DUMMYFUNCTION("""COMPUTED_VALUE"""),"Pombal") -> Pombal | C75: =IFERROR(__xludf.DUMMYFUNCTION("""COMPUTED_VALUE"""),2.5016075E7) -> 25016075 | D75: =IFERROR(__xludf.DUMMYFUNCTION("""COMPUTED_VALUE"""),"EEEF de Estrelo") -> EEEF de Estrelo | E75: =IFERROR(__xludf.DUMMYFUNCTION("""COMPUTED_VALUE"""),"RURAL") -> RURAL | F75: =IFERROR(__xludf.DUMMYFUNCTION("""COMPUTED_VALUE"""),"-") -> - | G75: =IFERROR(__xludf.DUMMYFUNCTION("""COMPUTED_VALUE"""),"-") -> - | H75: =IFERROR(__xludf.DUMMYFUNCTION("""COMPUTED_VALUE"""),"-") -> - | I75: =IFERROR(__xludf.DUMMYFUNCTION("""COMPUTED_VALUE"""),"-") -> - | J75: =IFERROR(__xludf.DUMMYFUNCTION("""COMPUTED_VALUE"""),"-") -> - | K75: =IFERROR(__xludf.DUMMYFUNCTION("""COMPUTED_VALUE"""),"-") -> - | L75: =IFERROR(__xludf.DUMMYFUNCTION("""COMPUTED_VALUE"""),"-") -> - | M75: =IFERROR(__xludf.DUMMYFUNCTION("""COMPUTED_VALUE"""),"-") -> - | N75: =IFERROR(__xludf.DUMMYFUNCTION("""COMPUTED_VALUE"""),"Black Box (3G)") -> Black Box (3G) | O75: =IFERROR(__xludf.DUMMYFUNCTION("""COMPUTED_VALUE"""),"-") -> -
A76: =IFERROR(__xludf.DUMMYFUNCTION("""COMPUTED_VALUE"""),"13ª GRE (Pombal)") -> 13ª GRE (Pombal) | B76: =IFERROR(__xludf.DUMMYFUNCTION("""COMPUTED_VALUE"""),"São Bentinho") -> São Bentinho | C76: =IFERROR(__xludf.DUMMYFUNCTION("""COMPUTED_VALUE"""),2.5016105E7) -> 25016105 | D76: =IFERROR(__xludf.DUMMYFUNCTION("""COMPUTED_VALUE"""),"ECI Deputado Levi Olímpio Ferreira") -> ECI Deputado Levi Olímpio Ferreira | E76: =IFERROR(__xludf.DUMMYFUNCTION("""COMPUTED_VALUE"""),"URBANA") -> URBANA | F76: =IFERROR(__xludf.DUMMYFUNCTION("""COMPUTED_VALUE"""),"2 Mbps") -> 2 Mbps | G76: =IFERROR(__xludf.DUMMYFUNCTION("""COMPUTED_VALUE"""),"-") -> - | H76: =IFERROR(__xludf.DUMMYFUNCTION("""COMPUTED_VALUE"""),"-") -> - | I76: =IFERROR(__xludf.DUMMYFUNCTION("""COMPUTED_VALUE"""),"-") -> - | J76: =IFERROR(__xludf.DUMMYFUNCTION("""COMPUTED_VALUE"""),"-") -> - | K76: =IFERROR(__xludf.DUMMYFUNCTION("""COMPUTED_VALUE"""),"-") -> - | L76: =IFERROR(__xludf.DUMMYFUNCTION("""COMPUTED_VALUE"""),"-") -> - | M76: =IFERROR(__xludf.DUMMYFUNCTION("""COMPUTED_VALUE"""),"100 Mbps") -> 100 Mbps | N76: =IFERROR(__xludf.DUMMYFUNCTION("""COMPUTED_VALUE"""),"-") -> - | O76: =IFERROR(__xludf.DUMMYFUNCTION("""COMPUTED_VALUE"""),"-") -> -
A77: =IFERROR(__xludf.DUMMYFUNCTION("""COMPUTED_VALUE"""),"13ª GRE (Pombal)") -> 13ª GRE (Pombal) | B77: =IFERROR(__xludf.DUMMYFUNCTION("""COMPUTED_VALUE"""),"São Domingos") -> São Domingos | C77: =IFERROR(__xludf.DUMMYFUNCTION("""COMPUTED_VALUE"""),2.5016164E7) -> 25016164 | D77: =IFERROR(__xludf.DUMMYFUNCTION("""COMPUTED_VALUE"""),"Ecit Cicero Severo Lopes") -> Ecit Cicero Severo Lopes | E77: =IFERROR(__xludf.DUMMYFUNCTION("""COMPUTED_VALUE"""),"URBANA") -> URBANA | F77: =IFERROR(__xludf.DUMMYFUNCTION("""COMPUTED_VALUE"""),"2 Mbps") -> 2 Mbps | G77: =IFERROR(__xludf.DUMMYFUNCTION("""COMPUTED_VALUE"""),"10 Mbps") -> 10 Mbps | H77: =IFERROR(__xludf.DUMMYFUNCTION("""COMPUTED_VALUE"""),"-") -> - | I77: =IFERROR(__xludf.DUMMYFUNCTION("""COMPUTED_VALUE"""),"-") -> - | J77: =IFERROR(__xludf.DUMMYFUNCTION("""COMPUTED_VALUE"""),"-") -> - | K77: =IFERROR(__xludf.DUMMYFUNCTION("""COMPUTED_VALUE"""),"-") -> - | L77: =IFERROR(__xludf.DUMMYFUNCTION("""COMPUTED_VALUE"""),"-") -> - | M77: =IFERROR(__xludf.DUMMYFUNCTION("""COMPUTED_VALUE"""),"-") -> - | N77: =IFERROR(__xludf.DUMMYFUNCTION("""COMPUTED_VALUE"""),"-") -> - | O77: =IFERROR(__xludf.DUMMYFUNCTION("""COMPUTED_VALUE"""),"-") -> -
A78: =IFERROR(__xludf.DUMMYFUNCTION("""COMPUTED_VALUE"""),"10ª GRE (Sousa)") -> 10ª GRE (Sousa) | B78: =IFERROR(__xludf.DUMMYFUNCTION("""COMPUTED_VALUE"""),"Santa Cruz") -> Santa Cruz | C78: =IFERROR(__xludf.DUMMYFUNCTION("""COMPUTED_VALUE"""),2.5017071E7) -> 25017071 | D78: =IFERROR(__xludf.DUMMYFUNCTION("""COMPUTED_VALUE"""),"EEEF Prof Nestor Antunes") -> EEEF Prof Nestor Antunes | E78: =IFERROR(__xludf.DUMMYFUNCTION("""COMPUTED_VALUE"""),"URBANA") -> URBANA | F78: =IFERROR(__xludf.DUMMYFUNCTION("""COMPUTED_VALUE"""),"2 Mbps") -> 2 Mbps | G78: =IFERROR(__xludf.DUMMYFUNCTION("""COMPUTED_VALUE"""),"-") -> - | H78: =IFERROR(__xludf.DUMMYFUNCTION("""COMPUTED_VALUE"""),"-") -> - | I78: =IFERROR(__xludf.DUMMYFUNCTION("""COMPUTED_VALUE"""),"-") -> - | J78: =IFERROR(__xludf.DUMMYFUNCTION("""COMPUTED_VALUE"""),"-") -> - | K78: =IFERROR(__xludf.DUMMYFUNCTION("""COMPUTED_VALUE"""),"-") -> - | L78: =IFERROR(__xludf.DUMMYFUNCTION("""COMPUTED_VALUE"""),"-") -> - | M78: =IFERROR(__xludf.DUMMYFUNCTION("""COMPUTED_VALUE"""),"100 Mbps") -> 100 Mbps | N78: =IFERROR(__xludf.DUMMYFUNCTION("""COMPUTED_VALUE"""),"-") -> - | O78: =IFERROR(__xludf.DUMMYFUNCTION("""COMPUTED_VALUE"""),"-") -> -
A79: =IFERROR(__xludf.DUMMYFUNCTION("""COMPUTED_VALUE"""),"10ª GRE (Sousa)") -> 10ª GRE (Sousa) | B79: =IFERROR(__xludf.DUMMYFUNCTION("""COMPUTED_VALUE"""),"Santa Cruz") -> Santa Cruz | C79: =IFERROR(__xludf.DUMMYFUNCTION("""COMPUTED_VALUE"""),2.501708E7) -> 25017080 | D79: =IFERROR(__xludf.DUMMYFUNCTION("""COMPUTED_VALUE"""),"ECIT EEFM Valdemiro Wanderley de Oliveira") -> ECIT EEFM Valdemiro Wanderley de Oliveira | E79: =IFERROR(__xludf.DUMMYFUNCTION("""COMPUTED_VALUE"""),"URBANA") -> URBANA | F79: =IFERROR(__xludf.DUMMYFUNCTION("""COMPUTED_VALUE"""),"2 Mbps") -> 2 Mbps | G79: =IFERROR(__xludf.DUMMYFUNCTION("""COMPUTED_VALUE"""),"-") -> - | H79: =IFERROR(__xludf.DUMMYFUNCTION("""COMPUTED_VALUE"""),"-") -> - | I79: =IFERROR(__xludf.DUMMYFUNCTION("""COMPUTED_VALUE"""),"-") -> - | J79: =IFERROR(__xludf.DUMMYFUNCTION("""COMPUTED_VALUE"""),"-") -> - | K79: =IFERROR(__xludf.DUMMYFUNCTION("""COMPUTED_VALUE"""),"-") -> - | L79: =IFERROR(__xludf.DUMMYFUNCTION("""COMPUTED_VALUE"""),"-") -> - | M79: =IFERROR(__xludf.DUMMYFUNCTION("""COMPUTED_VALUE"""),"100 Mbps") -> 100 Mbps | N79: =IFERROR(__xludf.DUMMYFUNCTION("""COMPUTED_VALUE"""),"-") -> - | O79: =IFERROR(__xludf.DUMMYFUNCTION("""COMPUTED_VALUE"""),"-") -> -
A80: =IFERROR(__xludf.DUMMYFUNCTION("""COMPUTED_VALUE"""),"10ª GRE (Sousa)") -> 10ª GRE (Sousa) | B80: =IFERROR(__xludf.DUMMYFUNCTION("""COMPUTED_VALUE"""),"São José da Lagoa Tapada") -> São José da Lagoa Tapada | C80: =IFERROR(__xludf.DUMMYFUNCTION("""COMPUTED_VALUE"""),2.5017438E7) -> 25017438 | D80: =IFERROR(__xludf.DUMMYFUNCTION("""COMPUTED_VALUE"""),"ECI EEEFM Antonio Gregorio de Lacerda") -> ECI EEEFM Antonio Gregorio de Lacerda | E80: =IFERROR(__xludf.DUMMYFUNCTION("""COMPUTED_VALUE"""),"URBANA") -> URBANA | F80: =IFERROR(__xludf.DUMMYFUNCTION("""COMPUTED_VALUE"""),"2 Mbps") -> 2 Mbps | G80: =IFERROR(__xludf.DUMMYFUNCTION("""COMPUTED_VALUE"""),"-") -> - | H80: =IFERROR(__xludf.DUMMYFUNCTION("""COMPUTED_VALUE"""),"-") -> - | I80: =IFERROR(__xludf.DUMMYFUNCTION("""COMPUTED_VALUE"""),"-") -> - | J80: =IFERROR(__xludf.DUMMYFUNCTION("""COMPUTED_VALUE"""),"-") -> - | K80: =IFERROR(__xludf.DUMMYFUNCTION("""COMPUTED_VALUE"""),"-") -> - | L80: =IFERROR(__xludf.DUMMYFUNCTION("""COMPUTED_VALUE"""),"-") -> - | N80: =IFERROR(__xludf.DUMMYFUNCTION("""COMPUTED_VALUE"""),"-") -> - | O80: =IFERROR(__xludf.DUMMYFUNCTION("""COMPUTED_VALUE"""),"-") -> -
A81: =IFERROR(__xludf.DUMMYFUNCTION("""COMPUTED_VALUE"""),"10ª GRE (Sousa)") -> 10ª GRE (Sousa) | B81: =IFERROR(__xludf.DUMMYFUNCTION("""COMPUTED_VALUE"""),"Sousa") -> Sousa | C81: =IFERROR(__xludf.DUMMYFUNCTION("""COMPUTED_VALUE"""),2.501806E7) -> 25018060 | D81: =IFERROR(__xludf.DUMMYFUNCTION("""COMPUTED_VALUE"""),"EEEFM Izidra Pacifico de Araujo") -> EEEFM Izidra Pacifico de Araujo | E81: =IFERROR(__xludf.DUMMYFUNCTION("""COMPUTED_VALUE"""),"RURAL") -> RURAL | F81: =IFERROR(__xludf.DUMMYFUNCTION("""COMPUTED_VALUE"""),"-") -> - | G81: =IFERROR(__xludf.DUMMYFUNCTION("""COMPUTED_VALUE"""),"-") -> - | H81: =IFERROR(__xludf.DUMMYFUNCTION("""COMPUTED_VALUE"""),"-") -> - | I81: =IFERROR(__xludf.DUMMYFUNCTION("""COMPUTED_VALUE"""),"-") -> - | J81: =IFERROR(__xludf.DUMMYFUNCTION("""COMPUTED_VALUE"""),"-") -> - | K81: =IFERROR(__xludf.DUMMYFUNCTION("""COMPUTED_VALUE"""),"-") -> - | L81: =IFERROR(__xludf.DUMMYFUNCTION("""COMPUTED_VALUE"""),"-") -> - | M81: =IFERROR(__xludf.DUMMYFUNCTION("""COMPUTED_VALUE"""),"-") -> - | N81: =IFERROR(__xludf.DUMMYFUNCTION("""COMPUTED_VALUE"""),"Black Box (3G)") -> Black Box (3G) | O81: =IFERROR(__xludf.DUMMYFUNCTION("""COMPUTED_VALUE"""),"-") -> -
A82: =IFERROR(__xludf.DUMMYFUNCTION("""COMPUTED_VALUE"""),"10ª GRE (Sousa)") -> 10ª GRE (Sousa) | B82: =IFERROR(__xludf.DUMMYFUNCTION("""COMPUTED_VALUE"""),"Sousa") -> Sousa | C82: =IFERROR(__xludf.DUMMYFUNCTION("""COMPUTED_VALUE"""),2.5018078E7) -> 25018078 | D82: =IFERROR(__xludf.DUMMYFUNCTION("""COMPUTED_VALUE"""),"EEEF Andre Gadelha") -> EEEF Andre Gadelha | E82: =IFERROR(__xludf.DUMMYFUNCTION("""COMPUTED_VALUE"""),"URBANA") -> URBANA | F82: =IFERROR(__xludf.DUMMYFUNCTION("""COMPUTED_VALUE"""),"5 Mbps") -> 5 Mbps | G82: =IFERROR(__xludf.DUMMYFUNCTION("""COMPUTED_VALUE"""),"-") -> - | H82: =IFERROR(__xludf.DUMMYFUNCTION("""COMPUTED_VALUE"""),"-") -> - | I82: =IFERROR(__xludf.DUMMYFUNCTION("""COMPUTED_VALUE"""),"-") -> - | J82: =IFERROR(__xludf.DUMMYFUNCTION("""COMPUTED_VALUE"""),"-") -> - | K82: =IFERROR(__xludf.DUMMYFUNCTION("""COMPUTED_VALUE"""),"-") -> - | L82: =IFERROR(__xludf.DUMMYFUNCTION("""COMPUTED_VALUE"""),"-") -> - | M82: =IFERROR(__xludf.DUMMYFUNCTION("""COMPUTED_VALUE"""),"100 Mbps") -> 100 Mbps | N82: =IFERROR(__xludf.DUMMYFUNCTION("""COMPUTED_VALUE"""),"-") -> - | O82: =IFERROR(__xludf.DUMMYFUNCTION("""COMPUTED_VALUE"""),"-") -> -
A83: =IFERROR(__xludf.DUMMYFUNCTION("""COMPUTED_VALUE"""),"10ª GRE (Sousa)") -> 10ª GRE (Sousa) | B83: =IFERROR(__xludf.DUMMYFUNCTION("""COMPUTED_VALUE"""),"Aparecida") -> Aparecida | C83: =IFERROR(__xludf.DUMMYFUNCTION("""COMPUTED_VALUE"""),2.5018094E7) -> 25018094 | D83: =IFERROR(__xludf.DUMMYFUNCTION("""COMPUTED_VALUE"""),"ECI EEFM Dr Jose Gadelha") -> ECI EEFM Dr Jose Gadelha | E83: =IFERROR(__xludf.DUMMYFUNCTION("""COMPUTED_VALUE"""),"URBANA") -> URBANA | F83: =IFERROR(__xludf.DUMMYFUNCTION("""COMPUTED_VALUE"""),"2 Mbps") -> 2 Mbps | G83: =IFERROR(__xludf.DUMMYFUNCTION("""COMPUTED_VALUE"""),"-") -> - | H83: =IFERROR(__xludf.DUMMYFUNCTION("""COMPUTED_VALUE"""),"-") -> - | I83: =IFERROR(__xludf.DUMMYFUNCTION("""COMPUTED_VALUE"""),"-") -> - | J83: =IFERROR(__xludf.DUMMYFUNCTION("""COMPUTED_VALUE"""),"-") -> - | K83: =IFERROR(__xludf.DUMMYFUNCTION("""COMPUTED_VALUE"""),"-") -> - | L83: =IFERROR(__xludf.DUMMYFUNCTION("""COMPUTED_VALUE"""),"-") -> - | M83: =IFERROR(__xludf.DUMMYFUNCTION("""COMPUTED_VALUE"""),"100 Mbps") -> 100 Mbps | N83: =IFERROR(__xludf.DUMMYFUNCTION("""COMPUTED_VALUE"""),"-") -> - | O83: =IFERROR(__xludf.DUMMYFUNCTION("""COMPUTED_VALUE"""),"-") -> -
A84: =IFERROR(__xludf.DUMMYFUNCTION("""COMPUTED_VALUE"""),"10ª GRE (Sousa)") -> 10ª GRE (Sousa) | B84: =IFERROR(__xludf.DUMMYFUNCTION("""COMPUTED_VALUE"""),"Sousa") -> Sousa | C84: =IFERROR(__xludf.DUMMYFUNCTION("""COMPUTED_VALUE"""),2.5018124E7) -> 25018124 | D84: =IFERROR(__xludf.DUMMYFUNCTION("""COMPUTED_VALUE"""),"EEEF Batista Leite") -> EEEF Batista Leite | E84: =IFERROR(__xludf.DUMMYFUNCTION("""COMPUTED_VALUE"""),"URBANA") -> URBANA | F84: =IFERROR(__xludf.DUMMYFUNCTION("""COMPUTED_VALUE"""),"5 Mbps") -> 5 Mbps | G84: =IFERROR(__xludf.DUMMYFUNCTION("""COMPUTED_VALUE"""),"-") -> - | H84: =IFERROR(__xludf.DUMMYFUNCTION("""COMPUTED_VALUE"""),"-") -> - | I84: =IFERROR(__xludf.DUMMYFUNCTION("""COMPUTED_VALUE"""),"-") -> - | J84: =IFERROR(__xludf.DUMMYFUNCTION("""COMPUTED_VALUE"""),"-") -> - | K84: =IFERROR(__xludf.DUMMYFUNCTION("""COMPUTED_VALUE"""),"-") -> - | L84: =IFERROR(__xludf.DUMMYFUNCTION("""COMPUTED_VALUE"""),"-") -> - | M84: =IFERROR(__xludf.DUMMYFUNCTION("""COMPUTED_VALUE"""),"100 Mbps") -> 100 Mbps | N84: =IFERROR(__xludf.DUMMYFUNCTION("""COMPUTED_VALUE"""),"-") -> - | O84: =IFERROR(__xludf.DUMMYFUNCTION("""COMPUTED_VALUE"""),"-") -> -
A85: =IFERROR(__xludf.DUMMYFUNCTION("""COMPUTED_VALUE"""),"10ª GRE (Sousa)") -> 10ª GRE (Sousa) | B85: =IFERROR(__xludf.DUMMYFUNCTION("""COMPUTED_VALUE"""),"Sousa") -> Sousa | C85: =IFERROR(__xludf.DUMMYFUNCTION("""COMPUTED_VALUE"""),2.5018132E7) -> 25018132 | D85: =IFERROR(__xludf.DUMMYFUNCTION("""COMPUTED_VALUE"""),"EEEF Bento Freire") -> EEEF Bento Freire | E85: =IFERROR(__xludf.DUMMYFUNCTION("""COMPUTED_VALUE"""),"URBANA") -> URBANA | F85: =IFERROR(__xludf.DUMMYFUNCTION("""COMPUTED_VALUE"""),"5 Mbps") -> 5 Mbps | G85: =IFERROR(__xludf.DUMMYFUNCTION("""COMPUTED_VALUE"""),"-") -> - | H85: =IFERROR(__xludf.DUMMYFUNCTION("""COMPUTED_VALUE"""),"-") -> - | I85: =IFERROR(__xludf.DUMMYFUNCTION("""COMPUTED_VALUE"""),"-") -> - | J85: =IFERROR(__xludf.DUMMYFUNCTION("""COMPUTED_VALUE"""),"-") -> - | K85: =IFERROR(__xludf.DUMMYFUNCTION("""COMPUTED_VALUE"""),"-") -> - | L85: =IFERROR(__xludf.DUMMYFUNCTION("""COMPUTED_VALUE"""),"-") -> - | M85: =IFERROR(__xludf.DUMMYFUNCTION("""COMPUTED_VALUE"""),"100 Mbps") -> 100 Mbps | N85: =IFERROR(__xludf.DUMMYFUNCTION("""COMPUTED_VALUE"""),"-") -> - | O85: =IFERROR(__xludf.DUMMYFUNCTION("""COMPUTED_VALUE"""),"-") -> -
A86: =IFERROR(__xludf.DUMMYFUNCTION("""COMPUTED_VALUE"""),"10ª GRE (Sousa)") -> 10ª GRE (Sousa) | B86: =IFERROR(__xludf.DUMMYFUNCTION("""COMPUTED_VALUE"""),"Sousa") -> Sousa | C86: =IFERROR(__xludf.DUMMYFUNCTION("""COMPUTED_VALUE"""),2.501814E7) -> 25018140 | D86: =IFERROR(__xludf.DUMMYFUNCTION("""COMPUTED_VALUE"""),"EEEFM Celso Mariz") -> EEEFM Celso Mariz | E86: =IFERROR(__xludf.DUMMYFUNCTION("""COMPUTED_VALUE"""),"URBANA") -> URBANA | F86: =IFERROR(__xludf.DUMMYFUNCTION("""COMPUTED_VALUE"""),"2 Mbps") -> 2 Mbps | G86: =IFERROR(__xludf.DUMMYFUNCTION("""COMPUTED_VALUE"""),"-") -> - | H86: =IFERROR(__xludf.DUMMYFUNCTION("""COMPUTED_VALUE"""),"-") -> - | I86: =IFERROR(__xludf.DUMMYFUNCTION("""COMPUTED_VALUE"""),"-") -> - | J86: =IFERROR(__xludf.DUMMYFUNCTION("""COMPUTED_VALUE"""),"50 Mbps") -> 50 Mbps | K86: =IFERROR(__xludf.DUMMYFUNCTION("""COMPUTED_VALUE"""),"-") -> - | L86: =IFERROR(__xludf.DUMMYFUNCTION("""COMPUTED_VALUE"""),"-") -> - | M86: =IFERROR(__xludf.DUMMYFUNCTION("""COMPUTED_VALUE"""),"-") -> - | N86: =IFERROR(__xludf.DUMMYFUNCTION("""COMPUTED_VALUE"""),"-") -> - | O86: =IFERROR(__xludf.DUMMYFUNCTION("""COMPUTED_VALUE"""),"-") -> -
A87: =IFERROR(__xludf.DUMMYFUNCTION("""COMPUTED_VALUE"""),"10ª GRE (Sousa)") -> 10ª GRE (Sousa) | B87: =IFERROR(__xludf.DUMMYFUNCTION("""COMPUTED_VALUE"""),"Sousa") -> Sousa | C87: =IFERROR(__xludf.DUMMYFUNCTION("""COMPUTED_VALUE"""),2.5018183E7) -> 25018183 | D87: =IFERROR(__xludf.DUMMYFUNCTION("""COMPUTED_VALUE"""),"EEEFM Estevam Marinho") -> EEEFM Estevam Marinho | E87: =IFERROR(__xludf.DUMMYFUNCTION("""COMPUTED_VALUE"""),"RURAL") -> RURAL | F87: =IFERROR(__xludf.DUMMYFUNCTION("""COMPUTED_VALUE"""),"-") -> - | G87: =IFERROR(__xludf.DUMMYFUNCTION("""COMPUTED_VALUE"""),"-") -> - | H87: =IFERROR(__xludf.DUMMYFUNCTION("""COMPUTED_VALUE"""),"-") -> - | I87: =IFERROR(__xludf.DUMMYFUNCTION("""COMPUTED_VALUE"""),"-") -> - | J87: =IFERROR(__xludf.DUMMYFUNCTION("""COMPUTED_VALUE"""),"-") -> - | K87: =IFERROR(__xludf.DUMMYFUNCTION("""COMPUTED_VALUE"""),"-") -> - | L87: =IFERROR(__xludf.DUMMYFUNCTION("""COMPUTED_VALUE"""),"-") -> - | M87: =IFERROR(__xludf.DUMMYFUNCTION("""COMPUTED_VALUE"""),"-") -> - | ... O87: =IFERROR(__xludf.DUMMYFUNCTION("""COMPUTED_VALUE"""),"-") -> -
A88: =IFERROR(__xludf.DUMMYFUNCTION("""COMPUTED_VALUE"""),"10ª GRE (Sousa)") -> 10ª GRE (Sousa) | B88: =IFERROR(__xludf.DUMMYFUNCTION("""COMPUTED_VALUE"""),"Sousa") -> Sousa | C88: =IFERROR(__xludf.DUMMYFUNCTION("""COMPUTED_VALUE"""),2.5018191E7) -> 25018191 | D88: =IFERROR(__xludf.DUMMYFUNCTION("""COMPUTED_VALUE"""),"EEEFM Francisco Cicero Sobrinho") -> EEEFM Francisco Cicero Sobrinho | E88: =IFERROR(__xludf.DUMMYFUNCTION("""COMPUTED_VALUE"""),"RURAL") -> RURAL | F88: =IFERROR(__xludf.DUMMYFUNCTION("""COMPUTED_VALUE"""),"-") -> - | G88: =IFERROR(__xludf.DUMMYFUNCTION("""COMPUTED_VALUE"""),"-") -> - | H88: =IFERROR(__xludf.DUMMYFUNCTION("""COMPUTED_VALUE"""),"-") -> - | I88: =IFERROR(__xludf.DUMMYFUNCTION("""COMPUTED_VALUE"""),"-") -> - | J88: =IFERROR(__xludf.DUMMYFUNCTION("""COMPUTED_VALUE"""),"-") -> - | K88: =IFERROR(__xludf.DUMMYFUNCTION("""COMPUTED_VALUE"""),"-") -> - | L88: =IFERROR(__xludf.DUMMYFUNCTION("""COMPUTED_VALUE"""),"-") -> - | M88: =IFERROR(__xludf.DUMMYFUNCTION("""COMPUTED_VALUE"""),"-") -> - | N88: =IFERROR(__xludf.DUMMYFUNCTION("""COMPUTED_VALUE"""),"Black Box (3G)") -> Black Box (3G) | O88: =IFERROR(__xludf.DUMMYFUNCTION("""COMPUTED_VALUE"""),"-") -> -
